Workbook

Sheet Leia-me
B2: Grupo Meridiano Varejo Ltda
B3: Dataset financeiro sintetico e integrado | Base de conhecimento para o Agente Expert em Financas
B5: 1. Objetivo
B6: Este arquivo e um conjunto de dados financeiros completo e internamente consistente, criado para alimentar e testar o Agente Expert em Financas da Draiven. Ele simula as tres demonstracoes contabeis de um grupo varejista consolidado ao longo de 36 meses (jan/2025 a dez/2027), com todos os indicadores que um especialista senior de FP&A analisaria: margens, liquidez, ciclo de conversao de caixa, endividamento, ROIC, cenarios e sensibilidade.
B8: 2. Entidade simulada
B9: Grupo Meridiano Varejo Ltda (entidade ficticia) e um grupo consolidado com cinco unidades de negocio: Materiais de Construcao, Utilidades Domesticas, Papelaria e Impressao, Servicos Automotivos e Vestuario. Cada unidade tem perfil proprio de margem, sazonalidade, prazos e crescimento.
B11: 3. Procedencia dos dados
B12: Receita 2025 e 2026 | C12: Real. Derivada de notas fiscais agregadas por mes e por unidade (linha de topo verdadeira). Sao as celulas de receita e impostos em azul na aba DRE_por_UN.
B13: Projecao 2027 | C13: Modelada. Cada mes de 2027 parte do mesmo mes de 2026 e aplica o crescimento por unidade definido em Premissas.
B14: Custos, balanco e fluxo | C14: Sinteticos. CMV, folha, ocupacao, capital de giro, imobilizado, divida, impostos e dividendos sao modelados a partir dos drivers em Premissas. Nenhum custo real foi usado.
B16: 4. Estrutura das abas
B17: Premissas | C17: Painel de controle. Todos os inputs ajustaveis (celulas azuis): parametros globais, saldos de abertura, drivers por unidade, aging e multiplicadores de cenario.
B18: DRE_Consolidado | C18: Demonstracao de resultado mensal consolidada, com totais anuais 2025 a 2027.
B19: Balanco_Consolidado | C19: Balanco patrimonial mensal. A ultima linha (Checagem) confirma que Ativo = Passivo + PL em todos os meses (deve ser zero).
B20: DFC_Consolidado | C20: Fluxo de caixa pelo metodo indireto, conciliado linha a linha com o balanco.
B21: KPIs_Mensais | C21: Vinte indicadores por mes: margens, crescimento, DSO/DIO/DPO, ciclo de caixa, liquidez, divida liquida/EBITDA, cobertura de juros, ROIC e geracao de caixa.
B22: Cenarios | C22: Resultado de 2027 sob tres cenarios (Conservador, Base, Otimista) a partir dos multiplicadores em Premissas.
B23: Sensibilidade | C23: Dois grids 2D: EBITDA e Lucro Liquido de 2027 variando crescimento, margem bruta e custos.
B24: DRE_por_UN | C24: Espinha dorsal (formato tidy). Resultado ate EBITDA por unidade e por mes. Fonte de todas as agregacoes.
B25: Headcount_Folha | C25: Quadro de pessoal e folha (com encargos) por unidade e mes.
B26: Estoque | C26: Estoque, giro e DIO por unidade e mes.
B27: Contas_Receber | C27: Contas a receber, DSO e aging por unidade e mes.
B28: Contas_Pagar | C28: Contas a pagar, DPO e aging por unidade e mes.
... B30: CMV_Custos_Produto | C30: Referencia de custo e margem por produto, com precos medios reais das notas fiscais.
B32: 5. Dinamicas embutidas (gabarito para validar o agente)
B33: O dataset contem padroes intencionais e conhecidos. Um agente de financas competente deve identifica-los. Use esta lista como gabarito ao avaliar as analises geradas:
B34: Rentabilidade declinante | C34: Receita cresce todo ano, mas EBITDA e margem liquida caem (margem EBITDA ~8,6% em 2025 para ~5,6% em 2027). O agente deve notar que crescimento nao virou lucro.
B35: Compressao de margem | C35: Utilidades Domesticas, a maior unidade em volume, tem margem bruta caindo de 38% (2025) para 32% (2027). E o principal motor da queda de rentabilidade.
B36: Deterioracao de capital de giro | C36: DSO consolidado sobe de ~21 para ~26 dias e o ciclo de conversao de caixa se alonga, pressionando o caixa operacional.
B37: Sazonalidade | C37: Vestuario concentra vendas em novembro e dezembro. Meses de janeiro sao fracos e chegam a gerar prejuizo pontual.
B38: Ciclo de capex | C38: Ha uma reforma de lojas concentrada entre junho e agosto de 2025, visivel no fluxo de investimento.
B39: Posicao de caixa liquido | C39: O grupo mantem mais caixa do que divida (divida liquida negativa), entao multiplos como Divida Liquida/EBITDA aparecem negativos por construcao.
B41: 6. Convencoes
B42: Azul | C42: Input ajustavel pelo usuario.
B43: Preto | C43: Formula calculada dentro da propria aba.
B44: Verde | C44: Formula que busca dados de outra aba.
B45: Moeda em Reais (R$), sem casas decimais. Percentuais e dias com uma casa. Multiplos com "x".
B47: 7. Como usar
B48: Altere qualquer celula azul na aba Premissas (ou no Cronograma da linha de capital de giro) e recalcule a planilha. Todo o modelo, incluindo balanco, fluxo de caixa e KPIs, se atualiza. Os cenarios e a sensibilidade sao sobrepostos analiticos sobre 2027 e nao alteram o modelo mensal principal, que representa o caso Base.
B50: 8. Integridade do modelo
B51: Modelo de tres demonstracoes totalmente integrado e sem referencias circulares. Os juros sao calculados sobre os saldos de abertura de cada mes (divida e caixa do mes anterior), o que quebra o classico laco juros-caixa-lucro. O balanco fecha exatamente (diferenca zero) em todos os 36 meses, e a planilha nao possui erros de formula.
B53: 9. Limitacoes
B54: Dados sinteticos para fins de demonstracao e teste. Nao representam uma empresa real nem seu desempenho. As premissas de custo, capital de giro e estrutura de capital foram calibradas para plausibilidade, nao para precisao setorial. A projecao de 2027 e ilustrativa e sensivel as premissas.
B56: 10. Aviso
B57: Grupo Meridiano Varejo Ltda e uma entidade ficticia. Este material nao constitui aconselhamento fiscal, contabil, juridico ou de investimento. Numeros tributarios sao simplificacoes e nao refletem a legislacao vigente em nenhuma jurisdicao especifica.
B59: Gerado para Draiven Technology | Base de conhecimento do Agente Expert em Financas

Sheet Premissas
A1: PREMISSAS E DRIVERS DO MODELO
A2: Grupo Meridiano Varejo Ltda (entidade sintetica) | Todas as celulas azuis sao inputs ajustaveis
A4: PARAMETROS GLOBAIS
A5: IR/CSLL - aliquota efetiva sobre LAIR | B5: 0.34
A6: Taxa de juros da divida (% a.m.) | B6: 0.016
A7: Taxa de rendimento do caixa (% a.m.) | B7: 0.009
A8: Overhead corporativo / G&A (R$ / mes, base 2025) | B8: 8000
A9: Reajuste anual do overhead corporativo | B9: 0.06
A10: Capex de manutencao (% da receita liquida) | B10: 0.015
A11: Vida util media do imobilizado (meses) | B11: 120
A12: Payout de dividendos (% do lucro do ano anterior) | B12: 0.3
A13: Outros ativos circulantes (% receita liquida do mes) | B13: 0.08
A14: Outros passivos circulantes (% receita liquida do mes) | B14: 0.1
A15: Provisoes trabalhistas (% da folha do mes) | B15: 0.4
A17: SALDOS DE ABERTURA (Dez/2024)
A18: Contas a receber - abertura | B18: 130000
A19: Estoques - abertura | B19: 180000
A20: Outros ativos circulantes - abertura | B20: 16000
A21: Imobilizado bruto - abertura | B21: 500000
A22: Depreciacao acumulada - abertura | B22: 120000
A23: Intangivel liquido - abertura | B23: 40000
A24: Fornecedores - abertura | B24: 150000
A25: Obrigacoes fiscais - abertura | B25: 95000
A26: Obrigacoes trabalhistas - abertura | B26: 15000
A27: Outros passivos circulantes - abertura | B27: 20000
A28: Emprestimo termo - saldo abertura | B28: 250000
A29: Linha capital de giro - saldo abertura | B29: 80000
... A34: Amortizacao mensal do emprestimo termo (R$) | B34: 5000
A35: Caixa e equivalentes - abertura (PLUG p/ balancear) | B35: =(Premissas!$B$24+Premissas!$B$30+Premissas!$B$25+Premissas!$B$26+Premissas!$B$27+Premissas!$B$31+Premissas!$B$32+Premissas!$B$33)-(Premissas!$B$18+Premissas!$B$19+Premissas!$B$20+(Premissas!$B$21-Premissas!$B$22)+Premissas!$B$23) -> 464000
A37: Capex de expansao (reforma de lojas) - total R$ 90k em Jun-Ago/2025
A38: Capex expansao por mes (Jun,Jul,Ago 2025) | B38: 30000
A40: DISTRIBUICAO DE AGING (Contas a Receber e Pagar)
A41: Faixa | B41: A vencer | C41: 1-30 dias | D41: 31-60 dias | E41: 61-90 dias | F41: > 90 dias
A42: % da carteira | B42: 0.7 | C42: 0.15 | D42: 0.08 | E42: 0.04 | F42: 0.03
A44: CENARIOS (aplicados na projecao 2027 - aba Cenarios)
A45: Cenario | B45: Mult. crescimento | C45: Delta margem (p.p.) | D45: Mult. opex var.
A46: Conservador | B46: 0.5 | C46: -0.02 | D46: 1.04
A47: Base | B47: 1 | C47: 0 | D47: 1
A48: Otimista | B48: 1.5 | C48: 0.015 | D48: 0.97
A50: DRIVERS POR UNIDADE DE NEGOCIO
A51: Unidade de Negocio | B51: Margem Bruta 2025 | C51: Margem Bruta 2026 | D51: Margem Bruta 2027 | E51: Aliq. imposto s/vendas 2027 | F51: Cresc. receita 2027 (base) | G51: Marketing (% rec.liq) | H51: Frete/Log (% rec.liq) | I51: Outras diretas (% rec.liq) | J51: Aluguel mensal (R$) | K51: Reajuste aluguel a.a. | L51: DSO 2025 | M51: DSO 2026 | N51: DSO 2027 | O51: DIO (dias) | P51: DPO (dias)
A52: Materiais de Construcao | B52: 0.3 | C52: 0.3 | D52: 0.3 | E52: 0.3973 | F52: 0.08 | G52: 0.015 | H52: 0.04 | I52: 0.02 | J52: 2000 | K52: 0.045 | L52: 25 | M52: 25 | N52: 25 | O52: 50 | P52: 40
A53: Utilidades Domesticas | B53: 0.38 | C53: 0.34 | D53: 0.32 | E53: 0.3441 | F53: 0.05 | G53: 0.02 | H53: 0.035 | I53: 0.02 | J53: 3000 | K53: 0.045 | L53: 8 | M53: 12 | N53: 18 | O53: 55 | P53: 45
A54: Papelaria e Impressao | B54: 0.42 | C54: 0.42 | D54: 0.42 | E54: 0.3941 | F54: 0.1 | G54: 0.025 | H54: 0.02 | I54: 0.025 | J54: 1000 | K54: 0.045 | L54: 45 | M54: 50 | N54: 55 | O54: 45 | P54: 30
A55: Servicos Automotivos | B55: 0.46 | C55: 0.46 | D55: 0.47 | E55: 0.2432 | F55: 0.09 | G55: 0.02 | H55: 0.015 | I55: 0.02 | J55: 2500 | K55: 0.045 | L55: 15 | M55: 15 | N55: 15 | O55: 40 | P55: 35
A56: Vestuario | B56: 0.52 | C56: 0.53 | D56: 0.53 | E56: 0.3148 | F56: 0.07 | G56: 0.03 | H56: 0.025 | I56: 0.02 | J56: 3000 | K56: 0.045 | L56: 30 | M56: 32 | N56: 35 | O56: 60 | P56: 50

Sheet DRE_Consolidado
A1: DRE CONSOLIDADO - Grupo Meridiano Varejo (mensal, R$)
A2: Linha | C2: 2025-01 | D2: 2025-02 | E2: 2025-03 | F2: 2025-04 | G2: 2025-05 | H2: 2025-06 | I2: 2025-07 | J2: 2025-08 | K2: 2025-09 | L2: 2025-10 | M2: 2025-11 | N2: 2025-12 | O2: 2026-01 | P2: 2026-02 | Q2: 2026-03 | R2: 2026-04 | S2: 2026-05 | T2: 2026-06 | U2: 2026-07 | V2: 2026-08 | W2: 2026-09 | X2: 2026-10 | Y2: 2026-11 | Z2: 2026-12 | AA2: 2027-01 | AB2: 2027-02 | AC2: 2027-03 | AD2: 2027-04 | AE2: 2027-05 | AF2: 2027-06 | AG2: 2027-07 | AH2: 2027-08 | AI2: 2027-09 | AJ2: 2027-10 | AK2: 2027-11 | AL2: 2027-12 | AN2: 2025 | AO2: 2026 | AP2: 2027
C3: 2025 | D3: 2025 | E3: 2025 | F3: 2025 | G3: 2025 | H3: 2025 | I3: 2025 | J3: 2025 | K3: 2025 | L3: 2025 | M3: 2025 | N3: 2025 | O3: 2026 | P3: 2026 | Q3: 2026 | R3: 2026 | S3: 2026 | T3: 2026 | U3: 2026 | V3: 2026 | W3: 2026 | X3: 2026 | Y3: 2026 | Z3: 2026 | AA3: 2027 | AB3: 2027 | AC3: 2027 | AD3: 2027 | AE3: 2027 | AF3: 2027 | AG3: 2027 | AH3: 2027 | AI3: 2027 | AJ3: 2027 | AK3: 2027 | AL3: 2027 | AN3: Total | AO3: Total | AP3: Total
A4: Receita Bruta | C4: =SUMIFS(DRE_por_UN!$F:$F,DRE_por_UN!$C:$C,C$2) -> 261382.1 | D4: =SUMIFS(DRE_por_UN!$F:$F,DRE_por_UN!$C:$C,D$2) -> 250904.51 | E4: =SUMIFS(DRE_por_UN!$F:$F,DRE_por_UN!$C:$C,E$2) -> 277234.2 | F4: =SUMIFS(DRE_por_UN!$F:$F,DRE_por_UN!$C:$C,F$2) -> 280943.75 | G4: =SUMIFS(DRE_por_UN!$F:$F,DRE_por_UN!$C:$C,G$2) -> 285858.47 | H4: =SUMIFS(DRE_por_UN!$F:$F,DRE_por_UN!$C:$C,H$2) -> 311626.4 | I4: =SUMIFS(DRE_por_UN!$F:$F,DRE_por_UN!$C:$C,I$2) -> 314185.58 | J4: =SUMIFS(DRE_por_UN!$F:$F,DRE_por_UN!$C:$C,J$2) -> 276259.76 | ... AL4: =SUMIFS(DRE_por_UN!$F:$F,DRE_por_UN!$C:$C,AL$2) -> 426285.15 | AN4: =SUMIF($C$3:$AL$3,2025,$C4:$AL4) -> 3574762.7 | AO4: =SUMIF($C$3:$AL$3,2026,$C4:$AL4) -> 3763378.7 | AP4: =SUMIF($C$3:$AL$3,2027,$C4:$AL4) -> 4032546.8
A5: (-) Impostos sobre Vendas | C5: =-SUMIFS(DRE_por_UN!$G:$G,DRE_por_UN!$C:$C,C$2) -> -86466.46 | D5: =-SUMIFS(DRE_por_UN!$G:$G,DRE_por_UN!$C:$C,D$2) -> -80445.58 | E5: =-SUMIFS(DRE_por_UN!$G:$G,DRE_por_UN!$C:$C,E$2) -> -90609.13 | F5: =-SUMIFS(DRE_por_UN!$G:$G,DRE_por_UN!$C:$C,F$2) -> -89539.31 | G5: =-SUMIFS(DRE_por_UN!$G:$G,DRE_por_UN!$C:$C,G$2) -> -92063.98 | H5: =-SUMIFS(DRE_por_UN!$G:$G,DRE_por_UN!$C:$C,H$2) -> -101067.89 | I5: =-SUMIFS(DRE_por_UN!$G:$G,DRE_por_UN!$C:$C,I$2) -> -100997.11 | J5: =-SUMIFS(DRE_por_UN!$G:$G,DRE_por_UN!$C:$C,J$2) -> -88389.26 | ... AL5: =-SUMIFS(DRE_por_UN!$G:$G,DRE_por_UN!$C:$C,AL$2) -> -138084.05 | AN5: =SUMIF($C$3:$AL$3,2025,$C5:$AL5) -> -1156384.7 | AO5: =SUMIF($C$3:$AL$3,2026,$C5:$AL5) -> -1206831.2 | AP5: =SUMIF($C$3:$AL$3,2027,$C5:$AL5) -> -1311306.5
A6: Receita Liquida | C6: =C4+C5 -> 174915.64 | D6: =D4+D5 -> 170458.93 | E6: =E4+E5 -> 186625.07 | F6: =F4+F5 -> 191404.44 | G6: =G4+G5 -> 193794.49 | H6: =H4+H5 -> 210558.51 | I6: =I4+I5 -> 213188.47 | J6: =J4+J5 -> 187870.5 | ... AL6: =AL4+AL5 -> 288201.1 | AN6: =SUMIF($C$3:$AL$3,2025,$C6:$AL6) -> 2418378 | AO6: =SUMIF($C$3:$AL$3,2026,$C6:$AL6) -> 2556547.5 | AP6: =SUMIF($C$3:$AL$3,2027,$C6:$AL6) -> 2721240.3
A7: (-) CMV | C7: =-SUMIFS(DRE_por_UN!$J:$J,DRE_por_UN!$C:$C,C$2) -> -97086.387 | D7: =-SUMIFS(DRE_por_UN!$J:$J,DRE_por_UN!$C:$C,D$2) -> -95557.916 | E7: =-SUMIFS(DRE_por_UN!$J:$J,DRE_por_UN!$C:$C,E$2) -> -103385.47 | F7: =-SUMIFS(DRE_por_UN!$J:$J,DRE_por_UN!$C:$C,F$2) -> -105861.73 | G7: =-SUMIFS(DRE_por_UN!$J:$J,DRE_por_UN!$C:$C,G$2) -> -108114.01 | H7: =-SUMIFS(DRE_por_UN!$J:$J,DRE_por_UN!$C:$C,H$2) -> -118057.96 | I7: =-SUMIFS(DRE_por_UN!$J:$J,DRE_por_UN!$C:$C,I$2) -> -119272.14 | J7: =-SUMIFS(DRE_por_UN!$J:$J,DRE_por_UN!$C:$C,J$2) -> -104540.97 | ... AL7: =-SUMIFS(DRE_por_UN!$J:$J,DRE_por_UN!$C:$C,AL$2) -> -163050.32 | AN7: =SUMIF($C$3:$AL$3,2025,$C7:$AL7) -> -1346276.9 | AO7: =SUMIF($C$3:$AL$3,2026,$C7:$AL7) -> -1436488 | AP7: =SUMIF($C$3:$AL$3,2027,$C7:$AL7) -> -1533792.9
A8: Lucro Bruto | C8: =C6+C7 -> 77829.253 | D8: =D6+D7 -> 74901.014 | E8: =E6+E7 -> 83239.596 | F8: =F6+F7 -> 85542.711 | G8: =G6+G7 -> 85680.48 | H8: =H6+H7 -> 92500.555 | I8: =I6+I7 -> 93916.328 | J8: =J6+J7 -> 83329.526 | ... AL8: =AL6+AL7 -> 125150.78 | AN8: =SUMIF($C$3:$AL$3,2025,$C8:$AL8) -> 1072101.1 | AO8: =SUMIF($C$3:$AL$3,2026,$C8:$AL8) -> 1120059.5 | AP8: =SUMIF($C$3:$AL$3,2027,$C8:$AL8) -> 1187447.4
A9: Margem Bruta % | C9: =IF(C6=0,0,C8/C6) -> 0.44495308 | D9: =IF(D6=0,0,D8/D6) -> 0.43940798 | E9: =IF(E6=0,0,E8/E6) -> 0.4460258 | F9: =IF(F6=0,0,F8/F6) -> 0.44692125 | G9: =IF(G6=0,0,G8/G6) -> 0.44212031 | H9: =IF(H6=0,0,H8/H6) -> 0.43931046 | I9: =IF(I6=0,0,I8/I6) -> 0.44053193 | J9: =IF(J6=0,0,J8/J6) -> 0.44354769 | ... AL9: =IF(AL6=0,0,AL8/AL6) -> 0.43424809 | AN9: =IF(AN6=0,0,AN8/AN6) -> 0.44331412 | AO9: =IF(AO6=0,0,AO8/AO6) -> 0.4381141 | AP9: =IF(AP6=0,0,AP8/AP6) -> 0.43636255
A10: (-) Folha Direta | C10: =-SUMIFS(DRE_por_UN!$L:$L,DRE_por_UN!$C:$C,C$2) -> -38136 | D10: =-SUMIFS(DRE_por_UN!$L:$L,DRE_por_UN!$C:$C,D$2) -> -38136 | E10: =-SUMIFS(DRE_por_UN!$L:$L,DRE_por_UN!$C:$C,E$2) -> -38136 | F10: =-SUMIFS(DRE_por_UN!$L:$L,DRE_por_UN!$C:$C,F$2) -> -38136 | G10: =-SUMIFS(DRE_por_UN!$L:$L,DRE_por_UN!$C:$C,G$2) -> -38136 | H10: =-SUMIFS(DRE_por_UN!$L:$L,DRE_por_UN!$C:$C,H$2) -> -38136 | I10: =-SUMIFS(DRE_por_UN!$L:$L,DRE_por_UN!$C:$C,I$2) -> -38136 | J10: =-SUMIFS(DRE_por_UN!$L:$L,DRE_por_UN!$C:$C,J$2) -> -38136 | ... AL10: =-SUMIFS(DRE_por_UN!$L:$L,DRE_por_UN!$C:$C,AL$2) -> -48720 | AN10: =SUMIF($C$3:$AL$3,2025,$C10:$AL10) -> -457632 | AO10: =SUMIF($C$3:$AL$3,2026,$C10:$AL10) -> -510048 | AP10: =SUMIF($C$3:$AL$3,2027,$C10:$AL10) -> -584640
A11: (-) Aluguel/Ocupacao | C11: =-SUMIFS(DRE_por_UN!$M:$M,DRE_por_UN!$C:$C,C$2) -> -11500 | D11: =-SUMIFS(DRE_por_UN!$M:$M,DRE_por_UN!$C:$C,D$2) -> -11500 | E11: =-SUMIFS(DRE_por_UN!$M:$M,DRE_por_UN!$C:$C,E$2) -> -11500 | F11: =-SUMIFS(DRE_por_UN!$M:$M,DRE_por_UN!$C:$C,F$2) -> -11500 | G11: =-SUMIFS(DRE_por_UN!$M:$M,DRE_por_UN!$C:$C,G$2) -> -11500 | H11: =-SUMIFS(DRE_por_UN!$M:$M,DRE_por_UN!$C:$C,H$2) -> -11500 | I11: =-SUMIFS(DRE_por_UN!$M:$M,DRE_por_UN!$C:$C,I$2) -> -11500 | J11: =-SUMIFS(DRE_por_UN!$M:$M,DRE_por_UN!$C:$C,J$2) -> -11500 | ... AL11: =-SUMIFS(DRE_por_UN!$M:$M,DRE_por_UN!$C:$C,AL$2) -> -12558.288 | AN11: =SUMIF($C$3:$AL$3,2025,$C11:$AL11) -> -138000 | AO11: =SUMIF($C$3:$AL$3,2026,$C11:$AL11) -> -144210 | AP11: =SUMIF($C$3:$AL$3,2027,$C11:$AL11) -> -150699.45
A12: (-) Marketing | C12: =-SUMIFS(DRE_por_UN!$N:$N,DRE_por_UN!$C:$C,C$2) -> -4180.487 | D12: =-SUMIFS(DRE_por_UN!$N:$N,DRE_por_UN!$C:$C,D$2) -> -3964.1712 | E12: =-SUMIFS(DRE_por_UN!$N:$N,DRE_por_UN!$C:$C,E$2) -> -4436.1659 | F12: =-SUMIFS(DRE_por_UN!$N:$N,DRE_por_UN!$C:$C,F$2) -> -4528.0571 | G12: =-SUMIFS(DRE_por_UN!$N:$N,DRE_por_UN!$C:$C,G$2) -> -4557.3676 | H12: =-SUMIFS(DRE_por_UN!$N:$N,DRE_por_UN!$C:$C,H$2) -> -4935.0675 | I12: =-SUMIFS(DRE_por_UN!$N:$N,DRE_por_UN!$C:$C,I$2) -> -4976.5728 | J12: =-SUMIFS(DRE_por_UN!$N:$N,DRE_por_UN!$C:$C,J$2) -> -4457.7932 | ... AL12: =-SUMIFS(DRE_por_UN!$N:$N,DRE_por_UN!$C:$C,AL$2) -> -6788.7931 | AN12: =SUMIF($C$3:$AL$3,2025,$C12:$AL12) -> -57110.663 | AO12: =SUMIF($C$3:$AL$3,2026,$C12:$AL12) -> -60469.046 | AP12: =SUMIF($C$3:$AL$3,2027,$C12:$AL12) -> -64417.348
A13: (-) Frete/Logistica | C13: =-SUMIFS(DRE_por_UN!$O:$O,DRE_por_UN!$C:$C,C$2) -> -4649.7356 | D13: =-SUMIFS(DRE_por_UN!$O:$O,DRE_por_UN!$C:$C,D$2) -> -4699.1016 | E13: =-SUMIFS(DRE_por_UN!$O:$O,DRE_por_UN!$C:$C,E$2) -> -5055.2644 | F13: =-SUMIFS(DRE_por_UN!$O:$O,DRE_por_UN!$C:$C,F$2) -> -5107.2756 | G13: =-SUMIFS(DRE_por_UN!$O:$O,DRE_por_UN!$C:$C,G$2) -> -5316.8364 | H13: =-SUMIFS(DRE_por_UN!$O:$O,DRE_por_UN!$C:$C,H$2) -> -5917.3043 | I13: =-SUMIFS(DRE_por_UN!$O:$O,DRE_por_UN!$C:$C,I$2) -> -5885.7169 | J13: =-SUMIFS(DRE_por_UN!$O:$O,DRE_por_UN!$C:$C,J$2) -> -5217.7056 | ... AL13: =-SUMIFS(DRE_por_UN!$O:$O,DRE_por_UN!$C:$C,AL$2) -> -7881.2362 | AN13: =SUMIF($C$3:$AL$3,2025,$C13:$AL13) -> -66105.464 | AO13: =SUMIF($C$3:$AL$3,2026,$C13:$AL13) -> -69266.62 | AP13: =SUMIF($C$3:$AL$3,2027,$C13:$AL13) -> -73451.744
A14: (-) Outras Desp. Diretas | C14: =-SUMIFS(DRE_por_UN!$P:$P,DRE_por_UN!$C:$C,C$2) -> -3582.3205 | D14: =-SUMIFS(DRE_por_UN!$P:$P,DRE_por_UN!$C:$C,D$2) -> -3426.0813 | E14: =-SUMIFS(DRE_por_UN!$P:$P,DRE_por_UN!$C:$C,E$2) -> -3759.3547 | F14: =-SUMIFS(DRE_por_UN!$P:$P,DRE_por_UN!$C:$C,F$2) -> -3854.2389 | G14: =-SUMIFS(DRE_por_UN!$P:$P,DRE_por_UN!$C:$C,G$2) -> -3901.8419 | H14: =-SUMIFS(DRE_por_UN!$P:$P,DRE_por_UN!$C:$C,H$2) -> -4232.4221 | I14: =-SUMIFS(DRE_por_UN!$P:$P,DRE_por_UN!$C:$C,I$2) -> -4281.3389 | J14: =-SUMIFS(DRE_por_UN!$P:$P,DRE_por_UN!$C:$C,J$2) -> -3775.8989 | ... AL14: =-SUMIFS(DRE_por_UN!$P:$P,DRE_por_UN!$C:$C,AL$2) -> -5799.3279 | AN14: =SUMIF($C$3:$AL$3,2025,$C14:$AL14) -> -48756.916 | AO14: =SUMIF($C$3:$AL$3,2026,$C14:$AL14) -> -51756.505 | AP14: =SUMIF($C$3:$AL$3,2027,$C14:$AL14) -> -55081.725
A15: EBITDA das Unidades | C15: =C8+C10+C11+C12+C13+C14 -> 15780.71 | D15: =D8+D10+D11+D12+D13+D14 -> 13175.66 | E15: =E8+E10+E11+E12+E13+E14 -> 20352.811 | F15: =F8+F10+F11+F12+F13+F14 -> 22417.139 | G15: =G8+G10+G11+G12+G13+G14 -> 22268.434 | H15: =H8+H10+H11+H12+H13+H14 -> 27779.761 | I15: =I8+I10+I11+I12+I13+I14 -> 29136.7 | J15: =J8+J10+J11+J12+J13+J14 -> 20242.128 | ... AL15: =AL8+AL10+AL11+AL12+AL13+AL14 -> 43403.133 | AN15: =SUMIF($C$3:$AL$3,2025,$C15:$AL15) -> 304496.07 | AO15: =SUMIF($C$3:$AL$3,2026,$C15:$AL15) -> 284309.33 | AP15: =SUMIF($C$3:$AL$3,2027,$C15:$AL15) -> 259157.09
A16: (-) Overhead Corporativo (G&A) | C16: =-Premissas!$B$8*(1+Premissas!$B$9)^(C$3-2025) -> -8000 | D16: =-Premissas!$B$8*(1+Premissas!$B$9)^(D$3-2025) -> -8000 | E16: =-Premissas!$B$8*(1+Premissas!$B$9)^(E$3-2025) -> -8000 | F16: =-Premissas!$B$8*(1+Premissas!$B$9)^(F$3-2025) -> -8000 | G16: =-Premissas!$B$8*(1+Premissas!$B$9)^(G$3-2025) -> -8000 | H16: =-Premissas!$B$8*(1+Premissas!$B$9)^(H$3-2025) -> -8000 | I16: =-Premissas!$B$8*(1+Premissas!$B$9)^(I$3-2025) -> -8000 | J16: =-Premissas!$B$8*(1+Premissas!$B$9)^(J$3-2025) -> -8000 | ... AL16: =-Premissas!$B$8*(1+Premissas!$B$9)^(AL$3-2025) -> -8988.8 | AN16: =SUMIF($C$3:$AL$3,2025,$C16:$AL16) -> -96000 | AO16: =SUMIF($C$3:$AL$3,2026,$C16:$AL16) -> -101760 | AP16: =SUMIF($C$3:$AL$3,2027,$C16:$AL16) -> -107865.6
A17: EBITDA Consolidado | C17: =C15+C16 -> 7780.7099 | D17: =D15+D16 -> 5175.6597 | E17: =E15+E16 -> 12352.811 | F17: =F15+F16 -> 14417.139 | G17: =G15+G16 -> 14268.434 | H17: =H15+H16 -> 19779.761 | I17: =I15+I16 -> 21136.7 | J17: =J15+J16 -> 12242.128 | ... AL17: =AL15+AL16 -> 34414.333 | AN17: =SUMIF($C$3:$AL$3,2025,$C17:$AL17) -> 208496.07 | AO17: =SUMIF($C$3:$AL$3,2026,$C17:$AL17) -> 182549.33 | AP17: =SUMIF($C$3:$AL$3,2027,$C17:$AL17) -> 151291.49
A18: Margem EBITDA % | C18: =IF(C6=0,0,C17/C6) -> 0.044482643 | D18: =IF(D6=0,0,D17/D6) -> 0.030363089 | E18: =IF(E6=0,0,E17/E6) -> 0.066190525 | F18: =IF(F6=0,0,F17/F6) -> 0.075322908 | G18: =IF(G6=0,0,G17/G6) -> 0.073626625 | H18: =IF(H6=0,0,H17/H6) -> 0.0939395 | I18: =IF(I6=0,0,I17/I6) -> 0.099145604 | J18: =IF(J6=0,0,J17/J6) -> 0.065162589 | ... AL18: =IF(AL6=0,0,AL17/AL6) -> 0.11941083 | AN18: =IF(AN6=0,0,AN17/AN6) -> 0.086213184 | AO18: =IF(AO6=0,0,AO17/AO6) -> 0.071404632 | AP18: =IF(AP6=0,0,AP17/AP6) -> 0.055596518
A19: (-) Depreciacao e Amortizacao | C19: =-(Cronogramas!C7+Cronogramas!C11) -> -4855.1978 | D19: =-(Cronogramas!D7+Cronogramas!D11) -> -4876.5052 | E19: =-(Cronogramas!E7+Cronogramas!E11) -> -4899.8333 | F19: =-(Cronogramas!F7+Cronogramas!F11) -> -4923.7588 | G19: =-(Cronogramas!G7+Cronogramas!G11) -> -4947.9832 | H19: =-(Cronogramas!H7+Cronogramas!H11) -> -5224.303 | I19: =-(Cronogramas!I7+Cronogramas!I11) -> -5500.9515 | J19: =-(Cronogramas!J7+Cronogramas!J11) -> -5774.4353 | ... AL19: =-(Cronogramas!AL7+Cronogramas!AL11) -> -6545.3541 | AN19: =SUMIF($C$3:$AL$3,2025,$C19:$AL19) -> -64364.765 | AO19: =SUMIF($C$3:$AL$3,2026,$C19:$AL19) -> -72573.103 | AP19: =SUMIF($C$3:$AL$3,2027,$C19:$AL19) -> -76537.059
A20: EBIT | C20: =C17+C19 -> 2925.5121 | D20: =D17+D19 -> 299.15455 | E20: =E17+E19 -> 7452.978 | F20: =F17+F19 -> 9493.3803 | G20: =G17+G19 -> 9320.451 | H20: =H17+H19 -> 14555.458 | I20: =I17+I19 -> 15635.748 | J20: =J17+J19 -> 6467.6928 | ... AL20: =AL17+AL19 -> 27868.979 | AN20: =SUMIF($C$3:$AL$3,2025,$C20:$AL20) -> 144131.3 | AO20: =SUMIF($C$3:$AL$3,2026,$C20:$AL20) -> 109976.23 | AP20: =SUMIF($C$3:$AL$3,2027,$C20:$AL20) -> 74754.426
A21: (+/-) Resultado Financeiro | C21: =Cronogramas!C24 -> -1104 | D21: =Cronogramas!D24 -> -1164.4387 | E21: =Cronogramas!E24 -> -1032.9368 | F21: =Cronogramas!F24 -> -999.25666 | G21: =Cronogramas!G24 -> -876.23057 | H21: =Cronogramas!H24 -> -813.8763 | I21: =Cronogramas!I24 -> -922.98088 | J21: =Cronogramas!J24 -> -1068.2297 | ... AL21: =Cronogramas!AL24 -> 210.1587 | AN21: =SUMIF($C$3:$AL$3,2025,$C21:$AL21) -> -12328.415 | AO21: =SUMIF($C$3:$AL$3,2026,$C21:$AL21) -> -12554.887 | AP21: =SUMIF($C$3:$AL$3,2027,$C21:$AL21) -> -4429.021
A22: LAIR (Lucro antes IR) | C22: =C20+C21 -> 1821.5121 | D22: =D20+D21 -> -865.28417 | E22: =E20+E21 -> 6420.0413 | F22: =F20+F21 -> 8494.1236 | G22: =G20+G21 -> 8444.2205 | H22: =H20+H21 -> 13741.582 | I22: =I20+I21 -> 14712.767 | J22: =J20+J21 -> 5399.4631 | ... AL22: =AL20+AL21 -> 28079.138 | AN22: =SUMIF($C$3:$AL$3,2025,$C22:$AL22) -> 131802.89 | AO22: =SUMIF($C$3:$AL$3,2026,$C22:$AL22) -> 97421.344 | AP22: =SUMIF($C$3:$AL$3,2027,$C22:$AL22) -> 70325.405
A23: (-) IR/CSLL | C23: =-MAX(0,C22)*Premissas!$B$5 -> -619.31412 | D23: =-MAX(0,D22)*Premissas!$B$5 -> 0 | E23: =-MAX(0,E22)*Premissas!$B$5 -> -2182.814 | F23: =-MAX(0,F22)*Premissas!$B$5 -> -2888.002 | G23: =-MAX(0,G22)*Premissas!$B$5 -> -2871.035 | H23: =-MAX(0,H22)*Premissas!$B$5 -> -4672.1379 | I23: =-MAX(0,I22)*Premissas!$B$5 -> -5002.3408 | J23: =-MAX(0,J22)*Premissas!$B$5 -> -1835.8175 | ... AL23: =-MAX(0,AL22)*Premissas!$B$5 -> -9546.9069 | AN23: =SUMIF($C$3:$AL$3,2025,$C23:$AL23) -> -45107.179 | AO23: =SUMIF($C$3:$AL$3,2026,$C23:$AL23) -> -39773.176 | AP23: =SUMIF($C$3:$AL$3,2027,$C23:$AL23) -> -34063.385
A24: Lucro Liquido | C24: =C22+C23 -> 1202.198 | D24: =D22+D23 -> -865.28417 | E24: =E22+E23 -> 4237.2272 | F24: =F22+F23 -> 5606.1216 | G24: =G22+G23 -> 5573.1855 | H24: =H22+H23 -> 9069.4441 | I24: =I22+I23 -> 9710.4263 | J24: =J22+J23 -> 3563.6457 | ... AL24: =AL22+AL23 -> 18532.231 | AN24: =SUMIF($C$3:$AL$3,2025,$C24:$AL24) -> 86695.71 | AO24: =SUMIF($C$3:$AL$3,2026,$C24:$AL24) -> 57648.168 | AP24: =SUMIF($C$3:$AL$3,2027,$C24:$AL24) -> 36262.021
A25: Margem Liquida % | C25: =IF(C6=0,0,C24/C6) -> 0.006873016 | D25: =IF(D6=0,0,D24/D6) -> -0.0050762032 | E25: =IF(E6=0,0,E24/E6) -> 0.022704491 | F25: =IF(F6=0,0,F24/F6) -> 0.029289402 | G25: =IF(G6=0,0,G24/G6) -> 0.028758225 | H25: =IF(H6=0,0,H24/H6) -> 0.043073272 | I25: =IF(I6=0,0,I24/I6) -> 0.045548553 | J25: =IF(J6=0,0,J24/J6) -> 0.018968628 | ... AL25: =IF(AL6=0,0,AL24/AL6) -> 0.064303123 | AN25: =IF(AN6=0,0,AN24/AN6) -> 0.035848701 | AO25: =IF(AO6=0,0,AO24/AO6) -> 0.022549226 | AP25: =IF(AP6=0,0,AP24/AP6) -> 0.013325549

Sheet Balanco_Consolidado
A1: BALANCO PATRIMONIAL CONSOLIDADO (mensal, R$)
A2: Linha | C2: 2025-01 | D2: 2025-02 | E2: 2025-03 | F2: 2025-04 | G2: 2025-05 | H2: 2025-06 | I2: 2025-07 | J2: 2025-08 | K2: 2025-09 | L2: 2025-10 | M2: 2025-11 | N2: 2025-12 | O2: 2026-01 | P2: 2026-02 | Q2: 2026-03 | R2: 2026-04 | S2: 2026-05 | T2: 2026-06 | U2: 2026-07 | V2: 2026-08 | W2: 2026-09 | X2: 2026-10 | Y2: 2026-11 | Z2: 2026-12 | AA2: 2027-01 | AB2: 2027-02 | AC2: 2027-03 | AD2: 2027-04 | AE2: 2027-05 | AF2: 2027-06 | AG2: 2027-07 | AH2: 2027-08 | AI2: 2027-09 | AJ2: 2027-10 | AK2: 2027-11 | AL2: 2027-12 | AN2: 2025 | AO2: 2026 | AP2: 2027
C3: 2025 | D3: 2025 | E3: 2025 | F3: 2025 | G3: 2025 | H3: 2025 | I3: 2025 | J3: 2025 | K3: 2025 | L3: 2025 | M3: 2025 | N3: 2025 | O3: 2026 | P3: 2026 | Q3: 2026 | R3: 2026 | S3: 2026 | T3: 2026 | U3: 2026 | V3: 2026 | W3: 2026 | X3: 2026 | Y3: 2026 | Z3: 2026 | AA3: 2027 | AB3: 2027 | AC3: 2027 | AD3: 2027 | AE3: 2027 | AF3: 2027 | AG3: 2027 | AH3: 2027 | AI3: 2027 | AJ3: 2027 | AK3: 2027 | AL3: 2027 | AN3: Total | AO3: Total | AP3: Total
A4: ATIVO
A5: Caixa e Equivalentes | C5: =DFC_Consolidado!C21 -> 448395.7 | D5: =DFC_Consolidado!D21 -> 454118.14 | E5: =DFC_Consolidado!E21 -> 448971.48 | F5: =DFC_Consolidado!F21 -> 453752.16 | G5: =DFC_Consolidado!G21 -> 451791.52 | H5: =DFC_Consolidado!H21 -> 430779.9 | I5: =DFC_Consolidado!I21 -> 405752.26 | J5: =DFC_Consolidado!J21 -> 378941.04 | ... AL5: =DFC_Consolidado!AL21 -> 387018.24 | AN5: =DFC_Consolidado!N21 -> 400785.67 | AO5: =DFC_Consolidado!Z21 -> 503671.04 | AP5: =DFC_Consolidado!AL21 -> 387018.24
A6: Contas a Receber | C6: =SUMIFS(Contas_Receber!$G:$G,Contas_Receber!$C:$C,C$2) -> 134689.72 | D6: =SUMIFS(Contas_Receber!$G:$G,Contas_Receber!$C:$C,D$2) -> 120751.33 | E6: =SUMIFS(Contas_Receber!$G:$G,Contas_Receber!$C:$C,E$2) -> 137288.64 | F6: =SUMIFS(Contas_Receber!$G:$G,Contas_Receber!$C:$C,F$2) -> 134627.58 | G6: =SUMIFS(Contas_Receber!$G:$G,Contas_Receber!$C:$C,G$2) -> 140529.43 | H6: =SUMIFS(Contas_Receber!$G:$G,Contas_Receber!$C:$C,H$2) -> 145382.58 | I6: =SUMIFS(Contas_Receber!$G:$G,Contas_Receber!$C:$C,I$2) -> 148041.69 | J6: =SUMIFS(Contas_Receber!$G:$G,Contas_Receber!$C:$C,J$2) -> 134050.9 | ... AL6: =SUMIFS(Contas_Receber!$G:$G,Contas_Receber!$C:$C,AL$2) -> 251071.58 | AN6: =SUMIF($C$3:$AL$3,2025,$C6:$AL6) -> 1740010.2 | AO6: =SUMIF($C$3:$AL$3,2026,$C6:$AL6) -> 2054628.9 | AP6: =SUMIF($C$3:$AL$3,2027,$C6:$AL6) -> 2446583.1
A7: Estoques | C7: =SUMIFS(Estoque!$G:$G,Estoque!$C:$C,C$2) -> 169799.38 | D7: =SUMIFS(Estoque!$G:$G,Estoque!$C:$C,D$2) -> 167734.2 | E7: =SUMIFS(Estoque!$G:$G,Estoque!$C:$C,E$2) -> 182327.48 | F7: =SUMIFS(Estoque!$G:$G,Estoque!$C:$C,F$2) -> 185651.9 | G7: =SUMIFS(Estoque!$G:$G,Estoque!$C:$C,G$2) -> 190437.99 | H7: =SUMIFS(Estoque!$G:$G,Estoque!$C:$C,H$2) -> 209970.7 | I7: =SUMIFS(Estoque!$G:$G,Estoque!$C:$C,I$2) -> 210217.62 | J7: =SUMIFS(Estoque!$G:$G,Estoque!$C:$C,J$2) -> 186204 | ... AL7: =SUMIFS(Estoque!$G:$G,Estoque!$C:$C,AL$2) -> 287759.5 | AN7: =SUMIF($C$3:$AL$3,2025,$C7:$AL7) -> 2375129.2 | AO7: =SUMIF($C$3:$AL$3,2026,$C7:$AL7) -> 2522982.2 | AP7: =SUMIF($C$3:$AL$3,2027,$C7:$AL7) -> 2694470.8
A8: Outros Ativos Circulantes | C8: =DRE_Consolidado!C6*Premissas!$B$13 -> 13993.251 | D8: =DRE_Consolidado!D6*Premissas!$B$13 -> 13636.714 | E8: =DRE_Consolidado!E6*Premissas!$B$13 -> 14930.006 | F8: =DRE_Consolidado!F6*Premissas!$B$13 -> 15312.355 | G8: =DRE_Consolidado!G6*Premissas!$B$13 -> 15503.559 | H8: =DRE_Consolidado!H6*Premissas!$B$13 -> 16844.681 | I8: =DRE_Consolidado!I6*Premissas!$B$13 -> 17055.078 | J8: =DRE_Consolidado!J6*Premissas!$B$13 -> 15029.64 | ... AL8: =DRE_Consolidado!AL6*Premissas!$B$13 -> 23056.088 | AN8: =SUMIF($C$3:$AL$3,2025,$C8:$AL8) -> 193470.24 | AO8: =SUMIF($C$3:$AL$3,2026,$C8:$AL8) -> 204523.8 | AP8: =SUMIF($C$3:$AL$3,2027,$C8:$AL8) -> 217699.22
A9: Ativo Circulante | C9: =SUM(C5:C8) -> 766878.05 | D9: =SUM(D5:D8) -> 756240.38 | E9: =SUM(E5:E8) -> 783517.61 | F9: =SUM(F5:F8) -> 789343.99 | G9: =SUM(G5:G8) -> 798262.51 | H9: =SUM(H5:H8) -> 802977.87 | I9: =SUM(I5:I8) -> 781066.65 | J9: =SUM(J5:J8) -> 714225.58 | ... AL9: =SUM(AL5:AL8) -> 948905.42 | AN9: =SUMIF($C$3:$AL$3,2025,$C9:$AL9) -> 9328904.7 | AO9: =SUMIF($C$3:$AL$3,2026,$C9:$AL9) -> 10156699 | AP9: =SUMIF($C$3:$AL$3,2027,$C9:$AL9) -> 10349987
A10: Imobilizado Liquido | C10: =Cronogramas!C9 -> 378435.2 | D10: =Cronogramas!D9 -> 376782.25 | E10: =Cronogramas!E9 -> 375348.46 | F10: =Cronogramas!F9 -> 373962.43 | G10: =Cronogramas!G9 -> 372588.03 | H10: =Cronogramas!H9 -> 401188.78 | I10: =Cronogramas!I9 -> 429552.32 | J10: =Cronogramas!J9 -> 457262.61 | ... AL10: =Cronogramas!AL9 -> 395967.56 | AN10: =SUMIF($C$3:$AL$3,2025,$C10:$AL10) -> 4974265.4 | AO10: =SUMIF($C$3:$AL$3,2026,$C10:$AL10) -> 5216557.2 | AP10: =SUMIF($C$3:$AL$3,2027,$C10:$AL10) -> 4891832.5
A11: Intangivel Liquido | C11: =Cronogramas!C12 -> 39333.333 | D11: =Cronogramas!D12 -> 38666.667 | E11: =Cronogramas!E12 -> 38000 | F11: =Cronogramas!F12 -> 37333.333 | G11: =Cronogramas!G12 -> 36666.667 | H11: =Cronogramas!H12 -> 36000 | I11: =Cronogramas!I12 -> 35333.333 | J11: =Cronogramas!J12 -> 34666.667 | ... AL11: =Cronogramas!AL12 -> 16000 | AN11: =SUMIF($C$3:$AL$3,2025,$C11:$AL11) -> 428000 | AO11: =SUMIF($C$3:$AL$3,2026,$C11:$AL11) -> 332000 | AP11: =SUMIF($C$3:$AL$3,2027,$C11:$AL11) -> 236000
A12: Ativo Nao Circulante | C12: =C10+C11 -> 417768.54 | D12: =D10+D11 -> 415448.92 | E12: =E10+E11 -> 413348.46 | F12: =F10+F11 -> 411295.77 | G12: =G10+G11 -> 409254.7 | H12: =H10+H11 -> 437188.78 | I12: =I10+I11 -> 464885.65 | J12: =J10+J11 -> 491929.27 | ... AL12: =AL10+AL11 -> 411967.56 | AN12: =SUMIF($C$3:$AL$3,2025,$C12:$AL12) -> 5402265.4 | AO12: =SUMIF($C$3:$AL$3,2026,$C12:$AL12) -> 5548557.2 | AP12: =SUMIF($C$3:$AL$3,2027,$C12:$AL12) -> 5127832.5
A13: ATIVO TOTAL | C13: =C9+C12 -> 1184646.6 | D13: =D9+D12 -> 1171689.3 | E13: =E9+E12 -> 1196866.1 | F13: =F9+F12 -> 1200639.8 | G13: =G9+G12 -> 1207517.2 | H13: =H9+H12 -> 1240166.6 | I13: =I9+I12 -> 1245952.3 | J13: =J9+J12 -> 1206154.9 | ... AL13: =AL9+AL12 -> 1360873 | AN13: =SUMIF($C$3:$AL$3,2025,$C13:$AL13) -> 14731170 | AO13: =SUMIF($C$3:$AL$3,2026,$C13:$AL13) -> 15705257 | AP13: =SUMIF($C$3:$AL$3,2027,$C13:$AL13) -> 15477819
A15: PASSIVO E PATRIMONIO LIQUIDO
A16: Fornecedores | C16: =SUMIFS(Contas_Pagar!$G:$G,Contas_Pagar!$C:$C,C$2) -> 138612.65 | D16: =SUMIFS(Contas_Pagar!$G:$G,Contas_Pagar!$C:$C,D$2) -> 138606.51 | E16: =SUMIFS(Contas_Pagar!$G:$G,Contas_Pagar!$C:$C,E$2) -> 150583.08 | F16: =SUMIFS(Contas_Pagar!$G:$G,Contas_Pagar!$C:$C,F$2) -> 153637.34 | G16: =SUMIFS(Contas_Pagar!$G:$G,Contas_Pagar!$C:$C,G$2) -> 157194.9 | H16: =SUMIFS(Contas_Pagar!$G:$G,Contas_Pagar!$C:$C,H$2) -> 173293.47 | I16: =SUMIFS(Contas_Pagar!$G:$G,Contas_Pagar!$C:$C,I$2) -> 173846.28 | J16: =SUMIFS(Contas_Pagar!$G:$G,Contas_Pagar!$C:$C,J$2) -> 153791.36 | ... AL16: =SUMIFS(Contas_Pagar!$G:$G,Contas_Pagar!$C:$C,AL$2) -> 237631.17 | AN16: =SUMIF($C$3:$AL$3,2025,$C16:$AL16) -> 1959414.5 | AO16: =SUMIF($C$3:$AL$3,2026,$C16:$AL16) -> 2075363.8 | AP16: =SUMIF($C$3:$AL$3,2027,$C16:$AL16) -> 2216816.1
A17: Emprestimos Curto Prazo | C17: =Cronogramas!C19 -> 140000 | D17: =Cronogramas!D19 -> 140000 | E17: =Cronogramas!E19 -> 140000 | F17: =Cronogramas!F19 -> 140000 | G17: =Cronogramas!G19 -> 140000 | H17: =Cronogramas!H19 -> 140000 | I17: =Cronogramas!I19 -> 140000 | J17: =Cronogramas!J19 -> 140000 | ... AL17: =Cronogramas!AL19 -> 180000 | AN17: =SUMIF($C$3:$AL$3,2025,$C17:$AL17) -> 1680000 | AO17: =SUMIF($C$3:$AL$3,2026,$C17:$AL17) -> 2640000 | AP17: =SUMIF($C$3:$AL$3,2027,$C17:$AL17) -> 2560000
A18: Obrigacoes Fiscais | C18: =-DRE_Consolidado!C5-DRE_Consolidado!C23 -> 87085.774 | D18: =-DRE_Consolidado!D5-DRE_Consolidado!D23 -> 80445.58 | E18: =-DRE_Consolidado!E5-DRE_Consolidado!E23 -> 92791.944 | F18: =-DRE_Consolidado!F5-DRE_Consolidado!F23 -> 92427.312 | G18: =-DRE_Consolidado!G5-DRE_Consolidado!G23 -> 94935.015 | H18: =-DRE_Consolidado!H5-DRE_Consolidado!H23 -> 105740.03 | I18: =-DRE_Consolidado!I5-DRE_Consolidado!I23 -> 105999.45 | J18: =-DRE_Consolidado!J5-DRE_Consolidado!J23 -> 90225.077 | ... AL18: =-DRE_Consolidado!AL5-DRE_Consolidado!AL23 -> 147630.96 | AN18: =SUMIF($C$3:$AL$3,2025,$C18:$AL18) -> 1201491.8 | AO18: =SUMIF($C$3:$AL$3,2026,$C18:$AL18) -> 1246604.4 | AP18: =SUMIF($C$3:$AL$3,2027,$C18:$AL18) -> 1345369.9
A19: Obrigacoes Trabalhistas | C19: =-DRE_Consolidado!C10*Premissas!$B$15 -> 15254.4 | D19: =-DRE_Consolidado!D10*Premissas!$B$15 -> 15254.4 | E19: =-DRE_Consolidado!E10*Premissas!$B$15 -> 15254.4 | F19: =-DRE_Consolidado!F10*Premissas!$B$15 -> 15254.4 | G19: =-DRE_Consolidado!G10*Premissas!$B$15 -> 15254.4 | H19: =-DRE_Consolidado!H10*Premissas!$B$15 -> 15254.4 | I19: =-DRE_Consolidado!I10*Premissas!$B$15 -> 15254.4 | J19: =-DRE_Consolidado!J10*Premissas!$B$15 -> 15254.4 | ... AL19: =-DRE_Consolidado!AL10*Premissas!$B$15 -> 19488 | AN19: =SUMIF($C$3:$AL$3,2025,$C19:$AL19) -> 183052.8 | AO19: =SUMIF($C$3:$AL$3,2026,$C19:$AL19) -> 204019.2 | AP19: =SUMIF($C$3:$AL$3,2027,$C19:$AL19) -> 233856
A20: Outros Passivos Circulantes | C20: =DRE_Consolidado!C6*Premissas!$B$14 -> 17491.564 | D20: =DRE_Consolidado!D6*Premissas!$B$14 -> 17045.893 | E20: =DRE_Consolidado!E6*Premissas!$B$14 -> 18662.507 | F20: =DRE_Consolidado!F6*Premissas!$B$14 -> 19140.444 | G20: =DRE_Consolidado!G6*Premissas!$B$14 -> 19379.449 | H20: =DRE_Consolidado!H6*Premissas!$B$14 -> 21055.851 | I20: =DRE_Consolidado!I6*Premissas!$B$14 -> 21318.847 | J20: =DRE_Consolidado!J6*Premissas!$B$14 -> 18787.05 | ... AL20: =DRE_Consolidado!AL6*Premissas!$B$14 -> 28820.11 | AN20: =SUMIF($C$3:$AL$3,2025,$C20:$AL20) -> 241837.8 | AO20: =SUMIF($C$3:$AL$3,2026,$C20:$AL20) -> 255654.75 | AP20: =SUMIF($C$3:$AL$3,2027,$C20:$AL20) -> 272124.03
A21: Passivo Circulante | C21: =SUM(C16:C20) -> 398444.39 | D21: =SUM(D16:D20) -> 391352.39 | E21: =SUM(E16:E20) -> 417291.93 | F21: =SUM(F16:F20) -> 420459.5 | G21: =SUM(G16:G20) -> 426763.76 | H21: =SUM(H16:H20) -> 455343.75 | I21: =SUM(I16:I20) -> 456418.98 | J21: =SUM(J16:J20) -> 418057.89 | ... AL21: =SUM(AL16:AL20) -> 613570.24 | AN21: =SUMIF($C$3:$AL$3,2025,$C21:$AL21) -> 5265796.9 | AO21: =SUMIF($C$3:$AL$3,2026,$C21:$AL21) -> 6421642.1 | AP21: =SUMIF($C$3:$AL$3,2027,$C21:$AL21) -> 6628166
A22: Emprestimos Longo Prazo | C22: =Cronogramas!C20 -> 185000 | D22: =Cronogramas!D20 -> 180000 | E22: =Cronogramas!E20 -> 175000 | F22: =Cronogramas!F20 -> 170000 | G22: =Cronogramas!G20 -> 165000 | H22: =Cronogramas!H20 -> 160000 | I22: =Cronogramas!I20 -> 155000 | J22: =Cronogramas!J20 -> 150000 | ... AL22: =Cronogramas!AL20 -> 10000 | AN22: =SUMIF($C$3:$AL$3,2025,$C22:$AL22) -> 1890000 | AO22: =SUMIF($C$3:$AL$3,2026,$C22:$AL22) -> 1170000 | AP22: =SUMIF($C$3:$AL$3,2027,$C22:$AL22) -> 450000
A23: Passivo Nao Circulante | C23: =C22 -> 185000 | D23: =D22 -> 180000 | E23: =E22 -> 175000 | F23: =F22 -> 170000 | G23: =G22 -> 165000 | H23: =H22 -> 160000 | I23: =I22 -> 155000 | J23: =J22 -> 150000 | ... AL23: =AL22 -> 10000 | AN23: =SUMIF($C$3:$AL$3,2025,$C23:$AL23) -> 1890000 | AO23: =SUMIF($C$3:$AL$3,2026,$C23:$AL23) -> 1170000 | AP23: =SUMIF($C$3:$AL$3,2027,$C23:$AL23) -> 450000
A24: (memo) Dividendos Pagos no Mes | C24: =0 -> 0 | D24: =0 -> 0 | E24: =0 -> 0 | F24: =0 -> 0 | G24: =0 -> 0 | H24: =0 -> 0 | I24: =0 -> 0 | J24: =0 -> 0 | ... Q24: =0 -> 0 | R24: =DRE_Consolidado!AN24*Premissas!$B$12 -> 26008.713 | S24: =0 -> 0 | T24: =0 -> 0 | U24: =0 -> 0 | V24: =0 -> 0 | W24: =0 -> 0 | X24: =0 -> 0 | Y24: =0 -> 0 | Z24: =0 -> 0 | ... AC24: =0 -> 0 | AD24: =DRE_Consolidado!AO24*Premissas!$B$12 -> 17294.451 | AE24: =0 -> 0 | AF24: =0 -> 0 | AG24: =0 -> 0 | AH24: =0 -> 0 | AI24: =0 -> 0 | AJ24: =0 -> 0 | AK24: =0 -> 0 | AL24: =0 -> 0 | AN24: =SUMIF($C$3:$AL$3,2025,$C24:$AL24) -> 0 | AO24: =SUMIF($C$3:$AL$3,2026,$C24:$AL24) -> 26008.713 | AP24: =SUMIF($C$3:$AL$3,2027,$C24:$AL24) -> 17294.451
A25: Capital Social | C25: =Premissas!$B$32 -> 400000 | D25: =Premissas!$B$32 -> 400000 | E25: =Premissas!$B$32 -> 400000 | F25: =Premissas!$B$32 -> 400000 | G25: =Premissas!$B$32 -> 400000 | H25: =Premissas!$B$32 -> 400000 | I25: =Premissas!$B$32 -> 400000 | J25: =Premissas!$B$32 -> 400000 | ... AL25: =Premissas!$B$32 -> 400000 | AN25: =SUMIF($C$3:$AL$3,2025,$C25:$AL25) -> 4800000 | AO25: =SUMIF($C$3:$AL$3,2026,$C25:$AL25) -> 4800000 | AP25: =SUMIF($C$3:$AL$3,2027,$C25:$AL25) -> 4800000
A26: Lucros Acumulados | C26: =Premissas!$B$33+DRE_Consolidado!C24-C24 -> 201202.2 | D26: =C26+DRE_Consolidado!D24-D24 -> 200336.91 | E26: =D26+DRE_Consolidado!E24-E24 -> 204574.14 | F26: =E26+DRE_Consolidado!F24-F24 -> 210180.26 | G26: =F26+DRE_Consolidado!G24-G24 -> 215753.45 | H26: =G26+DRE_Consolidado!H24-H24 -> 224822.89 | I26: =H26+DRE_Consolidado!I24-I24 -> 234533.32 | J26: =I26+DRE_Consolidado!J24-J24 -> 238096.96 | K26: =J26+DRE_Consolidado!K24-K24 -> 242579.36 | ... AL26: =AK26+DRE_Consolidado!AL24-AL24 -> 337302.74 | AN26: =N26 -> 286695.71 | AO26: =Z26 -> 318335.17 | AP26: =AL26 -> 337302.74
A27: Patrimonio Liquido | C27: =C25+C26 -> 601202.2 | D27: =D25+D26 -> 600336.91 | E27: =E25+E26 -> 604574.14 | F27: =F25+F26 -> 610180.26 | G27: =G25+G26 -> 615753.45 | H27: =H25+H26 -> 624822.89 | I27: =I25+I26 -> 634533.32 | J27: =J25+J26 -> 638096.96 | ... AL27: =AL25+AL26 -> 737302.74 | AN27: =SUMIF($C$3:$AL$3,2025,$C27:$AL27) -> 7575373.2 | AO27: =SUMIF($C$3:$AL$3,2026,$C27:$AL27) -> 8113614.5 | AP27: =SUMIF($C$3:$AL$3,2027,$C27:$AL27) -> 8399653.4
A28: PASSIVO + PL TOTAL | C28: =C21+C23+C27 -> 1184646.6 | D28: =D21+D23+D27 -> 1171689.3 | E28: =E21+E23+E27 -> 1196866.1 | F28: =F21+F23+F27 -> 1200639.8 | G28: =G21+G23+G27 -> 1207517.2 | H28: =H21+H23+H27 -> 1240166.6 | I28: =I21+I23+I27 -> 1245952.3 | J28: =J21+J23+J27 -> 1206154.9 | ... AL28: =AL21+AL23+AL27 -> 1360873 | AN28: =SUMIF($C$3:$AL$3,2025,$C28:$AL28) -> 14731170 | AO28: =SUMIF($C$3:$AL$3,2026,$C28:$AL28) -> 15705257 | AP28: =SUMIF($C$3:$AL$3,2027,$C28:$AL28) -> 15477819
A29: CHECAGEM (Ativo - Passivo-PL) | C29: =C13-C28 -> 0 | D29: =D13-D28 -> 0 | E29: =E13-E28 -> 0 | F29: =F13-F28 -> 0 | G29: =G13-G28 -> 0 | H29: =H13-H28 -> 0 | I29: =I13-I28 -> 0 | J29: =J13-J28 -> 0 | ... AL29: =AL13-AL28 -> 0 | AN29: =SUMIF($C$3:$AL$3,2025,$C29:$AL29) -> 0 | AO29: =SUMIF($C$3:$AL$3,2026,$C29:$AL29) -> 0 | AP29: =SUMIF($C$3:$AL$3,2027,$C29:$AL29) -> 0

Sheet DFC_Consolidado
A1: DEMONSTRACAO DE FLUXO DE CAIXA - Metodo Indireto (mensal, R$)
A2: Linha | C2: 2025-01 | D2: 2025-02 | E2: 2025-03 | F2: 2025-04 | G2: 2025-05 | H2: 2025-06 | I2: 2025-07 | J2: 2025-08 | K2: 2025-09 | L2: 2025-10 | M2: 2025-11 | N2: 2025-12 | O2: 2026-01 | P2: 2026-02 | Q2: 2026-03 | R2: 2026-04 | S2: 2026-05 | T2: 2026-06 | U2: 2026-07 | V2: 2026-08 | W2: 2026-09 | X2: 2026-10 | Y2: 2026-11 | Z2: 2026-12 | AA2: 2027-01 | AB2: 2027-02 | AC2: 2027-03 | AD2: 2027-04 | AE2: 2027-05 | AF2: 2027-06 | AG2: 2027-07 | AH2: 2027-08 | AI2: 2027-09 | AJ2: 2027-10 | AK2: 2027-11 | AL2: 2027-12 | AN2: 2025 | AO2: 2026 | AP2: 2027
C3: 2025 | D3: 2025 | E3: 2025 | F3: 2025 | G3: 2025 | H3: 2025 | I3: 2025 | J3: 2025 | K3: 2025 | L3: 2025 | M3: 2025 | N3: 2025 | O3: 2026 | P3: 2026 | Q3: 2026 | R3: 2026 | S3: 2026 | T3: 2026 | U3: 2026 | V3: 2026 | W3: 2026 | X3: 2026 | Y3: 2026 | Z3: 2026 | AA3: 2027 | AB3: 2027 | AC3: 2027 | AD3: 2027 | AE3: 2027 | AF3: 2027 | AG3: 2027 | AH3: 2027 | AI3: 2027 | AJ3: 2027 | AK3: 2027 | AL3: 2027 | AN3: Total | AO3: Total | AP3: Total
A4: Lucro Liquido | C4: =DRE_Consolidado!C24 -> 1202.198 | D4: =DRE_Consolidado!D24 -> -865.28417 | E4: =DRE_Consolidado!E24 -> 4237.2272 | F4: =DRE_Consolidado!F24 -> 5606.1216 | G4: =DRE_Consolidado!G24 -> 5573.1855 | H4: =DRE_Consolidado!H24 -> 9069.4441 | I4: =DRE_Consolidado!I24 -> 9710.4263 | J4: =DRE_Consolidado!J24 -> 3563.6457 | ... AL4: =DRE_Consolidado!AL24 -> 18532.231 | AN4: =SUMIF($C$3:$AL$3,2025,$C4:$AL4) -> 86695.71 | AO4: =SUMIF($C$3:$AL$3,2026,$C4:$AL4) -> 57648.168 | AP4: =SUMIF($C$3:$AL$3,2027,$C4:$AL4) -> 36262.021
A5: (+) Depreciacao e Amortizacao | C5: =Cronogramas!C7+Cronogramas!C11 -> 4855.1978 | D5: =Cronogramas!D7+Cronogramas!D11 -> 4876.5052 | E5: =Cronogramas!E7+Cronogramas!E11 -> 4899.8333 | F5: =Cronogramas!F7+Cronogramas!F11 -> 4923.7588 | G5: =Cronogramas!G7+Cronogramas!G11 -> 4947.9832 | H5: =Cronogramas!H7+Cronogramas!H11 -> 5224.303 | I5: =Cronogramas!I7+Cronogramas!I11 -> 5500.9515 | J5: =Cronogramas!J7+Cronogramas!J11 -> 5774.4353 | ... AL5: =Cronogramas!AL7+Cronogramas!AL11 -> 6545.3541 | AN5: =SUMIF($C$3:$AL$3,2025,$C5:$AL5) -> 64364.765 | AO5: =SUMIF($C$3:$AL$3,2026,$C5:$AL5) -> 72573.103 | AP5: =SUMIF($C$3:$AL$3,2027,$C5:$AL5) -> 76537.059
A6: (-) Var. Contas a Receber | C6: =-(Balanco_Consolidado!C6-Premissas!$B$18) -> -4689.7217 | D6: =-(Balanco_Consolidado!D6-Balanco_Consolidado!C6) -> 13938.393 | E6: =-(Balanco_Consolidado!E6-Balanco_Consolidado!D6) -> -16537.316 | F6: =-(Balanco_Consolidado!F6-Balanco_Consolidado!E6) -> 2661.0673 | G6: =-(Balanco_Consolidado!G6-Balanco_Consolidado!F6) -> -5901.8567 | H6: =-(Balanco_Consolidado!H6-Balanco_Consolidado!G6) -> -4853.1493 | I6: =-(Balanco_Consolidado!I6-Balanco_Consolidado!H6) -> -2659.1057 | J6: =-(Balanco_Consolidado!J6-Balanco_Consolidado!I6) -> 13990.787 | K6: =-(Balanco_Consolidado!K6-Balanco_Consolidado!J6) -> -10965.034 | ... AL6: =-(Balanco_Consolidado!AL6-Balanco_Consolidado!AK6) -> -11187.887 | AN6: =SUMIF($C$3:$AL$3,2025,$C6:$AL6) -> -51941.238 | AO6: =SUMIF($C$3:$AL$3,2026,$C6:$AL6) -> -27852.784 | AP6: =SUMIF($C$3:$AL$3,2027,$C6:$AL6) -> -41277.559
A7: (-) Var. Estoques | C7: =-(Balanco_Consolidado!C7-Premissas!$B$19) -> 10200.622 | D7: =-(Balanco_Consolidado!D7-Balanco_Consolidado!C7) -> 2065.1749 | E7: =-(Balanco_Consolidado!E7-Balanco_Consolidado!D7) -> -14593.278 | F7: =-(Balanco_Consolidado!F7-Balanco_Consolidado!E7) -> -3324.419 | G7: =-(Balanco_Consolidado!G7-Balanco_Consolidado!F7) -> -4786.0923 | H7: =-(Balanco_Consolidado!H7-Balanco_Consolidado!G7) -> -19532.706 | I7: =-(Balanco_Consolidado!I7-Balanco_Consolidado!H7) -> -246.92437 | J7: =-(Balanco_Consolidado!J7-Balanco_Consolidado!I7) -> 24013.626 | K7: =-(Balanco_Consolidado!K7-Balanco_Consolidado!J7) -> -53.1437 | ... AL7: =-(Balanco_Consolidado!AL7-Balanco_Consolidado!AK7) -> -20592.984 | AN7: =SUMIF($C$3:$AL$3,2025,$C7:$AL7) -> -68556.416 | AO7: =SUMIF($C$3:$AL$3,2026,$C7:$AL7) -> -20523.768 | AP7: =SUMIF($C$3:$AL$3,2027,$C7:$AL7) -> -18679.321
A8: (-) Var. Outros Ativos Circ. | C8: =-(Balanco_Consolidado!C8-Premissas!$B$20) -> 2006.7488 | D8: =-(Balanco_Consolidado!D8-Balanco_Consolidado!C8) -> 356.5368 | E8: =-(Balanco_Consolidado!E8-Balanco_Consolidado!D8) -> -1293.2912 | F8: =-(Balanco_Consolidado!F8-Balanco_Consolidado!E8) -> -382.3496 | G8: =-(Balanco_Consolidado!G8-Balanco_Consolidado!F8) -> -191.204 | H8: =-(Balanco_Consolidado!H8-Balanco_Consolidado!G8) -> -1341.1216 | I8: =-(Balanco_Consolidado!I8-Balanco_Consolidado!H8) -> -210.3968 | J8: =-(Balanco_Consolidado!J8-Balanco_Consolidado!I8) -> 2025.4376 | K8: =-(Balanco_Consolidado!K8-Balanco_Consolidado!J8) -> -195.4848 | ... AL8: =-(Balanco_Consolidado!AL8-Balanco_Consolidado!AK8) -> -1669.3598 | AN8: =SUMIF($C$3:$AL$3,2025,$C8:$AL8) -> -4266.7496 | AO8: =SUMIF($C$3:$AL$3,2026,$C8:$AL8) -> -1396.1424 | AP8: =SUMIF($C$3:$AL$3,2027,$C8:$AL8) -> -1393.1961
A9: (+) Var. Fornecedores | C9: =(Balanco_Consolidado!C16-Premissas!$B$24) -> -11387.35 | D9: =(Balanco_Consolidado!D16-Balanco_Consolidado!C16) -> -6.1367333 | E9: =(Balanco_Consolidado!E16-Balanco_Consolidado!D16) -> 11976.566 | F9: =(Balanco_Consolidado!F16-Balanco_Consolidado!E16) -> 3054.2589 | G9: =(Balanco_Consolidado!G16-Balanco_Consolidado!F16) -> 3557.5574 | H9: =(Balanco_Consolidado!H16-Balanco_Consolidado!G16) -> 16098.573 | I9: =(Balanco_Consolidado!I16-Balanco_Consolidado!H16) -> 552.8142 | J9: =(Balanco_Consolidado!J16-Balanco_Consolidado!I16) -> -20054.924 | K9: =(Balanco_Consolidado!K16-Balanco_Consolidado!J16) -> -1166.5077 | ... AL9: =(Balanco_Consolidado!AL16-Balanco_Consolidado!AK16) -> 17746.329 | AN9: =SUMIF($C$3:$AL$3,2025,$C9:$AL9) -> 54938.123 | AO9: =SUMIF($C$3:$AL$3,2026,$C9:$AL9) -> 17279.659 | AP9: =SUMIF($C$3:$AL$3,2027,$C9:$AL9) -> 15413.388
A10: (+) Var. Obrigacoes Fiscais | C10: =(Balanco_Consolidado!C18-Premissas!$B$25) -> -7914.2259 | D10: =(Balanco_Consolidado!D18-Balanco_Consolidado!C18) -> -6640.1941 | E10: =(Balanco_Consolidado!E18-Balanco_Consolidado!D18) -> 12346.364 | F10: =(Balanco_Consolidado!F18-Balanco_Consolidado!E18) -> -364.632 | G10: =(Balanco_Consolidado!G18-Balanco_Consolidado!F18) -> 2507.7029 | H10: =(Balanco_Consolidado!H18-Balanco_Consolidado!G18) -> 10805.013 | I10: =(Balanco_Consolidado!I18-Balanco_Consolidado!H18) -> 259.42299 | J10: =(Balanco_Consolidado!J18-Balanco_Consolidado!I18) -> -15774.373 | K10: =(Balanco_Consolidado!K18-Balanco_Consolidado!J18) -> 7732.4336 | ... AL10: =(Balanco_Consolidado!AL18-Balanco_Consolidado!AK18) -> 10974.353 | AN10: =SUMIF($C$3:$AL$3,2025,$C10:$AL10) -> 36239.306 | AO10: =SUMIF($C$3:$AL$3,2026,$C10:$AL10) -> 6021.6884 | AP10: =SUMIF($C$3:$AL$3,2027,$C10:$AL10) -> 10369.966
A11: (+) Var. Obrigacoes Trabalhistas | C11: =(Balanco_Consolidado!C19-Premissas!$B$26) -> 254.4 | D11: =(Balanco_Consolidado!D19-Balanco_Consolidado!C19) -> 0 | E11: =(Balanco_Consolidado!E19-Balanco_Consolidado!D19) -> 0 | F11: =(Balanco_Consolidado!F19-Balanco_Consolidado!E19) -> 0 | G11: =(Balanco_Consolidado!G19-Balanco_Consolidado!F19) -> 0 | H11: =(Balanco_Consolidado!H19-Balanco_Consolidado!G19) -> 0 | I11: =(Balanco_Consolidado!I19-Balanco_Consolidado!H19) -> 0 | J11: =(Balanco_Consolidado!J19-Balanco_Consolidado!I19) -> 0 | K11: =(Balanco_Consolidado!K19-Balanco_Consolidado!J19) -> 0 | ... AL11: =(Balanco_Consolidado!AL19-Balanco_Consolidado!AK19) -> 0 | AN11: =SUMIF($C$3:$AL$3,2025,$C11:$AL11) -> 254.4 | AO11: =SUMIF($C$3:$AL$3,2026,$C11:$AL11) -> 1747.2 | AP11: =SUMIF($C$3:$AL$3,2027,$C11:$AL11) -> 2486.4
A12: (+) Var. Outros Passivos Circ. | C12: =(Balanco_Consolidado!C20-Premissas!$B$27) -> -2508.436 | D12: =(Balanco_Consolidado!D20-Balanco_Consolidado!C20) -> -445.671 | E12: =(Balanco_Consolidado!E20-Balanco_Consolidado!D20) -> 1616.614 | F12: =(Balanco_Consolidado!F20-Balanco_Consolidado!E20) -> 477.937 | G12: =(Balanco_Consolidado!G20-Balanco_Consolidado!F20) -> 239.005 | H12: =(Balanco_Consolidado!H20-Balanco_Consolidado!G20) -> 1676.402 | I12: =(Balanco_Consolidado!I20-Balanco_Consolidado!H20) -> 262.996 | J12: =(Balanco_Consolidado!J20-Balanco_Consolidado!I20) -> -2531.797 | K12: =(Balanco_Consolidado!K20-Balanco_Consolidado!J20) -> 244.356 | ... AL12: =(Balanco_Consolidado!AL20-Balanco_Consolidado!AK20) -> 2086.6998 | AN12: =SUMIF($C$3:$AL$3,2025,$C12:$AL12) -> 5333.437 | AO12: =SUMIF($C$3:$AL$3,2026,$C12:$AL12) -> 1745.178 | AP12: =SUMIF($C$3:$AL$3,2027,$C12:$AL12) -> 1741.4951
A13: (=) Fluxo de Caixa Operacional | C13: =SUM(C4:C12) -> -7980.5669 | D13: =SUM(D4:D12) -> 13279.324 | E13: =SUM(E4:E12) -> 2652.7199 | F13: =SUM(F4:F12) -> 12651.743 | G13: =SUM(G4:G12) -> 5946.2811 | H13: =SUM(H4:H12) -> 17146.758 | I13: =SUM(I4:I12) -> 13170.184 | J13: =SUM(J4:J12) -> 11006.837 | ... AL13: =SUM(AL4:AL12) -> 22434.736 | AN13: =SUMIF($C$3:$AL$3,2025,$C13:$AL13) -> 123061.34 | AO13: =SUMIF($C$3:$AL$3,2026,$C13:$AL13) -> 107242.3 | AP13: =SUMIF($C$3:$AL$3,2027,$C13:$AL13) -> 81460.253
A14: (-) Capex | C14: =-Cronogramas!C5 -> -2623.7346 | D14: =-Cronogramas!D5 -> -2556.8839 | E14: =-Cronogramas!E5 -> -2799.376 | F14: =-Cronogramas!F5 -> -2871.0666 | G14: =-Cronogramas!G5 -> -2906.9174 | H14: =-Cronogramas!H5 -> -33158.378 | I14: =-Cronogramas!I5 -> -33197.827 | J14: =-Cronogramas!J5 -> -32818.058 | ... AL14: =-Cronogramas!AL5 -> -4323.0165 | AN14: =SUMIF($C$3:$AL$3,2025,$C14:$AL14) -> -126275.67 | AO14: =SUMIF($C$3:$AL$3,2026,$C14:$AL14) -> -38348.213 | AP14: =SUMIF($C$3:$AL$3,2027,$C14:$AL14) -> -40818.604
A15: (=) Fluxo de Caixa de Investimento | C15: =C14 -> -2623.7346 | D15: =D14 -> -2556.8839 | E15: =E14 -> -2799.376 | F15: =F14 -> -2871.0666 | G15: =G14 -> -2906.9174 | H15: =H14 -> -33158.378 | I15: =I14 -> -33197.827 | J15: =J14 -> -32818.058 | ... AL15: =AL14 -> -4323.0165 | AN15: =SUMIF($C$3:$AL$3,2025,$C15:$AL15) -> -126275.67 | AO15: =SUMIF($C$3:$AL$3,2026,$C15:$AL15) -> -38348.213 | AP15: =SUMIF($C$3:$AL$3,2027,$C15:$AL15) -> -40818.604
A16: (+/-) Captacao/Amortizacao de Divida | C16: =(Cronogramas!C18-(Premissas!$B$28+Premissas!$B$29)) -> -5000 | D16: =(Cronogramas!D18-Cronogramas!C18) -> -5000 | E16: =(Cronogramas!E18-Cronogramas!D18) -> -5000 | F16: =(Cronogramas!F18-Cronogramas!E18) -> -5000 | G16: =(Cronogramas!G18-Cronogramas!F18) -> -5000 | H16: =(Cronogramas!H18-Cronogramas!G18) -> -5000 | I16: =(Cronogramas!I18-Cronogramas!H18) -> -5000 | J16: =(Cronogramas!J18-Cronogramas!I18) -> -5000 | K16: =(Cronogramas!K18-Cronogramas!J18) -> -5000 | ... AL16: =(Cronogramas!AL18-Cronogramas!AK18) -> -10000 | AN16: =SUMIF($C$3:$AL$3,2025,$C16:$AL16) -> -60000 | AO16: =SUMIF($C$3:$AL$3,2026,$C16:$AL16) -> 60000 | AP16: =SUMIF($C$3:$AL$3,2027,$C16:$AL16) -> -140000
A17: (-) Dividendos | C17: =-Balanco_Consolidado!C24 -> 0 | D17: =-Balanco_Consolidado!D24 -> 0 | E17: =-Balanco_Consolidado!E24 -> 0 | F17: =-Balanco_Consolidado!F24 -> 0 | G17: =-Balanco_Consolidado!G24 -> 0 | H17: =-Balanco_Consolidado!H24 -> 0 | I17: =-Balanco_Consolidado!I24 -> 0 | J17: =-Balanco_Consolidado!J24 -> 0 | ... AL17: =-Balanco_Consolidado!AL24 -> 0 | AN17: =SUMIF($C$3:$AL$3,2025,$C17:$AL17) -> 0 | AO17: =SUMIF($C$3:$AL$3,2026,$C17:$AL17) -> -26008.713 | AP17: =SUMIF($C$3:$AL$3,2027,$C17:$AL17) -> -17294.451
A18: (=) Fluxo de Caixa de Financiamento | C18: =C16+C17 -> -5000 | D18: =D16+D17 -> -5000 | E18: =E16+E17 -> -5000 | F18: =F16+F17 -> -5000 | G18: =G16+G17 -> -5000 | H18: =H16+H17 -> -5000 | I18: =I16+I17 -> -5000 | J18: =J16+J17 -> -5000 | ... AL18: =AL16+AL17 -> -10000 | AN18: =SUMIF($C$3:$AL$3,2025,$C18:$AL18) -> -60000 | AO18: =SUMIF($C$3:$AL$3,2026,$C18:$AL18) -> 33991.287 | AP18: =SUMIF($C$3:$AL$3,2027,$C18:$AL18) -> -157294.45
A19: Variacao de Caixa | C19: =C13+C15+C18 -> -15604.302 | D19: =D13+D15+D18 -> 5722.4396 | E19: =E13+E15+E18 -> -5146.6561 | F19: =F13+F15+F18 -> 4780.6765 | G19: =G13+G15+G18 -> -1960.6363 | H19: =H13+H15+H18 -> -21011.62 | I19: =I13+I15+I18 -> -25027.643 | J19: =J13+J15+J18 -> -26811.221 | ... AL19: =AL13+AL15+AL18 -> 8111.7193 | AN19: =SUMIF($C$3:$AL$3,2025,$C19:$AL19) -> -63214.333 | AO19: =SUMIF($C$3:$AL$3,2026,$C19:$AL19) -> 102885.38 | AP19: =SUMIF($C$3:$AL$3,2027,$C19:$AL19) -> -116652.8
A20: Caixa Inicial | C20: =Premissas!$B$35 -> 464000 | D20: =C21 -> 448395.7 | E20: =D21 -> 454118.14 | F20: =E21 -> 448971.48 | G20: =F21 -> 453752.16 | H20: =G21 -> 451791.52 | I20: =H21 -> 430779.9 | J20: =I21 -> 405752.26 | K20: =J21 -> 378941.04 | ... AL20: =AK21 -> 378906.52 | AN20: =C20 -> 464000 | AO20: =O20 -> 400785.67 | AP20: =AA20 -> 503671.04
A21: Caixa Final | C21: =C20+C19 -> 448395.7 | D21: =D20+D19 -> 454118.14 | E21: =E20+E19 -> 448971.48 | F21: =F20+F19 -> 453752.16 | G21: =G20+G19 -> 451791.52 | H21: =H20+H19 -> 430779.9 | I21: =I20+I19 -> 405752.26 | J21: =J20+J19 -> 378941.04 | ... AL21: =AL20+AL19 -> 387018.24 | AN21: =N21 -> 400785.67 | AO21: =Z21 -> 503671.04 | AP21: =AL21 -> 387018.24

Sheet KPIs_Mensais
A1: Ano | B1: Mes | C1: ChaveMes | D1: DataRef | E1: Receita Bruta | F1: Receita Liquida | G1: Cresc. MoM % | H1: Cresc. YoY % | I1: Margem Bruta % | J1: Margem EBITDA % | K1: Margem Liquida % | L1: EBITDA | M1: Lucro Liquido | N1: DSO (dias) | O1: DIO (dias) | P1: DPO (dias) | Q1: Ciclo Caixa (dias) | R1: Liquidez Corrente | S1: Divida Liquida | T1: Div.Liq/EBITDA LTM | U1: Cobertura Juros | V1: ROIC LTM % | W1: FCO do Mes | X1: Capital Giro Liq.
A2: 2025 | B2: 1 | C2: 2025-01 | D2: 45658 | E2: =DRE_Consolidado!C4 -> 261382.1 | F2: =DRE_Consolidado!C6 -> 174915.64 | I2: =DRE_Consolidado!C9 -> 0.44495308 | J2: =DRE_Consolidado!C18 -> 0.044482643 | K2: =DRE_Consolidado!C25 -> 0.006873016 | L2: =DRE_Consolidado!C17 -> 7780.7099 | M2: =DRE_Consolidado!C24 -> 1202.198 | N2: =IF(DRE_Consolidado!C6=0,0,Balanco_Consolidado!C6/DRE_Consolidado!C6*30) -> 23.100802 | O2: =IF(DRE_Consolidado!C7=0,0,Balanco_Consolidado!C7/(-DRE_Consolidado!C7)*30) -> 52.468544 | P2: =IF(DRE_Consolidado!C7=0,0,Balanco_Consolidado!C16/(-DRE_Consolidado!C7)*30) -> 42.831746 | Q2: =N2+O2-P2 -> 32.7376 | R2: =IF(Balanco_Consolidado!C21=0,0,Balanco_Consolidado!C9/Balanco_Consolidado!C21) -> 1.9246803 | S2: =Cronogramas!C18-Balanco_Consolidado!C5 -> -123395.7 | U2: =IF(Cronogramas!C22=0,0,DRE_Consolidado!C20/Cronogramas!C22) -> 0.55407426 | W2: =DFC_Consolidado!C13 -> -7980.5669 | X2: =Balanco_Consolidado!C9-Balanco_Consolidado!C21 -> 368433.66
A3: 2025 | B3: 2 | C3: 2025-02 | D3: 45689 | E3: =DRE_Consolidado!D4 -> 250904.51 | F3: =DRE_Consolidado!D6 -> 170458.93 | G3: =IF(DRE_Consolidado!C4=0,0,DRE_Consolidado!D4/DRE_Consolidado!C4-1) -> -0.040085339 | I3: =DRE_Consolidado!D9 -> 0.43940798 | J3: =DRE_Consolidado!D18 -> 0.030363089 | K3: =DRE_Consolidado!D25 -> -0.0050762032 | L3: =DRE_Consolidado!D17 -> 5175.6597 | M3: =DRE_Consolidado!D24 -> -865.28417 | N3: =IF(DRE_Consolidado!D6=0,0,Balanco_Consolidado!D6/DRE_Consolidado!D6*30) -> 21.251687 | O3: =IF(DRE_Consolidado!D7=0,0,Balanco_Consolidado!D7/(-DRE_Consolidado!D7)*30) -> 52.659437 | P3: =IF(DRE_Consolidado!D7=0,0,Balanco_Consolidado!D16/(-DRE_Consolidado!D7)*30) -> 43.514923 | Q3: =N3+O3-P3 -> 30.396201 | R3: =IF(Balanco_Consolidado!D21=0,0,Balanco_Consolidado!D9/Balanco_Consolidado!D21) -> 1.9323771 | S3: =Cronogramas!D18-Balanco_Consolidado!D5 -> -134118.14 | U3: =IF(Cronogramas!D22=0,0,DRE_Consolidado!D20/Cronogramas!D22) -> 0.05752972 | W3: =DFC_Consolidado!D13 -> 13279.324 | X3: =Balanco_Consolidado!D9-Balanco_Consolidado!D21 -> 364888
A4: 2025 | B4: 3 | C4: 2025-03 | D4: 45717 | E4: =DRE_Consolidado!E4 -> 277234.2 | F4: =DRE_Consolidado!E6 -> 186625.07 | G4: =IF(DRE_Consolidado!D4=0,0,DRE_Consolidado!E4/DRE_Consolidado!D4-1) -> 0.10493909 | I4: =DRE_Consolidado!E9 -> 0.4460258 | J4: =DRE_Consolidado!E18 -> 0.066190525 | K4: =DRE_Consolidado!E25 -> 0.022704491 | L4: =DRE_Consolidado!E17 -> 12352.811 | M4: =DRE_Consolidado!E24 -> 4237.2272 | N4: =IF(DRE_Consolidado!E6=0,0,Balanco_Consolidado!E6/DRE_Consolidado!E6*30) -> 22.069164 | O4: =IF(DRE_Consolidado!E7=0,0,Balanco_Consolidado!E7/(-DRE_Consolidado!E7)*30) -> 52.907089 | P4: =IF(DRE_Consolidado!E7=0,0,Balanco_Consolidado!E16/(-DRE_Consolidado!E7)*30) -> 43.69562 | Q4: =N4+O4-P4 -> 31.280633 | R4: =IF(Balanco_Consolidado!E21=0,0,Balanco_Consolidado!E9/Balanco_Consolidado!E21) -> 1.8776246 | S4: =Cronogramas!E18-Balanco_Consolidado!E5 -> -133971.48 | U4: =IF(Cronogramas!E22=0,0,DRE_Consolidado!E20/Cronogramas!E22) -> 1.4556598 | W4: =DFC_Consolidado!E13 -> 2652.7199 | X4: =Balanco_Consolidado!E9-Balanco_Consolidado!E21 -> 366225.68
A5: 2025 | B5: 4 | C5: 2025-04 | D5: 45748 | E5: =DRE_Consolidado!F4 -> 280943.75 | F5: =DRE_Consolidado!F6 -> 191404.44 | G5: =IF(DRE_Consolidado!E4=0,0,DRE_Consolidado!F4/DRE_Consolidado!E4-1) -> 0.013380564 | I5: =DRE_Consolidado!F9 -> 0.44692125 | J5: =DRE_Consolidado!F18 -> 0.075322908 | K5: =DRE_Consolidado!F25 -> 0.029289402 | L5: =DRE_Consolidado!F17 -> 14417.139 | M5: =DRE_Consolidado!F24 -> 5606.1216 | N5: =IF(DRE_Consolidado!F6=0,0,Balanco_Consolidado!F6/DRE_Consolidado!F6*30) -> 21.101012 | O5: =IF(DRE_Consolidado!F7=0,0,Balanco_Consolidado!F7/(-DRE_Consolidado!F7)*30) -> 52.611619 | P5: =IF(DRE_Consolidado!F7=0,0,Balanco_Consolidado!F16/(-DRE_Consolidado!F7)*30) -> 43.53906 | Q5: =N5+O5-P5 -> 30.173571 | R5: =IF(Balanco_Consolidado!F21=0,0,Balanco_Consolidado!F9/Balanco_Consolidado!F21) -> 1.8773366 | S5: =Cronogramas!F18-Balanco_Consolidado!F5 -> -143752.16 | U5: =IF(Cronogramas!F22=0,0,DRE_Consolidado!F20/Cronogramas!F22) -> 1.8836072 | W5: =DFC_Consolidado!F13 -> 12651.743 | X5: =Balanco_Consolidado!F9-Balanco_Consolidado!F21 -> 368884.5
A6: 2025 | B6: 5 | C6: 2025-05 | D6: 45778 | E6: =DRE_Consolidado!G4 -> 285858.47 | F6: =DRE_Consolidado!G6 -> 193794.49 | G6: =IF(DRE_Consolidado!F4=0,0,DRE_Consolidado!G4/DRE_Consolidado!F4-1) -> 0.017493609 | I6: =DRE_Consolidado!G9 -> 0.44212031 | J6: =DRE_Consolidado!G18 -> 0.073626625 | K6: =DRE_Consolidado!G25 -> 0.028758225 | L6: =DRE_Consolidado!G17 -> 14268.434 | M6: =DRE_Consolidado!G24 -> 5573.1855 | N6: =IF(DRE_Consolidado!G6=0,0,Balanco_Consolidado!G6/DRE_Consolidado!G6*30) -> 21.754401 | O6: =IF(DRE_Consolidado!G7=0,0,Balanco_Consolidado!G7/(-DRE_Consolidado!G7)*30) -> 52.843658 | P6: =IF(DRE_Consolidado!G7=0,0,Balanco_Consolidado!G16/(-DRE_Consolidado!G7)*30) -> 43.619203 | Q6: =N6+O6-P6 -> 30.978857 | R6: =IF(Balanco_Consolidado!G21=0,0,Balanco_Consolidado!G9/Balanco_Consolidado!G21) -> 1.8705021 | S6: =Cronogramas!G18-Balanco_Consolidado!G5 -> -146791.52 | U6: =IF(Cronogramas!G22=0,0,DRE_Consolidado!G20/Cronogramas!G22) -> 1.8791232 | W6: =DFC_Consolidado!G13 -> 5946.2811 | X6: =Balanco_Consolidado!G9-Balanco_Consolidado!G21 -> 371498.75
A7: 2025 | B7: 6 | C7: 2025-06 | D7: 45809 | E7: =DRE_Consolidado!H4 -> 311626.4 | F7: =DRE_Consolidado!H6 -> 210558.51 | G7: =IF(DRE_Consolidado!G4=0,0,DRE_Consolidado!H4/DRE_Consolidado!G4-1) -> 0.090142265 | I7: =DRE_Consolidado!H9 -> 0.43931046 | J7: =DRE_Consolidado!H18 -> 0.0939395 | K7: =DRE_Consolidado!H25 -> 0.043073272 | L7: =DRE_Consolidado!H17 -> 19779.761 | M7: =DRE_Consolidado!H24 -> 9069.4441 | N7: =IF(DRE_Consolidado!H6=0,0,Balanco_Consolidado!H6/DRE_Consolidado!H6*30) -> 20.713851 | O7: =IF(DRE_Consolidado!H7=0,0,Balanco_Consolidado!H7/(-DRE_Consolidado!H7)*30) -> 53.356175 | P7: =IF(DRE_Consolidado!H7=0,0,Balanco_Consolidado!H16/(-DRE_Consolidado!H7)*30) -> 44.036034 | Q7: =N7+O7-P7 -> 30.033992 | R7: =IF(Balanco_Consolidado!H21=0,0,Balanco_Consolidado!H9/Balanco_Consolidado!H21) -> 1.7634542 | S7: =Cronogramas!H18-Balanco_Consolidado!H5 -> -130779.9 | U7: =IF(Cronogramas!H22=0,0,DRE_Consolidado!H20/Cronogramas!H22) -> 2.9826759 | W7: =DFC_Consolidado!H13 -> 17146.758 | X7: =Balanco_Consolidado!H9-Balanco_Consolidado!H21 -> 347634.12
A8: 2025 | B8: 7 | C8: 2025-07 | D8: 45839 | E8: =DRE_Consolidado!I4 -> 314185.58 | F8: =DRE_Consolidado!I6 -> 213188.47 | G8: =IF(DRE_Consolidado!H4=0,0,DRE_Consolidado!I4/DRE_Consolidado!H4-1) -> 0.0082123337 | I8: =DRE_Consolidado!I9 -> 0.44053193 | J8: =DRE_Consolidado!I18 -> 0.099145604 | K8: =DRE_Consolidado!I25 -> 0.045548553 | L8: =DRE_Consolidado!I17 -> 21136.7 | M8: =DRE_Consolidado!I24 -> 9710.4263 | N8: =IF(DRE_Consolidado!I6=0,0,Balanco_Consolidado!I6/DRE_Consolidado!I6*30) -> 20.832509 | O8: =IF(DRE_Consolidado!I7=0,0,Balanco_Consolidado!I7/(-DRE_Consolidado!I7)*30) -> 52.875119 | P8: =IF(DRE_Consolidado!I7=0,0,Balanco_Consolidado!I16/(-DRE_Consolidado!I7)*30) -> 43.726795 | Q8: =N8+O8-P8 -> 29.980833 | R8: =IF(Balanco_Consolidado!I21=0,0,Balanco_Consolidado!I9/Balanco_Consolidado!I21) -> 1.7112931 | S8: =Cronogramas!I18-Balanco_Consolidado!I5 -> -110752.26 | U8: =IF(Cronogramas!I22=0,0,DRE_Consolidado!I20/Cronogramas!I22) -> 3.2574475 | W8: =DFC_Consolidado!I13 -> 13170.184 | X8: =Balanco_Consolidado!I9-Balanco_Consolidado!I21 -> 324647.67
A9: 2025 | B9: 8 | C9: 2025-08 | D9: 45870 | E9: =DRE_Consolidado!J4 -> 276259.76 | F9: =DRE_Consolidado!J6 -> 187870.5 | G9: =IF(DRE_Consolidado!I4=0,0,DRE_Consolidado!J4/DRE_Consolidado!I4-1) -> -0.12071152 | I9: =DRE_Consolidado!J9 -> 0.44354769 | J9: =DRE_Consolidado!J18 -> 0.065162589 | K9: =DRE_Consolidado!J25 -> 0.018968628 | L9: =DRE_Consolidado!J17 -> 12242.128 | M9: =DRE_Consolidado!J24 -> 3563.6457 | N9: =IF(DRE_Consolidado!J6=0,0,Balanco_Consolidado!J6/DRE_Consolidado!J6*30) -> 21.405846 | O9: =IF(DRE_Consolidado!J7=0,0,Balanco_Consolidado!J7/(-DRE_Consolidado!J7)*30) -> 53.434741 | P9: =IF(DRE_Consolidado!J7=0,0,Balanco_Consolidado!J16/(-DRE_Consolidado!J7)*30) -> 44.133325 | Q9: =N9+O9-P9 -> 30.707263 | R9: =IF(Balanco_Consolidado!J21=0,0,Balanco_Consolidado!J9/Balanco_Consolidado!J21) -> 1.708437 | S9: =Cronogramas!J18-Balanco_Consolidado!J5 -> -88941.039 | U9: =IF(Cronogramas!J22=0,0,DRE_Consolidado!J20/Cronogramas!J22) -> 1.3702739 | W9: =DFC_Consolidado!J13 -> 11006.837 | X9: =Balanco_Consolidado!J9-Balanco_Consolidado!J21 -> 296167.69
A10: 2025 | B10: 9 | C10: 2025-09 | D10: 45901 | E10: =DRE_Consolidado!K4 -> 285962.46 | F10: =DRE_Consolidado!K6 -> 190314.06 | G10: =IF(DRE_Consolidado!J4=0,0,DRE_Consolidado!K4/DRE_Consolidado!J4-1) -> 0.035121655 | I10: =DRE_Consolidado!K9 -> 0.4468813 | J10: =DRE_Consolidado!K18 -> 0.072612913 | K10: =DRE_Consolidado!K25 -> 0.023552606 | L10: =DRE_Consolidado!K17 -> 13819.258 | M10: =DRE_Consolidado!K24 -> 4482.392 | N10: =IF(DRE_Consolidado!K6=0,0,Balanco_Consolidado!K6/DRE_Consolidado!K6*30) -> 22.859468 | O10: =IF(DRE_Consolidado!K7=0,0,Balanco_Consolidado!K7/(-DRE_Consolidado!K7)*30) -> 53.081718 | P10: =IF(DRE_Consolidado!K7=0,0,Balanco_Consolidado!K16/(-DRE_Consolidado!K7)*30) -> 43.496799 | Q10: =N10+O10-P10 -> 32.444387 | R10: =IF(Balanco_Consolidado!K21=0,0,Balanco_Consolidado!K9/Balanco_Consolidado!K21) -> 1.7027912 | S10: =Cronogramas!K18-Balanco_Consolidado!K5 -> -91963.564 | U10: =IF(Cronogramas!K22=0,0,DRE_Consolidado!K20/Cronogramas!K22) -> 1.7286711 | W10: =DFC_Consolidado!K13 -> 5877.236 | X10: =Balanco_Consolidado!K9-Balanco_Consolidado!K21 -> 298593.6
A11: 2025 | B11: 10 | C11: 2025-10 | D11: 45931 | E11: =DRE_Consolidado!L4 -> 299946.78 | F11: =DRE_Consolidado!L6 -> 206024.1 | G11: =IF(DRE_Consolidado!K4=0,0,DRE_Consolidado!L4/DRE_Consolidado!K4-1) -> 0.048902643 | I11: =DRE_Consolidado!L9 -> 0.43881589 | J11: =DRE_Consolidado!L18 -> 0.088076008 | K11: =DRE_Consolidado!L25 -> 0.035733457 | L11: =DRE_Consolidado!L17 -> 18145.78 | M11: =DRE_Consolidado!L24 -> 7361.9533 | N11: =IF(DRE_Consolidado!L6=0,0,Balanco_Consolidado!L6/DRE_Consolidado!L6*30) -> 21.547822 | O11: =IF(DRE_Consolidado!L7=0,0,Balanco_Consolidado!L7/(-DRE_Consolidado!L7)*30) -> 52.650839 | P11: =IF(DRE_Consolidado!L7=0,0,Balanco_Consolidado!L16/(-DRE_Consolidado!L7)*30) -> 43.491669 | Q11: =N11+O11-P11 -> 30.706992 | R11: =IF(Balanco_Consolidado!L21=0,0,Balanco_Consolidado!L9/Balanco_Consolidado!L21) -> 1.6883485 | S11: =Cronogramas!L18-Balanco_Consolidado!L5 -> -97501.569 | U11: =IF(Cronogramas!L22=0,0,DRE_Consolidado!L20/Cronogramas!L22) -> 2.7021497 | W11: =DFC_Consolidado!L13 -> 8628.366 | X11: =Balanco_Consolidado!L9-Balanco_Consolidado!L21 -> 303689.17
A12: 2025 | B12: 11 | C12: 2025-11 | D12: 45962 | E12: =DRE_Consolidado!M4 -> 356208.14 | F12: =DRE_Consolidado!M6 -> 239889.44 | G12: =IF(DRE_Consolidado!L4=0,0,DRE_Consolidado!M4/DRE_Consolidado!L4-1) -> 0.18757114 | I12: =DRE_Consolidado!M9 -> 0.44573631 | J12: =DRE_Consolidado!M18 -> 0.13449017 | K12: =DRE_Consolidado!M25 -> 0.069679485 | L12: =DRE_Consolidado!M17 -> 32262.772 | M12: =DRE_Consolidado!M24 -> 16715.373 | N12: =IF(DRE_Consolidado!M6=0,0,Balanco_Consolidado!M6/DRE_Consolidado!M6*30) -> 21.223791 | O12: =IF(DRE_Consolidado!M7=0,0,Balanco_Consolidado!M7/(-DRE_Consolidado!M7)*30) -> 53.036319 | P12: =IF(DRE_Consolidado!M7=0,0,Balanco_Consolidado!M16/(-DRE_Consolidado!M7)*30) -> 43.923685 | Q12: =N12+O12-P12 -> 30.336424 | R12: =IF(Balanco_Consolidado!M21=0,0,Balanco_Consolidado!M9/Balanco_Consolidado!M21) -> 1.6367904 | S12: =Cronogramas!M18-Balanco_Consolidado!M5 -> -117542.09 | U12: =IF(Cronogramas!M22=0,0,DRE_Consolidado!M20/Cronogramas!M22) -> 5.8948232 | W12: =DFC_Consolidado!M13 -> 23638.863 | X12: =Balanco_Consolidado!M9-Balanco_Consolidado!M21 -> 317660.16
A13: 2025 | B13: 12 | C13: 2025-12 | D13: 45992 | E13: =DRE_Consolidado!N4 -> 374250.54 | F13: =DRE_Consolidado!N6 -> 253334.37 | G13: =IF(DRE_Consolidado!M4=0,0,DRE_Consolidado!N4/DRE_Consolidado!M4-1) -> 0.050651285 | I13: =DRE_Consolidado!N9 -> 0.4451815 | J13: =DRE_Consolidado!N18 -> 0.14650564 | K13: =DRE_Consolidado!N25 -> 0.079101102 | L13: =DRE_Consolidado!N17 -> 37114.915 | M13: =DRE_Consolidado!N24 -> 20039.028 | N13: =IF(DRE_Consolidado!N6=0,0,Balanco_Consolidado!N6/DRE_Consolidado!N6*30) -> 21.545585 | O13: =IF(DRE_Consolidado!N7=0,0,Balanco_Consolidado!N7/(-DRE_Consolidado!N7)*30) -> 53.051929 | P13: =IF(DRE_Consolidado!N7=0,0,Balanco_Consolidado!N16/(-DRE_Consolidado!N7)*30) -> 43.742032 | Q13: =N13+O13-P13 -> 30.855482 | R13: =IF(Balanco_Consolidado!N21=0,0,Balanco_Consolidado!N9/Balanco_Consolidado!N21) -> 1.647847 | S13: =Cronogramas!N18-Balanco_Consolidado!N5 -> -130785.67 | T13: =IF((SUM(DRE_Consolidado!C17:DRE17))=0,0,S13/(SUM(DRE_Consolidado!C17:DRE17))) -> -0.12057604 | U13: =IF(Cronogramas!N22=0,0,DRE_Consolidado!N20/Cronogramas!N22) -> 7.0975647 | V13: =IF((Balanco_Consolidado!N27+S13)=0,0,(SUM(DRE_Consolidado!C20:DRE20))*(1-Premissas!$B$5)/(Balanco_Consolidado!N27+S13)) -> 0.78087776 | W13: =DFC_Consolidado!N13 -> 17043.592 | X13: =Balanco_Consolidado!N9-Balanco_Consolidado!N21 -> 334784.8
A14: 2026 | B14: 1 | C14: 2026-01 | D14: 46023 | E14: =DRE_Consolidado!O4 -> 274304.23 | F14: =DRE_Consolidado!O6 -> 182029.33 | G14: =IF(DRE_Consolidado!N4=0,0,DRE_Consolidado!O4/DRE_Consolidado!N4-1) -> -0.26705722 | H14: =IF(DRE_Consolidado!C4=0,0,DRE_Consolidado!O4/DRE_Consolidado!C4-1) -> 0.049437701 | I14: =DRE_Consolidado!O9 -> 0.44058955 | J14: =DRE_Consolidado!O18 -> 0.02342243 | K14: =DRE_Consolidado!O25 -> -0.01295255 | L14: =DRE_Consolidado!O17 -> 4263.5692 | M14: =DRE_Consolidado!O24 -> -2357.7441 | N14: =IF(DRE_Consolidado!O6=0,0,Balanco_Consolidado!O6/DRE_Consolidado!O6*30) -> 25.002457 | O14: =IF(DRE_Consolidado!O7=0,0,Balanco_Consolidado!O7/(-DRE_Consolidado!O7)*30) -> 52.666811 | P14: =IF(DRE_Consolidado!O7=0,0,Balanco_Consolidado!O16/(-DRE_Consolidado!O7)*30) -> 43.128742 | Q14: =N14+O14-P14 -> 34.540527 | R14: =IF(Balanco_Consolidado!O21=0,0,Balanco_Consolidado!O9/Balanco_Consolidado!O21) -> 1.7284111 | S14: =Cronogramas!O18-Balanco_Consolidado!O5 -> -134440.97 | T14: =IF((SUM(DRE_Consolidado!D17:DRE17))=0,0,S14/(SUM(DRE_Consolidado!D17:DRE17))) -> -0.12484152 | U14: =IF(Cronogramas!O22=0,0,DRE_Consolidado!O20/Cronogramas!O22) -> -0.38074423 | V14: =IF((Balanco_Consolidado!O27+S14)=0,0,(SUM(DRE_Consolidado!D20:DRE20))*(1-Premissas!$B$5)/(Balanco_Consolidado!O27+S14)) -> 0.78590528 | W14: =DFC_Consolidado!O13 -> 6385.7421 | X14: =Balanco_Consolidado!O9-Balanco_Consolidado!O21 -> 330605
A15: 2026 | B15: 2 | C15: 2026-02 | D15: 46054 | E15: =DRE_Consolidado!P4 -> 215905.8 | F15: =DRE_Consolidado!P6 -> 146499.33 | G15: =IF(DRE_Consolidado!O4=0,0,DRE_Consolidado!P4/DRE_Consolidado!O4-1) -> -0.21289657 | H15: =IF(DRE_Consolidado!D4=0,0,DRE_Consolidado!P4/DRE_Consolidado!D4-1) -> -0.13949016 | I15: =DRE_Consolidado!P9 -> 0.44743807 | J15: =DRE_Consolidado!P18 -> -0.054192786 | K15: =DRE_Consolidado!P25 -> -0.10096247 | L15: =DRE_Consolidado!P17 -> -7939.2069 | M15: =DRE_Consolidado!P24 -> -14790.935 | N15: =IF(DRE_Consolidado!P6=0,0,Balanco_Consolidado!P6/DRE_Consolidado!P6*30) -> 24.191667 | O15: =IF(DRE_Consolidado!P7=0,0,Balanco_Consolidado!P7/(-DRE_Consolidado!P7)*30) -> 53.676455 | P15: =IF(DRE_Consolidado!P7=0,0,Balanco_Consolidado!P16/(-DRE_Consolidado!P7)*30) -> 44.414042 | Q15: =N15+O15-P15 -> 33.45408 | R15: =IF(Balanco_Consolidado!P21=0,0,Balanco_Consolidado!P9/Balanco_Consolidado!P21) -> 1.7845893 | S15: =Cronogramas!P18-Balanco_Consolidado!P5 -> -140752.84 | T15: =IF((SUM(DRE_Consolidado!E17:DRE17))=0,0,S15/(SUM(DRE_Consolidado!E17:DRE17))) -> -0.13133391 | U15: =IF(Cronogramas!P22=0,0,DRE_Consolidado!P20/Cronogramas!P22) -> -2.8413737 | V15: =IF((Balanco_Consolidado!P27+S15)=0,0,(SUM(DRE_Consolidado!E20:DRE20))*(1-Premissas!$B$5)/(Balanco_Consolidado!P27+S15)) -> 0.81689533 | W15: =DFC_Consolidado!P13 -> 8509.3588 | X15: =Balanco_Consolidado!P9-Balanco_Consolidado!P21 -> 314543.28
A16: 2026 | B16: 3 | C16: 2026-03 | D16: 46082 | E16: =DRE_Consolidado!Q4 -> 292644.03 | F16: =DRE_Consolidado!Q6 -> 198000.09 | G16: =IF(DRE_Consolidado!P4=0,0,DRE_Consolidado!Q4/DRE_Consolidado!P4-1) -> 0.35542459 | H16: =IF(DRE_Consolidado!E4=0,0,DRE_Consolidado!Q4/DRE_Consolidado!E4-1) -> 0.05558416 | I16: =DRE_Consolidado!Q9 -> 0.43416386 | J16: =DRE_Consolidado!Q18 -> 0.044320995 | K16: =DRE_Consolidado!Q25 -> 0.0066362964 | L16: =DRE_Consolidado!Q17 -> 8775.561 | M16: =DRE_Consolidado!Q24 -> 1313.9873 | N16: =IF(DRE_Consolidado!Q6=0,0,Balanco_Consolidado!Q6/DRE_Consolidado!Q6*30) -> 23.257322 | O16: =IF(DRE_Consolidado!Q7=0,0,Balanco_Consolidado!Q7/(-DRE_Consolidado!Q7)*30) -> 53.356062 | P16: =IF(DRE_Consolidado!Q7=0,0,Balanco_Consolidado!Q16/(-DRE_Consolidado!Q7)*30) -> 44.02147 | Q16: =N16+O16-P16 -> 32.591914 | R16: =IF(Balanco_Consolidado!Q21=0,0,Balanco_Consolidado!Q9/Balanco_Consolidado!Q21) -> 1.6586034 | S16: =Cronogramas!Q18-Balanco_Consolidado!Q5 -> -126762.54 | T16: =IF((SUM(DRE_Consolidado!F17:DRE17))=0,0,S16/(SUM(DRE_Consolidado!F17:DRE17))) -> -0.11965903 | U16: =IF(Cronogramas!Q22=0,0,DRE_Consolidado!Q20/Cronogramas!Q22) -> 0.58835714 | V16: =IF((Balanco_Consolidado!Q27+S16)=0,0,(SUM(DRE_Consolidado!F20:DRE20))*(1-Premissas!$B$5)/(Balanco_Consolidado!Q27+S16)) -> 0.78487729 | W16: =DFC_Consolidado!Q13 -> -11020.3 | X16: =Balanco_Consolidado!Q9-Balanco_Consolidado!Q21 -> 313838.71
A17: 2026 | B17: 4 | C17: 2026-04 | D17: 46113 | E17: =DRE_Consolidado!R4 -> 261565.19 | F17: =DRE_Consolidado!R6 -> 178884.3 | G17: =IF(DRE_Consolidado!Q4=0,0,DRE_Consolidado!R4/DRE_Consolidado!Q4-1) -> -0.10620015 | H17: =IF(DRE_Consolidado!F4=0,0,DRE_Consolidado!R4/DRE_Consolidado!F4-1) -> -0.068976655 | I17: =DRE_Consolidado!R9 -> 0.44760551 | J17: =DRE_Consolidado!R18 -> 0.02508906 | K17: =DRE_Consolidado!R25 -> -0.013471866 | L17: =DRE_Consolidado!R17 -> 4488.039 | M17: =DRE_Consolidado!R24 -> -2409.9054 | N17: =IF(DRE_Consolidado!R6=0,0,Balanco_Consolidado!R6/DRE_Consolidado!R6*30) -> 23.75055 | O17: =IF(DRE_Consolidado!R7=0,0,Balanco_Consolidado!R7/(-DRE_Consolidado!R7)*30) -> 52.555181 | P17: =IF(DRE_Consolidado!R7=0,0,Balanco_Consolidado!R16/(-DRE_Consolidado!R7)*30) -> 43.556856 | Q17: =N17+O17-P17 -> 32.748875 | R17: =IF(Balanco_Consolidado!R21=0,0,Balanco_Consolidado!R9/Balanco_Consolidado!R21) -> 1.6432771 | S17: =Cronogramas!R18-Balanco_Consolidado!R5 -> -105711.9 | T17: =IF((SUM(DRE_Consolidado!G17:DRE17))=0,0,S17/(SUM(DRE_Consolidado!G17:DRE17))) -> -0.1011648 | U17: =IF(Cronogramas!R22=0,0,DRE_Consolidado!R20/Cronogramas!R22) -> -0.3147814 | V17: =IF((Balanco_Consolidado!R27+S17)=0,0,(SUM(DRE_Consolidado!G20:DRE20))*(1-Premissas!$B$5)/(Balanco_Consolidado!R27+S17)) -> 0.78397801 | W17: =DFC_Consolidado!R13 -> 7641.3397 | X17: =Balanco_Consolidado!R9-Balanco_Consolidado!R21 -> 283710.63
A18: 2026 | B18: 5 | C18: 2026-05 | D18: 46143 | E18: =DRE_Consolidado!S4 -> 340145.17 | F18: =DRE_Consolidado!S6 -> 232363.15 | G18: =IF(DRE_Consolidado!R4=0,0,DRE_Consolidado!S4/DRE_Consolidado!R4-1) -> 0.30042216 | H18: =IF(DRE_Consolidado!G4=0,0,DRE_Consolidado!S4/DRE_Consolidado!G4-1) -> 0.18990761 | I18: =DRE_Consolidado!S9 -> 0.43626137 | J18: =DRE_Consolidado!S18 -> 0.094300666 | K18: =DRE_Consolidado!S25 -> 0.042124432 | L18: =DRE_Consolidado!S17 -> 21912 | M18: =DRE_Consolidado!S24 -> 9788.1658 | N18: =IF(DRE_Consolidado!S6=0,0,Balanco_Consolidado!S6/DRE_Consolidado!S6*30) -> 25.376605 | O18: =IF(DRE_Consolidado!S7=0,0,Balanco_Consolidado!S7/(-DRE_Consolidado!S7)*30) -> 52.153338 | P18: =IF(DRE_Consolidado!S7=0,0,Balanco_Consolidado!S16/(-DRE_Consolidado!S7)*30) -> 42.504925 | Q18: =N18+O18-P18 -> 35.025018 | R18: =IF(Balanco_Consolidado!S21=0,0,Balanco_Consolidado!S9/Balanco_Consolidado!S21) -> 1.5610968 | S18: =Cronogramas!S18-Balanco_Consolidado!S5 -> -81807.689 | T18: =IF((SUM(DRE_Consolidado!H17:DRE17))=0,0,S18/(SUM(DRE_Consolidado!H17:DRE17))) -> -0.079372615 | U18: =IF(Cronogramas!S22=0,0,DRE_Consolidado!S20/Cronogramas!S22) -> 3.4286955 | V18: =IF((Balanco_Consolidado!S27+S18)=0,0,(SUM(DRE_Consolidado!H20:DRE20))*(1-Premissas!$B$5)/(Balanco_Consolidado!S27+S18)) -> 0.72688777 | W18: =DFC_Consolidado!S13 -> -20418.762 | X18: =Balanco_Consolidado!S9-Balanco_Consolidado!S21 -> 291016.2
A19: 2026 | B19: 6 | C19: 2026-06 | D19: 46174 | E19: =DRE_Consolidado!T4 -> 323173.51 | F19: =DRE_Consolidado!T6 -> 223242.79 | G19: =IF(DRE_Consolidado!S4=0,0,DRE_Consolidado!T4/DRE_Consolidado!S4-1) -> -0.049895343 | H19: =IF(DRE_Consolidado!H4=0,0,DRE_Consolidado!T4/DRE_Consolidado!H4-1) -> 0.037054338 | I19: =DRE_Consolidado!T9 -> 0.44051061 | J19: =DRE_Consolidado!T18 -> 0.087610797 | K19: =DRE_Consolidado!T25 -> 0.036272317 | L19: =DRE_Consolidado!T17 -> 19558.479 | M19: =DRE_Consolidado!T24 -> 8097.5333 | N19: =IF(DRE_Consolidado!T6=0,0,Balanco_Consolidado!T6/DRE_Consolidado!T6*30) -> 25.052766 | O19: =IF(DRE_Consolidado!T7=0,0,Balanco_Consolidado!T7/(-DRE_Consolidado!T7)*30) -> 52.298103 | P19: =IF(DRE_Consolidado!T7=0,0,Balanco_Consolidado!T16/(-DRE_Consolidado!T7)*30) -> 42.774048 | Q19: =N19+O19-P19 -> 34.576822 | R19: =IF(Balanco_Consolidado!T21=0,0,Balanco_Consolidado!T9/Balanco_Consolidado!T21) -> 1.5918003 | S19: =Cronogramas!T18-Balanco_Consolidado!T5 -> -96283.729 | T19: =IF((SUM(DRE_Consolidado!I17:DRE17))=0,0,S19/(SUM(DRE_Consolidado!I17:DRE17))) -> -0.095245622 | U19: =IF(Cronogramas!T22=0,0,DRE_Consolidado!T20/Cronogramas!T22) -> 2.9666054 | V19: =IF((Balanco_Consolidado!T27+S19)=0,0,(SUM(DRE_Consolidado!I20:DRE20))*(1-Premissas!$B$5)/(Balanco_Consolidado!T27+S19)) -> 0.71807615 | W19: =DFC_Consolidado!T13 -> 17824.681 | X19: =Balanco_Consolidado!T9-Balanco_Consolidado!T21 -> 296795.85
A20: 2026 | B20: 7 | C20: 2026-07 | D20: 46204 | E20: =DRE_Consolidado!U4 -> 349170.64 | F20: =DRE_Consolidado!U6 -> 236651.11 | G20: =IF(DRE_Consolidado!T4=0,0,DRE_Consolidado!U4/DRE_Consolidado!T4-1) -> 0.080443258 | H20: =IF(DRE_Consolidado!I4=0,0,DRE_Consolidado!U4/DRE_Consolidado!I4-1) -> 0.11135158 | I20: =DRE_Consolidado!U9 -> 0.43566919 | J20: =DRE_Consolidado!U18 -> 0.098916965 | K20: =DRE_Consolidado!U25 -> 0.045333892 | L20: =DRE_Consolidado!U17 -> 23408.81 | M20: =DRE_Consolidado!U24 -> 10728.316 | N20: =IF(DRE_Consolidado!U6=0,0,Balanco_Consolidado!U6/DRE_Consolidado!U6*30) -> 23.141866 | O20: =IF(DRE_Consolidado!U7=0,0,Balanco_Consolidado!U7/(-DRE_Consolidado!U7)*30) -> 52.364511 | P20: =IF(DRE_Consolidado!U7=0,0,Balanco_Consolidado!U16/(-DRE_Consolidado!U7)*30) -> 43.253868 | Q20: =N20+O20-P20 -> 32.25251 | R20: =IF(Balanco_Consolidado!U21=0,0,Balanco_Consolidado!U9/Balanco_Consolidado!U21) -> 1.4990229 | S20: =Cronogramas!U18-Balanco_Consolidado!U5 -> -126706.59 | T20: =IF((SUM(DRE_Consolidado!J17:DRE17))=0,0,S20/(SUM(DRE_Consolidado!J17:DRE17))) -> -0.12801716 | U20: =IF(Cronogramas!U22=0,0,DRE_Consolidado!U20/Cronogramas!U22) -> 3.8724264 | V20: =IF((Balanco_Consolidado!U27+S20)=0,0,(SUM(DRE_Consolidado!J20:DRE20))*(1-Premissas!$B$5)/(Balanco_Consolidado!U27+S20)) -> 0.72509846 | W20: =DFC_Consolidado!U13 -> 33972.629 | X20: =Balanco_Consolidado!U9-Balanco_Consolidado!U21 -> 305034.74
A21: 2026 | B21: 8 | C21: 2026-08 | D21: 46235 | E21: =DRE_Consolidado!V4 -> 323651.36 | F21: =DRE_Consolidado!V6 -> 218668.09 | G21: =IF(DRE_Consolidado!U4=0,0,DRE_Consolidado!V4/DRE_Consolidado!U4-1) -> -0.073085412 | H21: =IF(DRE_Consolidado!J4=0,0,DRE_Consolidado!V4/DRE_Consolidado!J4-1) -> 0.17154724 | I21: =DRE_Consolidado!V9 -> 0.43763014 | J21: =DRE_Consolidado!V18 -> 0.079011153 | K21: =DRE_Consolidado!V25 -> 0.02971461 | L21: =DRE_Consolidado!V17 -> 17277.218 | M21: =DRE_Consolidado!V24 -> 6497.6369 | N21: =IF(DRE_Consolidado!V6=0,0,Balanco_Consolidado!V6/DRE_Consolidado!V6*30) -> 23.763306 | O21: =IF(DRE_Consolidado!V7=0,0,Balanco_Consolidado!V7/(-DRE_Consolidado!V7)*30) -> 52.279258 | P21: =IF(DRE_Consolidado!V7=0,0,Balanco_Consolidado!V16/(-DRE_Consolidado!V7)*30) -> 43.06819 | Q21: =N21+O21-P21 -> 32.974374 | R21: =IF(Balanco_Consolidado!V21=0,0,Balanco_Consolidado!V9/Balanco_Consolidado!V21) -> 1.5299288 | S21: =Cronogramas!V18-Balanco_Consolidado!V5 -> -138079.42 | T21: =IF((SUM(DRE_Consolidado!K17:DRE17))=0,0,S21/(SUM(DRE_Consolidado!K17:DRE17))) -> -0.14125477 | U21: =IF(Cronogramas!V22=0,0,DRE_Consolidado!V20/Cronogramas!V22) -> 1.9699903 | V21: =IF((Balanco_Consolidado!V27+S21)=0,0,(SUM(DRE_Consolidado!K20:DRE20))*(1-Premissas!$B$5)/(Balanco_Consolidado!V27+S21)) -> 0.72373846 | W21: =DFC_Consolidado!V13 -> 14652.85 | X21: =Balanco_Consolidado!V9-Balanco_Consolidado!V21 -> 309340.03
A22: 2026 | B22: 9 | C22: 2026-09 | D22: 46266 | E22: =DRE_Consolidado!W4 -> 322444.6 | F22: =DRE_Consolidado!W6 -> 217463.98 | G22: =IF(DRE_Consolidado!V4=0,0,DRE_Consolidado!W4/DRE_Consolidado!V4-1) -> -0.00372858 | H22: =IF(DRE_Consolidado!K4=0,0,DRE_Consolidado!W4/DRE_Consolidado!K4-1) -> 0.12757668 | I22: =DRE_Consolidado!W9 -> 0.43027 | J22: =DRE_Consolidado!W18 -> 0.069500801 | K22: =DRE_Consolidado!W25 -> 0.023647937 | L22: =DRE_Consolidado!W17 -> 15113.921 | M22: =DRE_Consolidado!W24 -> 5142.5746 | N22: =IF(DRE_Consolidado!W6=0,0,Balanco_Consolidado!W6/DRE_Consolidado!W6*30) -> 23.096856 | O22: =IF(DRE_Consolidado!W7=0,0,Balanco_Consolidado!W7/(-DRE_Consolidado!W7)*30) -> 52.653484 | P22: =IF(DRE_Consolidado!W7=0,0,Balanco_Consolidado!W16/(-DRE_Consolidado!W7)*30) -> 43.35049 | Q22: =N22+O22-P22 -> 32.39985 | R22: =IF(Balanco_Consolidado!W21=0,0,Balanco_Consolidado!W9/Balanco_Consolidado!W21) -> 1.5335336 | S22: =Cronogramas!W18-Balanco_Consolidado!W5 -> -150471.68 | T22: =IF((SUM(DRE_Consolidado!L17:DRE17))=0,0,S22/(SUM(DRE_Consolidado!L17:DRE17))) -> -0.15613936 | U22: =IF(Cronogramas!W22=0,0,DRE_Consolidado!W20/Cronogramas!W22) -> 1.6069759 | V22: =IF((Balanco_Consolidado!W27+S22)=0,0,(SUM(DRE_Consolidado!L20:DRE20))*(1-Premissas!$B$5)/(Balanco_Consolidado!W27+S22)) -> 0.72365015 | W22: =DFC_Consolidado!W13 -> 15654.224 | X22: =Balanco_Consolidado!W9-Balanco_Consolidado!W21 -> 312335.5
A23: 2026 | B23: 10 | C23: 2026-10 | D23: 46296 | E23: =DRE_Consolidado!X4 -> 291366.8 | F23: =DRE_Consolidado!X6 -> 199075.16 | G23: =IF(DRE_Consolidado!W4=0,0,DRE_Consolidado!X4/DRE_Consolidado!W4-1) -> -0.096381828 | H23: =IF(DRE_Consolidado!L4=0,0,DRE_Consolidado!X4/DRE_Consolidado!L4-1) -> -0.028605008 | I23: =DRE_Consolidado!X9 -> 0.44056394 | J23: =DRE_Consolidado!X18 -> 0.052805879 | K23: =DRE_Consolidado!X25 -> 0.010979858 | L23: =DRE_Consolidado!X17 -> 10512.339 | M23: =DRE_Consolidado!X24 -> 2185.8169 | N23: =IF(DRE_Consolidado!X6=0,0,Balanco_Consolidado!X6/DRE_Consolidado!X6*30) -> 25.494474 | O23: =IF(DRE_Consolidado!X7=0,0,Balanco_Consolidado!X7/(-DRE_Consolidado!X7)*30) -> 52.723159 | P23: =IF(DRE_Consolidado!X7=0,0,Balanco_Consolidado!X16/(-DRE_Consolidado!X7)*30) -> 43.180444 | Q23: =N23+O23-P23 -> 35.03719 | R23: =IF(Balanco_Consolidado!X21=0,0,Balanco_Consolidado!X9/Balanco_Consolidado!X21) -> 1.5678528 | S23: =Cronogramas!X18-Balanco_Consolidado!X5 -> -142472.8 | T23: =IF((SUM(DRE_Consolidado!M17:DRE17))=0,0,S23/(SUM(DRE_Consolidado!M17:DRE17))) -> -0.15067631 | U23: =IF(Cronogramas!X22=0,0,DRE_Consolidado!X20/Cronogramas!X22) -> 0.79213744 | V23: =IF((Balanco_Consolidado!X27+S23)=0,0,(SUM(DRE_Consolidado!M20:DRE20))*(1-Premissas!$B$5)/(Balanco_Consolidado!X27+S23)) -> 0.69506926 | W23: =DFC_Consolidado!X13 -> -5012.7558 | X23: =Balanco_Consolidado!X9-Balanco_Consolidado!X21 -> 312674.93
A24: 2026 | B24: 11 | C24: 2026-11 | D24: 46327 | E24: =DRE_Consolidado!Y4 -> 370744.2 | F24: =DRE_Consolidado!Y6 -> 252884.02 | G24: =IF(DRE_Consolidado!X4=0,0,DRE_Consolidado!Y4/DRE_Consolidado!X4-1) -> 0.27243118 | H24: =IF(DRE_Consolidado!M4=0,0,DRE_Consolidado!Y4/DRE_Consolidado!M4-1) -> 0.04080777 | I24: =DRE_Consolidado!Y9 -> 0.4359518 | J24: =DRE_Consolidado!Y18 -> 0.11538327 | K24: =DRE_Consolidado!Y25 -> 0.057181403 | L24: =DRE_Consolidado!Y17 -> 29178.585 | M24: =DRE_Consolidado!Y24 -> 14460.263 | N24: =IF(DRE_Consolidado!Y6=0,0,Balanco_Consolidado!Y6/DRE_Consolidado!Y6*30) -> 24.263835 | O24: =IF(DRE_Consolidado!Y7=0,0,Balanco_Consolidado!Y7/(-DRE_Consolidado!Y7)*30) -> 52.977575 | P24: =IF(DRE_Consolidado!Y7=0,0,Balanco_Consolidado!Y16/(-DRE_Consolidado!Y7)*30) -> 43.524175 | Q24: =N24+O24-P24 -> 33.717234 | R24: =IF(Balanco_Consolidado!Y21=0,0,Balanco_Consolidado!Y9/Balanco_Consolidado!Y21) -> 1.5114146 | S24: =Cronogramas!Y18-Balanco_Consolidado!Y5 -> -147403.39 | T24: =IF((SUM(DRE_Consolidado!N17:DRE17))=0,0,S24/(SUM(DRE_Consolidado!N17:DRE17))) -> -0.16139777 | U24: =IF(Cronogramas!Y22=0,0,DRE_Consolidado!Y20/Cronogramas!Y22) -> 4.229271 | V24: =IF((Balanco_Consolidado!Y27+S24)=0,0,(SUM(DRE_Consolidado!N20:DRE20))*(1-Premissas!$B$5)/(Balanco_Consolidado!Y27+S24)) -> 0.65148912 | W24: =DFC_Consolidado!Y13 -> 8723.8519 | X24: =Balanco_Consolidado!Y9-Balanco_Consolidado!Y21 -> 324513.29
A25: 2026 | B25: 12 | C25: 2026-12 | D25: 46357 | E25: =DRE_Consolidado!Z4 -> 398263.15 | F25: =DRE_Consolidado!Z6 -> 270786.15 | G25: =IF(DRE_Consolidado!Y4=0,0,DRE_Consolidado!Z4/DRE_Consolidado!Y4-1) -> 0.074226245 | H25: =IF(DRE_Consolidado!N4=0,0,DRE_Consolidado!Z4/DRE_Consolidado!N4-1) -> 0.064161858 | I25: =DRE_Consolidado!Z9 -> 0.4366833 | J25: =DRE_Consolidado!Z18 -> 0.13294632 | K25: =DRE_Consolidado!Z25 -> 0.070138221 | L25: =DRE_Consolidado!Z17 -> 36000.021 | M25: =DRE_Consolidado!Z24 -> 18992.459 | N25: =IF(DRE_Consolidado!Z6=0,0,Balanco_Consolidado!Z6/DRE_Consolidado!Z6*30) -> 23.242772 | O25: =IF(DRE_Consolidado!Z7=0,0,Balanco_Consolidado!Z7/(-DRE_Consolidado!Z7)*30) -> 52.920495 | P25: =IF(DRE_Consolidado!Z7=0,0,Balanco_Consolidado!Z16/(-DRE_Consolidado!Z7)*30) -> 43.70398 | Q25: =N25+O25-P25 -> 32.459287 | R25: =IF(Balanco_Consolidado!Z21=0,0,Balanco_Consolidado!Z9/Balanco_Consolidado!Z21) -> 1.5133668 | S25: =Cronogramas!Z18-Balanco_Consolidado!Z5 -> -173671.04 | T25: =IF((SUM(DRE_Consolidado!O17:DRE17))=0,0,S25/(SUM(DRE_Consolidado!O17:DRE17))) -> -0.19821441 | U25: =IF(Cronogramas!Z22=0,0,DRE_Consolidado!Z20/Cronogramas!Z22) -> 5.5587355 | V25: =IF((Balanco_Consolidado!Z27+S25)=0,0,(SUM(DRE_Consolidado!O20:DRE20))*(1-Premissas!$B$5)/(Balanco_Consolidado!Z27+S25)) -> 0.62234892 | W25: =DFC_Consolidado!Z13 -> 30329.444 | X25: =Balanco_Consolidado!Z9-Balanco_Consolidado!Z21 -> 340649.15
A26: 2027 | B26: 1 | C26: 2027-01 | D26: 46388 | E26: =DRE_Consolidado!AA4 -> 294243.67 | F26: =DRE_Consolidado!AA6 -> 197737.78 | G26: =IF(DRE_Consolidado!Z4=0,0,DRE_Consolidado!AA4/DRE_Consolidado!Z4-1) -> -0.26118278 | H26: =IF(DRE_Consolidado!O4=0,0,DRE_Consolidado!AA4/DRE_Consolidado!O4-1) -> 0.072690986 | I26: =DRE_Consolidado!AA9 -> 0.43796863 | J26: =DRE_Consolidado!AA18 -> 0.011656474 | K26: =DRE_Consolidado!AA25 -> -0.023627006 | L26: =DRE_Consolidado!AA17 -> 2304.9253 | M26: =DRE_Consolidado!AA24 -> -4671.9516 | N26: =IF(DRE_Consolidado!AA6=0,0,Balanco_Consolidado!AA6/DRE_Consolidado!AA6*30) -> 28.357883 | O26: =IF(DRE_Consolidado!AA7=0,0,Balanco_Consolidado!AA7/(-DRE_Consolidado!AA7)*30) -> 52.523049 | P26: =IF(DRE_Consolidado!AA7=0,0,Balanco_Consolidado!AA16/(-DRE_Consolidado!AA7)*30) -> 42.911737 | Q26: =N26+O26-P26 -> 37.969195 | R26: =IF(Balanco_Consolidado!AA21=0,0,Balanco_Consolidado!AA9/Balanco_Consolidado!AA21) -> 1.6025249 | S26: =Cronogramas!AA18-Balanco_Consolidado!AA5 -> -166670.49 | T26: =IF((SUM(DRE_Consolidado!P17:DRE17))=0,0,S26/(SUM(DRE_Consolidado!P17:DRE17))) -> -0.19115471 | U26: =IF(Cronogramas!AA22=0,0,DRE_Consolidado!AA20/Cronogramas!AA22) -> -0.74336951 | V26: =IF((Balanco_Consolidado!AA27+S26)=0,0,(SUM(DRE_Consolidado!P20:DRE20))*(1-Premissas!$B$5)/(Balanco_Consolidado!AA27+S26)) -> 0.62168415 | W26: =DFC_Consolidado!AA13 -> -4034.4853 | X26: =Balanco_Consolidado!AA9-Balanco_Consolidado!AA21 -> 334241.05
A27: 2027 | B27: 2 | C27: 2027-02 | D27: 46419 | E27: =DRE_Consolidado!AB4 -> 231083.96 | F27: =DRE_Consolidado!AB6 -> 156413.74 | G27: =IF(DRE_Consolidado!AA4=0,0,DRE_Consolidado!AB4/DRE_Consolidado!AA4-1) -> -0.21465105 | H27: =IF(DRE_Consolidado!P4=0,0,DRE_Consolidado!AB4/DRE_Consolidado!P4-1) -> 0.070299928 | I27: =DRE_Consolidado!AB9 -> 0.44525826 | J27: =DRE_Consolidado!AB18 -> -0.075535457 | K27: =DRE_Consolidado!AB25 -> -0.12044477 | L27: =DRE_Consolidado!AB17 -> -11814.783 | M27: =DRE_Consolidado!AB24 -> -18839.217 | N27: =IF(DRE_Consolidado!AB6=0,0,Balanco_Consolidado!AB6/DRE_Consolidado!AB6*30) -> 27.099965 | O27: =IF(DRE_Consolidado!AB7=0,0,Balanco_Consolidado!AB7/(-DRE_Consolidado!AB7)*30) -> 53.693753 | P27: =IF(DRE_Consolidado!AB7=0,0,Balanco_Consolidado!AB16/(-DRE_Consolidado!AB7)*30) -> 44.412493 | Q27: =N27+O27-P27 -> 36.381225 | R27: =IF(Balanco_Consolidado!AB21=0,0,Balanco_Consolidado!AB9/Balanco_Consolidado!AB21) -> 1.6437325 | S27: =Cronogramas!AB18-Balanco_Consolidado!AB5 -> -183453.77 | T27: =IF((SUM(DRE_Consolidado!Q17:DRE17))=0,0,S27/(SUM(DRE_Consolidado!Q17:DRE17))) -> -0.20850495 | U27: =IF(Cronogramas!AB22=0,0,DRE_Consolidado!AB20/Cronogramas!AB22) -> -3.4738944 | V27: =IF((Balanco_Consolidado!AB27+S27)=0,0,(SUM(DRE_Consolidado!Q20:DRE20))*(1-Premissas!$B$5)/(Balanco_Consolidado!AB27+S27)) -> 0.68288724 | W27: =DFC_Consolidado!AB13 -> 19129.488 | X27: =Balanco_Consolidado!AB9-Balanco_Consolidado!AB21 -> 314305.09
A28: 2027 | B28: 3 | C28: 2027-03 | D28: 46447 | E28: =DRE_Consolidado!AC4 -> 312976.64 | F28: =DRE_Consolidado!AC6 -> 210873.31 | G28: =IF(DRE_Consolidado!AB4=0,0,DRE_Consolidado!AC4/DRE_Consolidado!AB4-1) -> 0.35438493 | H28: =IF(DRE_Consolidado!Q4=0,0,DRE_Consolidado!AC4/DRE_Consolidado!Q4-1) -> 0.069478973 | I28: =DRE_Consolidado!AC9 -> 0.43145472 | J28: =DRE_Consolidado!AC18 -> 0.026669655 | K28: =DRE_Consolidado!AC25 -> -0.0055522659 | L28: =DRE_Consolidado!AC17 -> 5623.9185 | M28: =DRE_Consolidado!AC24 -> -1170.8247 | N28: =IF(DRE_Consolidado!AC6=0,0,Balanco_Consolidado!AC6/DRE_Consolidado!AC6*30) -> 26.258026 | O28: =IF(DRE_Consolidado!AC7=0,0,Balanco_Consolidado!AC7/(-DRE_Consolidado!AC7)*30) -> 53.357925 | P28: =IF(DRE_Consolidado!AC7=0,0,Balanco_Consolidado!AC16/(-DRE_Consolidado!AC7)*30) -> 44.023402 | Q28: =N28+O28-P28 -> 35.592549 | R28: =IF(Balanco_Consolidado!AC21=0,0,Balanco_Consolidado!AC9/Balanco_Consolidado!AC21) -> 1.5571789 | S28: =Cronogramas!AC18-Balanco_Consolidado!AC5 -> -160181.04 | T28: =IF((SUM(DRE_Consolidado!R17:DRE17))=0,0,S28/(SUM(DRE_Consolidado!R17:DRE17))) -> -0.18388833 | U28: =IF(Cronogramas!AC22=0,0,DRE_Consolidado!AC20/Cronogramas!AC22) -> -0.1314332 | V28: =IF((Balanco_Consolidado!AC27+S28)=0,0,(SUM(DRE_Consolidado!R20:DRE20))*(1-Premissas!$B$5)/(Balanco_Consolidado!AC27+S28)) -> 0.65110109 | W28: =DFC_Consolidado!AC13 -> -20109.634 | X28: =Balanco_Consolidado!AC9-Balanco_Consolidado!AC21 -> 311247
A29: 2027 | B29: 4 | C29: 2027-04 | D29: 46478 | E29: =DRE_Consolidado!AD4 -> 280393.32 | F29: =DRE_Consolidado!AD6 -> 191146.55 | G29: =IF(DRE_Consolidado!AC4=0,0,DRE_Consolidado!AD4/DRE_Consolidado!AC4-1) -> -0.10410784 | H29: =IF(DRE_Consolidado!R4=0,0,DRE_Consolidado!AD4/DRE_Consolidado!R4-1) -> 0.071982535 | I29: =DRE_Consolidado!AD9 -> 0.4469898 | J29: =DRE_Consolidado!AD18 -> 0.0091242237 | K29: =DRE_Consolidado!AD25 -> -0.027094536 | L29: =DRE_Consolidado!AD17 -> 1744.0639 | M29: =DRE_Consolidado!AD24 -> -5179.0272 | N29: =IF(DRE_Consolidado!AD6=0,0,Balanco_Consolidado!AD6/DRE_Consolidado!AD6*30) -> 26.402963 | O29: =IF(DRE_Consolidado!AD7=0,0,Balanco_Consolidado!AD7/(-DRE_Consolidado!AD7)*30) -> 52.590493 | P29: =IF(DRE_Consolidado!AD7=0,0,Balanco_Consolidado!AD16/(-DRE_Consolidado!AD7)*30) -> 43.579336 | Q29: =N29+O29-P29 -> 35.414121 | R29: =IF(Balanco_Consolidado!AD21=0,0,Balanco_Consolidado!AD9/Balanco_Consolidado!AD21) -> 1.5616045 | S29: =Cronogramas!AD18-Balanco_Consolidado!AD5 -> -149784.78 | T29: =IF((SUM(DRE_Consolidado!S17:DRE17))=0,0,S29/(SUM(DRE_Consolidado!S17:DRE17))) -> -0.17284393 | U29: =IF(Cronogramas!AD22=0,0,DRE_Consolidado!AD20/Cronogramas!AD22) -> -0.96518147 | V29: =IF((Balanco_Consolidado!AD27+S29)=0,0,(SUM(DRE_Consolidado!S20:DRE20))*(1-Premissas!$B$5)/(Balanco_Consolidado!AD27+S29)) -> 0.66806346 | W29: =DFC_Consolidado!AD13 -> 9765.3842 | X29: =Balanco_Consolidado!AD9-Balanco_Consolidado!AD21 -> 287206.04
A30: 2027 | B30: 5 | C30: 2027-05 | D30: 46508 | E30: =DRE_Consolidado!AE4 -> 365041.04 | F30: =DRE_Consolidado!AE6 -> 245083.76 | G30: =IF(DRE_Consolidado!AD4=0,0,DRE_Consolidado!AE4/DRE_Consolidado!AD4-1) -> 0.30188924 | H30: =IF(DRE_Consolidado!S4=0,0,DRE_Consolidado!AE4/DRE_Consolidado!S4-1) -> 0.0731919 | I30: =DRE_Consolidado!AE9 -> 0.43530175 | J30: =DRE_Consolidado!AE18 -> 0.077878522 | K30: =DRE_Consolidado!AE25 -> 0.032704529 | L30: =DRE_Consolidado!AE17 -> 19086.761 | M30: =DRE_Consolidado!AE24 -> 8015.3489 | N30: =IF(DRE_Consolidado!AE6=0,0,Balanco_Consolidado!AE6/DRE_Consolidado!AE6*30) -> 28.349858 | O30: =IF(DRE_Consolidado!AE7=0,0,Balanco_Consolidado!AE7/(-DRE_Consolidado!AE7)*30) -> 52.175716 | P30: =IF(DRE_Consolidado!AE7=0,0,Balanco_Consolidado!AE16/(-DRE_Consolidado!AE7)*30) -> 42.546388 | Q30: =N30+O30-P30 -> 37.979185 | R30: =IF(Balanco_Consolidado!AE21=0,0,Balanco_Consolidado!AE9/Balanco_Consolidado!AE21) -> 1.5011892 | S30: =Cronogramas!AE18-Balanco_Consolidado!AE5 -> -120325.8 | T30: =IF((SUM(DRE_Consolidado!T17:DRE17))=0,0,S30/(SUM(DRE_Consolidado!T17:DRE17))) -> -0.14245172 | U30: =IF(Cronogramas!AE22=0,0,DRE_Consolidado!AE20/Cronogramas!AE22) -> 2.8474119 | V30: =IF((Balanco_Consolidado!AE27+S30)=0,0,(SUM(DRE_Consolidado!T20:DRE20))*(1-Premissas!$B$5)/(Balanco_Consolidado!AE27+S30)) -> 0.60447924 | W30: =DFC_Consolidado!AE13 -> -25782.721 | X30: =Balanco_Consolidado!AE9-Balanco_Consolidado!AE21 -> 292875.49
A31: 2027 | B31: 6 | C31: 2027-06 | D31: 46539 | E31: =DRE_Consolidado!AF4 -> 346635.36 | F31: =DRE_Consolidado!AF6 -> 234113.33 | G31: =IF(DRE_Consolidado!AE4=0,0,DRE_Consolidado!AF4/DRE_Consolidado!AE4-1) -> -0.050420865 | H31: =IF(DRE_Consolidado!T4=0,0,DRE_Consolidado!AF4/DRE_Consolidado!T4-1) -> 0.072598297 | I31: =DRE_Consolidado!AF9 -> 0.43981784 | J31: =DRE_Consolidado!AF18 -> 0.069137769 | K31: =DRE_Consolidado!AF25 -> 0.025525648 | L31: =DRE_Consolidado!AF17 -> 16186.073 | M31: =DRE_Consolidado!AF24 -> 5975.8942 | N31: =IF(DRE_Consolidado!AF6=0,0,Balanco_Consolidado!AF6/DRE_Consolidado!AF6*30) -> 27.728668 | O31: =IF(DRE_Consolidado!AF7=0,0,Balanco_Consolidado!AF7/(-DRE_Consolidado!AF7)*30) -> 52.34459 | P31: =IF(DRE_Consolidado!AF7=0,0,Balanco_Consolidado!AF16/(-DRE_Consolidado!AF7)*30) -> 42.906047 | Q31: =N31+O31-P31 -> 37.167211 | R31: =IF(Balanco_Consolidado!AF21=0,0,Balanco_Consolidado!AF9/Balanco_Consolidado!AF21) -> 1.5335692 | S31: =Cronogramas!AF18-Balanco_Consolidado!AF5 -> -138820.8 | T31: =IF((SUM(DRE_Consolidado!U17:DRE17))=0,0,S31/(SUM(DRE_Consolidado!U17:DRE17))) -> -0.16824331 | U31: =IF(Cronogramas!AF22=0,0,DRE_Consolidado!AF20/Cronogramas!AF22) -> 2.3175597 | V31: =IF((Balanco_Consolidado!AF27+S31)=0,0,(SUM(DRE_Consolidado!U20:DRE20))*(1-Premissas!$B$5)/(Balanco_Consolidado!AF27+S31)) -> 0.60198861 | W31: =DFC_Consolidado!AF13 -> 22006.701 | X31: =Balanco_Consolidado!AF9-Balanco_Consolidado!AF21 -> 296699.3
A32: 2027 | B32: 7 | C32: 2027-07 | D32: 46569 | E32: =DRE_Consolidado!AG4 -> 374119.68 | F32: =DRE_Consolidado!AG6 -> 253388.37 | G32: =IF(DRE_Consolidado!AF4=0,0,DRE_Consolidado!AG4/DRE_Consolidado!AF4-1) -> 0.079288875 | H32: =IF(DRE_Consolidado!U4=0,0,DRE_Consolidado!AG4/DRE_Consolidado!U4-1) -> 0.071452296 | I32: =DRE_Consolidado!AG9 -> 0.4338622 | J32: =DRE_Consolidado!AG18 -> 0.086123592 | K32: =DRE_Consolidado!AG25 -> 0.038890241 | L32: =DRE_Consolidado!AG17 -> 21822.717 | M32: =DRE_Consolidado!AG24 -> 9854.3348 | N32: =IF(DRE_Consolidado!AG6=0,0,Balanco_Consolidado!AG6/DRE_Consolidado!AG6*30) -> 25.885591 | O32: =IF(DRE_Consolidado!AG7=0,0,Balanco_Consolidado!AG7/(-DRE_Consolidado!AG7)*30) -> 52.352074 | P32: =IF(DRE_Consolidado!AG7=0,0,Balanco_Consolidado!AG16/(-DRE_Consolidado!AG7)*30) -> 43.233644 | Q32: =N32+O32-P32 -> 35.004021 | R32: =IF(Balanco_Consolidado!AG21=0,0,Balanco_Consolidado!AG9/Balanco_Consolidado!AG21) -> 1.5267774 | S32: =Cronogramas!AG18-Balanco_Consolidado!AG5 -> -157268.61 | T32: =IF((SUM(DRE_Consolidado!V17:DRE17))=0,0,S32/(SUM(DRE_Consolidado!V17:DRE17))) -> -0.19616635 | U32: =IF(Cronogramas!AG22=0,0,DRE_Consolidado!AG20/Cronogramas!AG22) -> 3.8578558 | V32: =IF((Balanco_Consolidado!AG27+S32)=0,0,(SUM(DRE_Consolidado!V20:DRE20))*(1-Premissas!$B$5)/(Balanco_Consolidado!AG27+S32)) -> 0.59031639 | W32: =DFC_Consolidado!AG13 -> 22248.642 | X32: =Balanco_Consolidado!AG9-Balanco_Consolidado!AG21 -> 304144.11
A33: 2027 | B33: 8 | C33: 2027-08 | D33: 46600 | E33: =DRE_Consolidado!AH4 -> 347007.54 | F33: =DRE_Consolidado!AH6 -> 234444.58 | G33: =IF(DRE_Consolidado!AG4=0,0,DRE_Consolidado!AH4/DRE_Consolidado!AG4-1) -> -0.07246918 | H33: =IF(DRE_Consolidado!V4=0,0,DRE_Consolidado!AH4/DRE_Consolidado!V4-1) -> 0.072164619 | I33: =DRE_Consolidado!AH9 -> 0.4357171 | J33: =DRE_Consolidado!AH18 -> 0.065482508 | K33: =DRE_Consolidado!AH25 -> 0.024497102 | L33: =DRE_Consolidado!AH17 -> 15352.019 | M33: =DRE_Consolidado!AH24 -> 5743.2126 | N33: =IF(DRE_Consolidado!AH6=0,0,Balanco_Consolidado!AH6/DRE_Consolidado!AH6*30) -> 26.758061 | O33: =IF(DRE_Consolidado!AH7=0,0,Balanco_Consolidado!AH7/(-DRE_Consolidado!AH7)*30) -> 52.314181 | P33: =IF(DRE_Consolidado!AH7=0,0,Balanco_Consolidado!AH16/(-DRE_Consolidado!AH7)*30) -> 43.042869 | Q33: =N33+O33-P33 -> 36.029373 | R33: =IF(Balanco_Consolidado!AH21=0,0,Balanco_Consolidado!AH9/Balanco_Consolidado!AH21) -> 1.5613933 | S33: =Cronogramas!AH18-Balanco_Consolidado!AH5 -> -167495.97 | T33: =IF((SUM(DRE_Consolidado!W17:DRE17))=0,0,S33/(SUM(DRE_Consolidado!W17:DRE17))) -> -0.21352482 | U33: =IF(Cronogramas!AH22=0,0,DRE_Consolidado!AH20/Cronogramas!AH22) -> 2.3753776 | V33: =IF((Balanco_Consolidado!AH27+S33)=0,0,(SUM(DRE_Consolidado!W20:DRE20))*(1-Premissas!$B$5)/(Balanco_Consolidado!AH27+S33)) -> 0.58143156 | W33: =DFC_Consolidado!AH13 -> 13744.024 | X33: =Balanco_Consolidado!AH9-Balanco_Consolidado!AH21 -> 307791.25
A34: 2027 | B34: 9 | C34: 2027-09 | D34: 46631 | E34: =DRE_Consolidado!AI4 -> 345213.61 | F34: =DRE_Consolidado!AI6 -> 232515.06 | G34: =IF(DRE_Consolidado!AH4=0,0,DRE_Consolidado!AI4/DRE_Consolidado!AH4-1) -> -0.0051697076 | H34: =IF(DRE_Consolidado!W4=0,0,DRE_Consolidado!AI4/DRE_Consolidado!W4-1) -> 0.07061371 | I34: =DRE_Consolidado!AI9 -> 0.427916 | J34: =DRE_Consolidado!AI18 -> 0.054748807 | K34: =DRE_Consolidado!AI25 -> 0.017535625 | L34: =DRE_Consolidado!AI17 -> 12729.922 | M34: =DRE_Consolidado!AI24 -> 4077.2968 | N34: =IF(DRE_Consolidado!AI6=0,0,Balanco_Consolidado!AI6/DRE_Consolidado!AI6*30) -> 26.216563 | O34: =IF(DRE_Consolidado!AI7=0,0,Balanco_Consolidado!AI7/(-DRE_Consolidado!AI7)*30) -> 52.626113 | P34: =IF(DRE_Consolidado!AI7=0,0,Balanco_Consolidado!AI16/(-DRE_Consolidado!AI7)*30) -> 43.291756 | Q34: =N34+O34-P34 -> 35.55092 | R34: =IF(Balanco_Consolidado!AI21=0,0,Balanco_Consolidado!AI9/Balanco_Consolidado!AI21) -> 1.5690273 | S34: =Cronogramas!AI18-Balanco_Consolidado!AI5 -> -179188.27 | T34: =IF((SUM(DRE_Consolidado!X17:DRE17))=0,0,S34/(SUM(DRE_Consolidado!X17:DRE17))) -> -0.23291794 | U34: =IF(Cronogramas!AI22=0,0,DRE_Consolidado!AI20/Cronogramas!AI22) -> 1.7065921 | V34: =IF((Balanco_Consolidado!AI27+S34)=0,0,(SUM(DRE_Consolidado!X20:DRE20))*(1-Premissas!$B$5)/(Balanco_Consolidado!AI27+S34)) -> 0.57855559 | W34: =DFC_Consolidado!AI13 -> 15180.028 | X34: =Balanco_Consolidado!AI9-Balanco_Consolidado!AI21 -> 309830.48
A35: 2027 | B35: 10 | C35: 2027-10 | D35: 46661 | E35: =DRE_Consolidado!AJ4 -> 312518.84 | F35: =DRE_Consolidado!AJ6 -> 209988.61 | G35: =IF(DRE_Consolidado!AI4=0,0,DRE_Consolidado!AJ4/DRE_Consolidado!AI4-1) -> -0.094708819 | H35: =IF(DRE_Consolidado!X4=0,0,DRE_Consolidado!AJ4/DRE_Consolidado!X4-1) -> 0.072595905 | I35: =DRE_Consolidado!AJ9 -> 0.43928135 | J35: =DRE_Consolidado!AJ18 -> 0.033442749 | K35: =DRE_Consolidado!AJ25 -> 0.0019467242 | L35: =DRE_Consolidado!AJ17 -> 7022.5964 | M35: =DRE_Consolidado!AJ24 -> 408.78992 | N35: =IF(DRE_Consolidado!AJ6=0,0,Balanco_Consolidado!AJ6/DRE_Consolidado!AJ6*30) -> 27.957592 | O35: =IF(DRE_Consolidado!AJ7=0,0,Balanco_Consolidado!AJ7/(-DRE_Consolidado!AJ7)*30) -> 52.80134 | P35: =IF(DRE_Consolidado!AJ7=0,0,Balanco_Consolidado!AJ16/(-DRE_Consolidado!AJ7)*30) -> 43.32779 | Q35: =N35+O35-P35 -> 37.431142 | R35: =IF(Balanco_Consolidado!AJ21=0,0,Balanco_Consolidado!AJ9/Balanco_Consolidado!AJ21) -> 1.6131071 | S35: =Cronogramas!AJ18-Balanco_Consolidado!AJ5 -> -182119.45 | T35: =IF((SUM(DRE_Consolidado!Y17:DRE17))=0,0,S35/(SUM(DRE_Consolidado!Y17:DRE17))) -> -0.24000761 | U35: =IF(Cronogramas!AJ22=0,0,DRE_Consolidado!AJ20/Cronogramas!AJ22) -> 0.15530802 | V35: =IF((Balanco_Consolidado!AJ27+S35)=0,0,(SUM(DRE_Consolidado!Y20:DRE20))*(1-Premissas!$B$5)/(Balanco_Consolidado!AJ27+S35)) -> 0.57582862 | W35: =DFC_Consolidado!AJ13 -> 6081.0084 | X35: =Balanco_Consolidado!AJ9-Balanco_Consolidado!AJ21 -> 308565.36
A36: 2027 | B36: 11 | C36: 2027-11 | D36: 46692 | E36: =DRE_Consolidado!AK4 -> 397027.96 | F36: =DRE_Consolidado!AK6 -> 267334.1 | G36: =IF(DRE_Consolidado!AJ4=0,0,DRE_Consolidado!AK4/DRE_Consolidado!AJ4-1) -> 0.27041289 | H36: =IF(DRE_Consolidado!Y4=0,0,DRE_Consolidado!AK4/DRE_Consolidado!Y4-1) -> 0.070894589 | I36: =DRE_Consolidado!AK9 -> 0.43445831 | J36: =DRE_Consolidado!AK18 -> 0.10031993 | K36: =DRE_Consolidado!AK25 -> 0.050558205 | L36: =DRE_Consolidado!AK17 -> 26818.939 | M36: =DRE_Consolidado!AK24 -> 13515.932 | N36: =IF(DRE_Consolidado!AK6=0,0,Balanco_Consolidado!AK6/DRE_Consolidado!AK6*30) -> 26.919539 | O36: =IF(DRE_Consolidado!AK7=0,0,Balanco_Consolidado!AK7/(-DRE_Consolidado!AK7)*30) -> 53.013234 | P36: =IF(DRE_Consolidado!AK7=0,0,Balanco_Consolidado!AK16/(-DRE_Consolidado!AK7)*30) -> 43.63124 | Q36: =N36+O36-P36 -> 36.301533 | R36: =IF(Balanco_Consolidado!AK21=0,0,Balanco_Consolidado!AK9/Balanco_Consolidado!AK21) -> 1.5437237 | S36: =Cronogramas!AK18-Balanco_Consolidado!AK5 -> -178906.52 | T36: =IF((SUM(DRE_Consolidado!Z17:DRE17))=0,0,S36/(SUM(DRE_Consolidado!Z17:DRE17))) -> -0.24520225 | U36: =IF(Cronogramas!AK22=0,0,DRE_Consolidado!AK20/Cronogramas!AK22) -> 6.0445269 | V36: =IF((Balanco_Consolidado!AK27+S36)=0,0,(SUM(DRE_Consolidado!Z20:DRE20))*(1-Premissas!$B$5)/(Balanco_Consolidado!AK27+S36)) -> 0.52985828 | W36: =DFC_Consolidado!AK13 -> 797.08319 | X36: =Balanco_Consolidado!AK9-Balanco_Consolidado!AK21 -> 319580.61
A37: 2027 | B37: 12 | C37: 2027-12 | D37: 46722 | E37: =DRE_Consolidado!AL4 -> 426285.15 | F37: =DRE_Consolidado!AL6 -> 288201.1 | G37: =IF(DRE_Consolidado!AK4=0,0,DRE_Consolidado!AL4/DRE_Consolidado!AK4-1) -> 0.073690521 | H37: =IF(DRE_Consolidado!Z4=0,0,DRE_Consolidado!AL4/DRE_Consolidado!Z4-1) -> 0.070360525 | I37: =DRE_Consolidado!AL9 -> 0.43424809 | J37: =DRE_Consolidado!AL18 -> 0.11941083 | K37: =DRE_Consolidado!AL25 -> 0.064303123 | L37: =DRE_Consolidado!AL17 -> 34414.333 | M37: =DRE_Consolidado!AL24 -> 18532.231 | N37: =IF(DRE_Consolidado!AL6=0,0,Balanco_Consolidado!AL6/DRE_Consolidado!AL6*30) -> 26.13504 | O37: =IF(DRE_Consolidado!AL7=0,0,Balanco_Consolidado!AL7/(-DRE_Consolidado!AL7)*30) -> 52.945526 | P37: =IF(DRE_Consolidado!AL7=0,0,Balanco_Consolidado!AL16/(-DRE_Consolidado!AL7)*30) -> 43.7223 | Q37: =N37+O37-P37 -> 35.358267 | R37: =IF(Balanco_Consolidado!AL21=0,0,Balanco_Consolidado!AL9/Balanco_Consolidado!AL21) -> 1.546531 | S37: =Cronogramas!AL18-Balanco_Consolidado!AL5 -> -197018.24 | T37: =IF((SUM(DRE_Consolidado!AA17:DRE17))=0,0,S37/(SUM(DRE_Consolidado!AA17:DRE17))) -> -0.28404006 | U37: =IF(Cronogramas!AL22=0,0,DRE_Consolidado!AL20/Cronogramas!AL22) -> 8.709056 | V37: =IF((Balanco_Consolidado!AL27+S37)=0,0,(SUM(DRE_Consolidado!AA20:DRE20))*(1-Premissas!$B$5)/(Balanco_Consolidado!AL27+S37)) -> 0.49304916 | W37: =DFC_Consolidado!AL13 -> 22434.736 | X37: =Balanco_Consolidado!AL9-Balanco_Consolidado!AL21 -> 335335.18

Sheet Cenarios
A1: ANALISE DE CENARIOS - Ano 2027 (consolidado)
A2: Base reproduz o modelo. Conservador e Otimista aplicam multiplicadores da aba Premissas sobre 2026.
A4: Linha (2027) | B4: Conservador | C4: Base | D4: Otimista
A5: Receita Bruta | B5: =DRE_Consolidado!AO4*(1+(DRE_Consolidado!AP4/DRE_Consolidado!AO4-1)*Premissas!B46) -> 3897962.7 | C5: =DRE_Consolidado!AO4*(1+(DRE_Consolidado!AP4/DRE_Consolidado!AO4-1)*Premissas!B47) -> 4032546.8 | D5: =DRE_Consolidado!AO4*(1+(DRE_Consolidado!AP4/DRE_Consolidado!AO4-1)*Premissas!B48) -> 4167130.8
A6: Receita Liquida | B6: =B5*(DRE_Consolidado!AP6/DRE_Consolidado!AP4) -> 2630420.4 | C6: =C5*(DRE_Consolidado!AP6/DRE_Consolidado!AP4) -> 2721240.3 | D6: =D5*(DRE_Consolidado!AP6/DRE_Consolidado!AP4) -> 2812060.2
A7: Lucro Bruto | B7: =B6*(DRE_Consolidado!AP8/DRE_Consolidado!AP6+Premissas!C46) -> 1095208.5 | C7: =C6*(DRE_Consolidado!AP8/DRE_Consolidado!AP6+Premissas!C47) -> 1187447.4 | D7: =D6*(DRE_Consolidado!AP8/DRE_Consolidado!AP6+Premissas!C48) -> 1269258.7
A8: (-) Custos Operacionais | B8: =-(DRE_Consolidado!AP8-DRE_Consolidado!AP17)*(B6/DRE_Consolidado!AP6)*Premissas!D46 -> -1041637.7 | C8: =-(DRE_Consolidado!AP8-DRE_Consolidado!AP17)*(C6/DRE_Consolidado!AP6)*Premissas!D47 -> -1036155.9 | D8: =-(DRE_Consolidado!AP8-DRE_Consolidado!AP17)*(D6/DRE_Consolidado!AP6)*Premissas!D48 -> -1038614.9
A9: EBITDA | B9: =B7+B8 -> 53570.818 | C9: =C7+C8 -> 151291.49 | D9: =D7+D8 -> 230643.77
A10: (-) D&A | B10: =--DRE_Consolidado!AP19 -> -76537.059 | C10: =--DRE_Consolidado!AP19 -> -76537.059 | D10: =--DRE_Consolidado!AP19 -> -76537.059
A11: EBIT | B11: =B9+B10 -> -22966.241 | C11: =C9+C10 -> 74754.426 | D11: =D9+D10 -> 154106.71
A12: (+/-) Resultado Financeiro | B12: =DRE_Consolidado!AP21 -> -4429.021 | C12: =DRE_Consolidado!AP21 -> -4429.021 | D12: =DRE_Consolidado!AP21 -> -4429.021
A13: LAIR | B13: =B11+B12 -> -27395.262 | C13: =C11+C12 -> 70325.405 | D13: =D11+D12 -> 149677.69
A14: (-) IR/CSLL | B14: =-MAX(0,B13)*Premissas!$B$5 -> 0 | C14: =-MAX(0,C13)*Premissas!$B$5 -> -23910.638 | D14: =-MAX(0,D13)*Premissas!$B$5 -> -50890.414
A15: Lucro Liquido | B15: =B13+B14 -> -27395.262 | C15: =C13+C14 -> 46414.767 | D15: =D13+D14 -> 98787.275
A17: Margem EBITDA % | B17: =B9/B6 -> 0.020365877 | C17: =C9/C6 -> 0.055596518 | D17: =D9/D6 -> 0.082019499
A18: Margem Liquida % | B18: =B15/B6 -> -0.010414785 | C18: =C15/C6 -> 0.017056475 | D18: =D15/D6 -> 0.035129858
A19: Divida Liquida / EBITDA | B19: =IF(B9=0,0,(Cronogramas!AP18-Balanco_Consolidado!AP5)/B9) -> -7.2244228 | C19: =IF(C9=0,0,(Cronogramas!AP18-Balanco_Consolidado!AP5)/C9) -> -2.5580966 | D19: =IF(D9=0,0,(Cronogramas!AP18-Balanco_Consolidado!AP5)/D9) -> -1.6779913
A20: Caixa aprox. fim 2027 | B20: =DFC_Consolidado!AO21+B15+-DRE_Consolidado!AP19-(-DFC_Consolidado!AO14)-(-DFC_Consolidado!AO17) -> 488455.92 | C20: =DFC_Consolidado!AO21+C15+-DRE_Consolidado!AP19-(-DFC_Consolidado!AO14)-(-DFC_Consolidado!AO17) -> 562265.95 | D20: =DFC_Consolidado!AO21+D15+-DRE_Consolidado!AP19-(-DFC_Consolidado!AO14)-(-DFC_Consolidado!AO17) -> 614638.45

Sheet Sensibilidade
A1: ANALISE DE SENSIBILIDADE - 2027
A2: Recalculo do resultado 2027 variando dois drivers. Celula central (destacada) = caso Base.
A4: Grid A - EBITDA 2027 (R$)
A5: Cresc. receita \ Delta margem bruta | B5: -3,0 p.p. | C5: -1,5 p.p. | D5: Base | E5: +1,5 p.p. | F5: +3,0 p.p.
A6: -6 p.p. | B6: =(((DRE_Consolidado!AP4*(1+-0.06))*(DRE_Consolidado!AP6/DRE_Consolidado!AP4))*((DRE_Consolidado!AP8/DRE_Consolidado!AP6)+-0.03))-((DRE_Consolidado!AP8-DRE_Consolidado!AP17)*(((DRE_Consolidado!AP4*(1+-0.06))*(DRE_Consolidado!AP6/DRE_Consolidado!AP4))/DRE_Consolidado!AP6)) -> 65475.02 | C6: =(((DRE_Consolidado!AP4*(1+-0.06))*(DRE_Consolidado!AP6/DRE_Consolidado!AP4))*((DRE_Consolidado!AP8/DRE_Consolidado!AP6)+-0.015))-((DRE_Consolidado!AP8-DRE_Consolidado!AP17)*(((DRE_Consolidado!AP4*(1+-0.06))*(DRE_Consolidado!AP6/DRE_Consolidado!AP4))/DRE_Consolidado!AP6)) -> 103844.51 | D6: =(((DRE_Consolidado!AP4*(1+-0.06))*(DRE_Consolidado!AP6/DRE_Consolidado!AP4))*((DRE_Consolidado!AP8/DRE_Consolidado!AP6)+0))-((DRE_Consolidado!AP8-DRE_Consolidado!AP17)*(((DRE_Consolidado!AP4*(1+-0.06))*(DRE_Consolidado!AP6/DRE_Consolidado!AP4))/DRE_Consolidado!AP6)) -> 142214 | E6: =(((DRE_Consolidado!AP4*(1+-0.06))*(DRE_Consolidado!AP6/DRE_Consolidado!AP4))*((DRE_Consolidado!AP8/DRE_Consolidado!AP6)+0.015))-((DRE_Consolidado!AP8-DRE_Consolidado!AP17)*(((DRE_Consolidado!AP4*(1+-0.06))*(DRE_Consolidado!AP6/DRE_Consolidado!AP4))/DRE_Consolidado!AP6)) -> 180583.48 | F6: =(((DRE_Consolidado!AP4*(1+-0.06))*(DRE_Consolidado!AP6/DRE_Consolidado!AP4))*((DRE_Consolidado!AP8/DRE_Consolidado!AP6)+0.03))-((DRE_Consolidado!AP8-DRE_Consolidado!AP17)*(((DRE_Consolidado!AP4*(1+-0.06))*(DRE_Consolidado!AP6/DRE_Consolidado!AP4))/DRE_Consolidado!AP6)) -> 218952.97
A7: -3 p.p. | B7: =(((DRE_Consolidado!AP4*(1+-0.03))*(DRE_Consolidado!AP6/DRE_Consolidado!AP4))*((DRE_Consolidado!AP8/DRE_Consolidado!AP6)+-0.03))-((DRE_Consolidado!AP8-DRE_Consolidado!AP17)*(((DRE_Consolidado!AP4*(1+-0.03))*(DRE_Consolidado!AP6/DRE_Consolidado!AP4))/DRE_Consolidado!AP6)) -> 67564.648 | C7: =(((DRE_Consolidado!AP4*(1+-0.03))*(DRE_Consolidado!AP6/DRE_Consolidado!AP4))*((DRE_Consolidado!AP8/DRE_Consolidado!AP6)+-0.015))-((DRE_Consolidado!AP8-DRE_Consolidado!AP17)*(((DRE_Consolidado!AP4*(1+-0.03))*(DRE_Consolidado!AP6/DRE_Consolidado!AP4))/DRE_Consolidado!AP6)) -> 107158.69 | D7: =(((DRE_Consolidado!AP4*(1+-0.03))*(DRE_Consolidado!AP6/DRE_Consolidado!AP4))*((DRE_Consolidado!AP8/DRE_Consolidado!AP6)+0))-((DRE_Consolidado!AP8-DRE_Consolidado!AP17)*(((DRE_Consolidado!AP4*(1+-0.03))*(DRE_Consolidado!AP6/DRE_Consolidado!AP4))/DRE_Consolidado!AP6)) -> 146752.74 | E7: =(((DRE_Consolidado!AP4*(1+-0.03))*(DRE_Consolidado!AP6/DRE_Consolidado!AP4))*((DRE_Consolidado!AP8/DRE_Consolidado!AP6)+0.015))-((DRE_Consolidado!AP8-DRE_Consolidado!AP17)*(((DRE_Consolidado!AP4*(1+-0.03))*(DRE_Consolidado!AP6/DRE_Consolidado!AP4))/DRE_Consolidado!AP6)) -> 186346.79 | F7: =(((DRE_Consolidado!AP4*(1+-0.03))*(DRE_Consolidado!AP6/DRE_Consolidado!AP4))*((DRE_Consolidado!AP8/DRE_Consolidado!AP6)+0.03))-((DRE_Consolidado!AP8-DRE_Consolidado!AP17)*(((DRE_Consolidado!AP4*(1+-0.03))*(DRE_Consolidado!AP6/DRE_Consolidado!AP4))/DRE_Consolidado!AP6)) -> 225940.83
A8: Base | B8: =(((DRE_Consolidado!AP4*(1+0))*(DRE_Consolidado!AP6/DRE_Consolidado!AP4))*((DRE_Consolidado!AP8/DRE_Consolidado!AP6)+-0.03))-((DRE_Consolidado!AP8-DRE_Consolidado!AP17)*(((DRE_Consolidado!AP4*(1+0))*(DRE_Consolidado!AP6/DRE_Consolidado!AP4))/DRE_Consolidado!AP6)) -> 69654.277 | C8: =(((DRE_Consolidado!AP4*(1+0))*(DRE_Consolidado!AP6/DRE_Consolidado!AP4))*((DRE_Consolidado!AP8/DRE_Consolidado!AP6)+-0.015))-((DRE_Consolidado!AP8-DRE_Consolidado!AP17)*(((DRE_Consolidado!AP4*(1+0))*(DRE_Consolidado!AP6/DRE_Consolidado!AP4))/DRE_Consolidado!AP6)) -> 110472.88 | D8: =(((DRE_Consolidado!AP4*(1+0))*(DRE_Consolidado!AP6/DRE_Consolidado!AP4))*((DRE_Consolidado!AP8/DRE_Consolidado!AP6)+0))-((DRE_Consolidado!AP8-DRE_Consolidado!AP17)*(((DRE_Consolidado!AP4*(1+0))*(DRE_Consolidado!AP6/DRE_Consolidado!AP4))/DRE_Consolidado!AP6)) -> 151291.49 | E8: =(((DRE_Consolidado!AP4*(1+0))*(DRE_Consolidado!AP6/DRE_Consolidado!AP4))*((DRE_Consolidado!AP8/DRE_Consolidado!AP6)+0.015))-((DRE_Consolidado!AP8-DRE_Consolidado!AP17)*(((DRE_Consolidado!AP4*(1+0))*(DRE_Consolidado!AP6/DRE_Consolidado!AP4))/DRE_Consolidado!AP6)) -> 192110.09 | F8: =(((DRE_Consolidado!AP4*(1+0))*(DRE_Consolidado!AP6/DRE_Consolidado!AP4))*((DRE_Consolidado!AP8/DRE_Consolidado!AP6)+0.03))-((DRE_Consolidado!AP8-DRE_Consolidado!AP17)*(((DRE_Consolidado!AP4*(1+0))*(DRE_Consolidado!AP6/DRE_Consolidado!AP4))/DRE_Consolidado!AP6)) -> 232928.69
A9: +3 p.p. | B9: =(((DRE_Consolidado!AP4*(1+0.03))*(DRE_Consolidado!AP6/DRE_Consolidado!AP4))*((DRE_Consolidado!AP8/DRE_Consolidado!AP6)+-0.03))-((DRE_Consolidado!AP8-DRE_Consolidado!AP17)*(((DRE_Consolidado!AP4*(1+0.03))*(DRE_Consolidado!AP6/DRE_Consolidado!AP4))/DRE_Consolidado!AP6)) -> 71743.905 | C9: =(((DRE_Consolidado!AP4*(1+0.03))*(DRE_Consolidado!AP6/DRE_Consolidado!AP4))*((DRE_Consolidado!AP8/DRE_Consolidado!AP6)+-0.015))-((DRE_Consolidado!AP8-DRE_Consolidado!AP17)*(((DRE_Consolidado!AP4*(1+0.03))*(DRE_Consolidado!AP6/DRE_Consolidado!AP4))/DRE_Consolidado!AP6)) -> 113787.07 | D9: =(((DRE_Consolidado!AP4*(1+0.03))*(DRE_Consolidado!AP6/DRE_Consolidado!AP4))*((DRE_Consolidado!AP8/DRE_Consolidado!AP6)+0))-((DRE_Consolidado!AP8-DRE_Consolidado!AP17)*(((DRE_Consolidado!AP4*(1+0.03))*(DRE_Consolidado!AP6/DRE_Consolidado!AP4))/DRE_Consolidado!AP6)) -> 155830.23 | E9: =(((DRE_Consolidado!AP4*(1+0.03))*(DRE_Consolidado!AP6/DRE_Consolidado!AP4))*((DRE_Consolidado!AP8/DRE_Consolidado!AP6)+0.015))-((DRE_Consolidado!AP8-DRE_Consolidado!AP17)*(((DRE_Consolidado!AP4*(1+0.03))*(DRE_Consolidado!AP6/DRE_Consolidado!AP4))/DRE_Consolidado!AP6)) -> 197873.39 | F9: =(((DRE_Consolidado!AP4*(1+0.03))*(DRE_Consolidado!AP6/DRE_Consolidado!AP4))*((DRE_Consolidado!AP8/DRE_Consolidado!AP6)+0.03))-((DRE_Consolidado!AP8-DRE_Consolidado!AP17)*(((DRE_Consolidado!AP4*(1+0.03))*(DRE_Consolidado!AP6/DRE_Consolidado!AP4))/DRE_Consolidado!AP6)) -> 239916.56
A10: +6 p.p. | B10: =(((DRE_Consolidado!AP4*(1+0.06))*(DRE_Consolidado!AP6/DRE_Consolidado!AP4))*((DRE_Consolidado!AP8/DRE_Consolidado!AP6)+-0.03))-((DRE_Consolidado!AP8-DRE_Consolidado!AP17)*(((DRE_Consolidado!AP4*(1+0.06))*(DRE_Consolidado!AP6/DRE_Consolidado!AP4))/DRE_Consolidado!AP6)) -> 73833.533 | C10: =(((DRE_Consolidado!AP4*(1+0.06))*(DRE_Consolidado!AP6/DRE_Consolidado!AP4))*((DRE_Consolidado!AP8/DRE_Consolidado!AP6)+-0.015))-((DRE_Consolidado!AP8-DRE_Consolidado!AP17)*(((DRE_Consolidado!AP4*(1+0.06))*(DRE_Consolidado!AP6/DRE_Consolidado!AP4))/DRE_Consolidado!AP6)) -> 117101.25 | D10: =(((DRE_Consolidado!AP4*(1+0.06))*(DRE_Consolidado!AP6/DRE_Consolidado!AP4))*((DRE_Consolidado!AP8/DRE_Consolidado!AP6)+0))-((DRE_Consolidado!AP8-DRE_Consolidado!AP17)*(((DRE_Consolidado!AP4*(1+0.06))*(DRE_Consolidado!AP6/DRE_Consolidado!AP4))/DRE_Consolidado!AP6)) -> 160368.97 | E10: =(((DRE_Consolidado!AP4*(1+0.06))*(DRE_Consolidado!AP6/DRE_Consolidado!AP4))*((DRE_Consolidado!AP8/DRE_Consolidado!AP6)+0.015))-((DRE_Consolidado!AP8-DRE_Consolidado!AP17)*(((DRE_Consolidado!AP4*(1+0.06))*(DRE_Consolidado!AP6/DRE_Consolidado!AP4))/DRE_Consolidado!AP6)) -> 203636.7 | F10: =(((DRE_Consolidado!AP4*(1+0.06))*(DRE_Consolidado!AP6/DRE_Consolidado!AP4))*((DRE_Consolidado!AP8/DRE_Consolidado!AP6)+0.03))-((DRE_Consolidado!AP8-DRE_Consolidado!AP17)*(((DRE_Consolidado!AP4*(1+0.06))*(DRE_Consolidado!AP6/DRE_Consolidado!AP4))/DRE_Consolidado!AP6)) -> 246904.42
A13: Grid B - Lucro Liquido 2027 (R$)
A14: Delta margem bruta \ Mult. custos oper. | B14: 0,90x | C14: 0,95x | D14: Base (1,00x) | E14: 1,05x | F14: 1,10x
A15: -3,0 p.p. | B15: =(((((DRE_Consolidado!AP6*((DRE_Consolidado!AP8/DRE_Consolidado!AP6)+-0.03))-((DRE_Consolidado!AP8-DRE_Consolidado!AP17)*0.9))-(-DRE_Consolidado!AP19))+DRE_Consolidado!AP21)-MAX(0,((((DRE_Consolidado!AP6*((DRE_Consolidado!AP8/DRE_Consolidado!AP6)+-0.03))-((DRE_Consolidado!AP8-DRE_Consolidado!AP17)*0.9))-(-DRE_Consolidado!AP19))+DRE_Consolidado!AP21))*Premissas!$B$5) -> 60920.497 | C15: =(((((DRE_Consolidado!AP6*((DRE_Consolidado!AP8/DRE_Consolidado!AP6)+-0.03))-((DRE_Consolidado!AP8-DRE_Consolidado!AP17)*0.95))-(-DRE_Consolidado!AP19))+DRE_Consolidado!AP21)-MAX(0,((((DRE_Consolidado!AP6*((DRE_Consolidado!AP8/DRE_Consolidado!AP6)+-0.03))-((DRE_Consolidado!AP8-DRE_Consolidado!AP17)*0.95))-(-DRE_Consolidado!AP19))+DRE_Consolidado!AP21))*Premissas!$B$5) -> 26727.353 | D15: =(((((DRE_Consolidado!AP6*((DRE_Consolidado!AP8/DRE_Consolidado!AP6)+-0.03))-((DRE_Consolidado!AP8-DRE_Consolidado!AP17)*1))-(-DRE_Consolidado!AP19))+DRE_Consolidado!AP21)-MAX(0,((((DRE_Consolidado!AP6*((DRE_Consolidado!AP8/DRE_Consolidado!AP6)+-0.03))-((DRE_Consolidado!AP8-DRE_Consolidado!AP17)*1))-(-DRE_Consolidado!AP19))+DRE_Consolidado!AP21))*Premissas!$B$5) -> -11311.804 | E15: =(((((DRE_Consolidado!AP6*((DRE_Consolidado!AP8/DRE_Consolidado!AP6)+-0.03))-((DRE_Consolidado!AP8-DRE_Consolidado!AP17)*1.05))-(-DRE_Consolidado!AP19))+DRE_Consolidado!AP21)-MAX(0,((((DRE_Consolidado!AP6*((DRE_Consolidado!AP8/DRE_Consolidado!AP6)+-0.03))-((DRE_Consolidado!AP8-DRE_Consolidado!AP17)*1.05))-(-DRE_Consolidado!AP19))+DRE_Consolidado!AP21))*Premissas!$B$5) -> -63119.597 | F15: =(((((DRE_Consolidado!AP6*((DRE_Consolidado!AP8/DRE_Consolidado!AP6)+-0.03))-((DRE_Consolidado!AP8-DRE_Consolidado!AP17)*1.1))-(-DRE_Consolidado!AP19))+DRE_Consolidado!AP21)-MAX(0,((((DRE_Consolidado!AP6*((DRE_Consolidado!AP8/DRE_Consolidado!AP6)+-0.03))-((DRE_Consolidado!AP8-DRE_Consolidado!AP17)*1.1))-(-DRE_Consolidado!AP19))+DRE_Consolidado!AP21))*Premissas!$B$5) -> -114927.39
A16: -1,5 p.p. | B16: =(((((DRE_Consolidado!AP6*((DRE_Consolidado!AP8/DRE_Consolidado!AP6)+-0.015))-((DRE_Consolidado!AP8-DRE_Consolidado!AP17)*0.9))-(-DRE_Consolidado!AP19))+DRE_Consolidado!AP21)-MAX(0,((((DRE_Consolidado!AP6*((DRE_Consolidado!AP8/DRE_Consolidado!AP6)+-0.015))-((DRE_Consolidado!AP8-DRE_Consolidado!AP17)*0.9))-(-DRE_Consolidado!AP19))+DRE_Consolidado!AP21))*Premissas!$B$5) -> 87860.776 | C16: =(((((DRE_Consolidado!AP6*((DRE_Consolidado!AP8/DRE_Consolidado!AP6)+-0.015))-((DRE_Consolidado!AP8-DRE_Consolidado!AP17)*0.95))-(-DRE_Consolidado!AP19))+DRE_Consolidado!AP21)-MAX(0,((((DRE_Consolidado!AP6*((DRE_Consolidado!AP8/DRE_Consolidado!AP6)+-0.015))-((DRE_Consolidado!AP8-DRE_Consolidado!AP17)*0.95))-(-DRE_Consolidado!AP19))+DRE_Consolidado!AP21))*Premissas!$B$5) -> 53667.632 | D16: =(((((DRE_Consolidado!AP6*((DRE_Consolidado!AP8/DRE_Consolidado!AP6)+-0.015))-((DRE_Consolidado!AP8-DRE_Consolidado!AP17)*1))-(-DRE_Consolidado!AP19))+DRE_Consolidado!AP21)-MAX(0,((((DRE_Consolidado!AP6*((DRE_Consolidado!AP8/DRE_Consolidado!AP6)+-0.015))-((DRE_Consolidado!AP8-DRE_Consolidado!AP17)*1))-(-DRE_Consolidado!AP19))+DRE_Consolidado!AP21))*Premissas!$B$5) -> 19474.489 | E16: =(((((DRE_Consolidado!AP6*((DRE_Consolidado!AP8/DRE_Consolidado!AP6)+-0.015))-((DRE_Consolidado!AP8-DRE_Consolidado!AP17)*1.05))-(-DRE_Consolidado!AP19))+DRE_Consolidado!AP21)-MAX(0,((((DRE_Consolidado!AP6*((DRE_Consolidado!AP8/DRE_Consolidado!AP6)+-0.015))-((DRE_Consolidado!AP8-DRE_Consolidado!AP17)*1.05))-(-DRE_Consolidado!AP19))+DRE_Consolidado!AP21))*Premissas!$B$5) -> -22300.992 | F16: =(((((DRE_Consolidado!AP6*((DRE_Consolidado!AP8/DRE_Consolidado!AP6)+-0.015))-((DRE_Consolidado!AP8-DRE_Consolidado!AP17)*1.1))-(-DRE_Consolidado!AP19))+DRE_Consolidado!AP21)-MAX(0,((((DRE_Consolidado!AP6*((DRE_Consolidado!AP8/DRE_Consolidado!AP6)+-0.015))-((DRE_Consolidado!AP8-DRE_Consolidado!AP17)*1.1))-(-DRE_Consolidado!AP19))+DRE_Consolidado!AP21))*Premissas!$B$5) -> -74108.786
A17: Base | B17: =(((((DRE_Consolidado!AP6*((DRE_Consolidado!AP8/DRE_Consolidado!AP6)+0))-((DRE_Consolidado!AP8-DRE_Consolidado!AP17)*0.9))-(-DRE_Consolidado!AP19))+DRE_Consolidado!AP21)-MAX(0,((((DRE_Consolidado!AP6*((DRE_Consolidado!AP8/DRE_Consolidado!AP6)+0))-((DRE_Consolidado!AP8-DRE_Consolidado!AP17)*0.9))-(-DRE_Consolidado!AP19))+DRE_Consolidado!AP21))*Premissas!$B$5) -> 114801.05 | C17: =(((((DRE_Consolidado!AP6*((DRE_Consolidado!AP8/DRE_Consolidado!AP6)+0))-((DRE_Consolidado!AP8-DRE_Consolidado!AP17)*0.95))-(-DRE_Consolidado!AP19))+DRE_Consolidado!AP21)-MAX(0,((((DRE_Consolidado!AP6*((DRE_Consolidado!AP8/DRE_Consolidado!AP6)+0))-((DRE_Consolidado!AP8-DRE_Consolidado!AP17)*0.95))-(-DRE_Consolidado!AP19))+DRE_Consolidado!AP21))*Premissas!$B$5) -> 80607.911 | D17: =(((((DRE_Consolidado!AP6*((DRE_Consolidado!AP8/DRE_Consolidado!AP6)+0))-((DRE_Consolidado!AP8-DRE_Consolidado!AP17)*1))-(-DRE_Consolidado!AP19))+DRE_Consolidado!AP21)-MAX(0,((((DRE_Consolidado!AP6*((DRE_Consolidado!AP8/DRE_Consolidado!AP6)+0))-((DRE_Consolidado!AP8-DRE_Consolidado!AP17)*1))-(-DRE_Consolidado!AP19))+DRE_Consolidado!AP21))*Premissas!$B$5) -> 46414.767 | E17: =(((((DRE_Consolidado!AP6*((DRE_Consolidado!AP8/DRE_Consolidado!AP6)+0))-((DRE_Consolidado!AP8-DRE_Consolidado!AP17)*1.05))-(-DRE_Consolidado!AP19))+DRE_Consolidado!AP21)-MAX(0,((((DRE_Consolidado!AP6*((DRE_Consolidado!AP8/DRE_Consolidado!AP6)+0))-((DRE_Consolidado!AP8-DRE_Consolidado!AP17)*1.05))-(-DRE_Consolidado!AP19))+DRE_Consolidado!AP21))*Premissas!$B$5) -> 12221.624 | F17: =(((((DRE_Consolidado!AP6*((DRE_Consolidado!AP8/DRE_Consolidado!AP6)+0))-((DRE_Consolidado!AP8-DRE_Consolidado!AP17)*1.1))-(-DRE_Consolidado!AP19))+DRE_Consolidado!AP21)-MAX(0,((((DRE_Consolidado!AP6*((DRE_Consolidado!AP8/DRE_Consolidado!AP6)+0))-((DRE_Consolidado!AP8-DRE_Consolidado!AP17)*1.1))-(-DRE_Consolidado!AP19))+DRE_Consolidado!AP21))*Premissas!$B$5) -> -33290.181
A18: +1,5 p.p. | B18: =(((((DRE_Consolidado!AP6*((DRE_Consolidado!AP8/DRE_Consolidado!AP6)+0.015))-((DRE_Consolidado!AP8-DRE_Consolidado!AP17)*0.9))-(-DRE_Consolidado!AP19))+DRE_Consolidado!AP21)-MAX(0,((((DRE_Consolidado!AP6*((DRE_Consolidado!AP8/DRE_Consolidado!AP6)+0.015))-((DRE_Consolidado!AP8-DRE_Consolidado!AP17)*0.9))-(-DRE_Consolidado!AP19))+DRE_Consolidado!AP21))*Premissas!$B$5) -> 141741.33 | C18: =(((((DRE_Consolidado!AP6*((DRE_Consolidado!AP8/DRE_Consolidado!AP6)+0.015))-((DRE_Consolidado!AP8-DRE_Consolidado!AP17)*0.95))-(-DRE_Consolidado!AP19))+DRE_Consolidado!AP21)-MAX(0,((((DRE_Consolidado!AP6*((DRE_Consolidado!AP8/DRE_Consolidado!AP6)+0.015))-((DRE_Consolidado!AP8-DRE_Consolidado!AP17)*0.95))-(-DRE_Consolidado!AP19))+DRE_Consolidado!AP21))*Premissas!$B$5) -> 107548.19 | D18: =(((((DRE_Consolidado!AP6*((DRE_Consolidado!AP8/DRE_Consolidado!AP6)+0.015))-((DRE_Consolidado!AP8-DRE_Consolidado!AP17)*1))-(-DRE_Consolidado!AP19))+DRE_Consolidado!AP21)-MAX(0,((((DRE_Consolidado!AP6*((DRE_Consolidado!AP8/DRE_Consolidado!AP6)+0.015))-((DRE_Consolidado!AP8-DRE_Consolidado!AP17)*1))-(-DRE_Consolidado!AP19))+DRE_Consolidado!AP21))*Premissas!$B$5) -> 73355.046 | E18: =(((((DRE_Consolidado!AP6*((DRE_Consolidado!AP8/DRE_Consolidado!AP6)+0.015))-((DRE_Consolidado!AP8-DRE_Consolidado!AP17)*1.05))-(-DRE_Consolidado!AP19))+DRE_Consolidado!AP21)-MAX(0,((((DRE_Consolidado!AP6*((DRE_Consolidado!AP8/DRE_Consolidado!AP6)+0.015))-((DRE_Consolidado!AP8-DRE_Consolidado!AP17)*1.05))-(-DRE_Consolidado!AP19))+DRE_Consolidado!AP21))*Premissas!$B$5) -> 39161.903 | F18: =(((((DRE_Consolidado!AP6*((DRE_Consolidado!AP8/DRE_Consolidado!AP6)+0.015))-((DRE_Consolidado!AP8-DRE_Consolidado!AP17)*1.1))-(-DRE_Consolidado!AP19))+DRE_Consolidado!AP21)-MAX(0,((((DRE_Consolidado!AP6*((DRE_Consolidado!AP8/DRE_Consolidado!AP6)+0.015))-((DRE_Consolidado!AP8-DRE_Consolidado!AP17)*1.1))-(-DRE_Consolidado!AP19))+DRE_Consolidado!AP21))*Premissas!$B$5) -> 4968.7592
A19: +3,0 p.p. | B19: =(((((DRE_Consolidado!AP6*((DRE_Consolidado!AP8/DRE_Consolidado!AP6)+0.03))-((DRE_Consolidado!AP8-DRE_Consolidado!AP17)*0.9))-(-DRE_Consolidado!AP19))+DRE_Consolidado!AP21)-MAX(0,((((DRE_Consolidado!AP6*((DRE_Consolidado!AP8/DRE_Consolidado!AP6)+0.03))-((DRE_Consolidado!AP8-DRE_Consolidado!AP17)*0.9))-(-DRE_Consolidado!AP19))+DRE_Consolidado!AP21))*Premissas!$B$5) -> 168681.61 | C19: =(((((DRE_Consolidado!AP6*((DRE_Consolidado!AP8/DRE_Consolidado!AP6)+0.03))-((DRE_Consolidado!AP8-DRE_Consolidado!AP17)*0.95))-(-DRE_Consolidado!AP19))+DRE_Consolidado!AP21)-MAX(0,((((DRE_Consolidado!AP6*((DRE_Consolidado!AP8/DRE_Consolidado!AP6)+0.03))-((DRE_Consolidado!AP8-DRE_Consolidado!AP17)*0.95))-(-DRE_Consolidado!AP19))+DRE_Consolidado!AP21))*Premissas!$B$5) -> 134488.47 | D19: =(((((DRE_Consolidado!AP6*((DRE_Consolidado!AP8/DRE_Consolidado!AP6)+0.03))-((DRE_Consolidado!AP8-DRE_Consolidado!AP17)*1))-(-DRE_Consolidado!AP19))+DRE_Consolidado!AP21)-MAX(0,((((DRE_Consolidado!AP6*((DRE_Consolidado!AP8/DRE_Consolidado!AP6)+0.03))-((DRE_Consolidado!AP8-DRE_Consolidado!AP17)*1))-(-DRE_Consolidado!AP19))+DRE_Consolidado!AP21))*Premissas!$B$5) -> 100295.33 | E19: =(((((DRE_Consolidado!AP6*((DRE_Consolidado!AP8/DRE_Consolidado!AP6)+0.03))-((DRE_Consolidado!AP8-DRE_Consolidado!AP17)*1.05))-(-DRE_Consolidado!AP19))+DRE_Consolidado!AP21)-MAX(0,((((DRE_Consolidado!AP6*((DRE_Consolidado!AP8/DRE_Consolidado!AP6)+0.03))-((DRE_Consolidado!AP8-DRE_Consolidado!AP17)*1.05))-(-DRE_Consolidado!AP19))+DRE_Consolidado!AP21))*Premissas!$B$5) -> 66102.182 | F19: =(((((DRE_Consolidado!AP6*((DRE_Consolidado!AP8/DRE_Consolidado!AP6)+0.03))-((DRE_Consolidado!AP8-DRE_Consolidado!AP17)*1.1))-(-DRE_Consolidado!AP19))+DRE_Consolidado!AP21)-MAX(0,((((DRE_Consolidado!AP6*((DRE_Consolidado!AP8/DRE_Consolidado!AP6)+0.03))-((DRE_Consolidado!AP8-DRE_Consolidado!AP17)*1.1))-(-DRE_Consolidado!AP19))+DRE_Consolidado!AP21))*Premissas!$B$5) -> 31909.038

Sheet Vendas_Representantes
A1: PERFORMANCE DE VENDAS POR REPRESENTANTE
A2: Grupo Meridiano Varejo | Metas x realizado por representante, segmento e mes (jan/2025 a dez/2027)
A4: PARAMETRO
A5: Crescimento anual das metas | B5: 0.06
A7: RESUMO POR REPRESENTANTE (anual)
A8: Representante | B8: Segmento | C8: 2025 Realiz. | D8: 2025 Meta | E8: 2025 Ating. | F8: 2026 Realiz. | G8: 2026 Meta | H8: 2026 Ating. | I8: 2027 Realiz. | J8: 2027 Meta | K8: 2027 Ating. | L8: Ating. 3 anos | M8: Ranking
A9: Rafael Nogueira | B9: Materiais de Construcao | C9: =SUMIFS($G$48:$G$479,$D$48:$D$479,$A9,$A$48:$A$479,2025) -> 271762.53 | D9: =SUMIFS($H$48:$H$479,$D$48:$D$479,$A9,$A$48:$A$479,2025) -> 258225.82 | E9: =IF(D9=0,0,C9/D9) -> 1.052422 | F9: =SUMIFS($G$48:$G$479,$D$48:$D$479,$A9,$A$48:$A$479,2026) -> 286535.42 | G9: =SUMIFS($H$48:$H$479,$D$48:$D$479,$A9,$A$48:$A$479,2026) -> 273719.37 | H9: =IF(G9=0,0,F9/G9) -> 1.0468219 | I9: =SUMIFS($G$48:$G$479,$D$48:$D$479,$A9,$A$48:$A$479,2027) -> 309458.26 | J9: =SUMIFS($H$48:$H$479,$D$48:$D$479,$A9,$A$48:$A$479,2027) -> 290142.53 | K9: =IF(J9=0,0,I9/J9) -> 1.0665732 | L9: =IF((D9+G9+J9)=0,0,(C9+F9+I9)/(D9+G9+J9)) -> 1.0555519 | M9: =RANK(L9,$L$9:$L$20,0) -> 6
A10: Beatriz Ramalho | B10: Materiais de Construcao | C10: =SUMIFS($G$48:$G$479,$D$48:$D$479,$A10,$A$48:$A$479,2025) -> 222351.17 | D10: =SUMIFS($H$48:$H$479,$D$48:$D$479,$A10,$A$48:$A$479,2025) -> 244624.46 | E10: =IF(D10=0,0,C10/D10) -> 0.90894903 | F10: =SUMIFS($G$48:$G$479,$D$48:$D$479,$A10,$A$48:$A$479,2026) -> 234438.08 | G10: =SUMIFS($H$48:$H$479,$D$48:$D$479,$A10,$A$48:$A$479,2026) -> 259301.93 | H10: =IF(G10=0,0,F10/G10) -> 0.90411235 | I10: =SUMIFS($G$48:$G$479,$D$48:$D$479,$A10,$A$48:$A$479,2027) -> 253193.12 | J10: =SUMIFS($H$48:$H$479,$D$48:$D$479,$A10,$A$48:$A$479,2027) -> 274860.04 | K10: =IF(J10=0,0,I10/J10) -> 0.92117107 | L10: =IF((D10+G10+J10)=0,0,(C10+F10+I10)/(D10+G10+J10)) -> 0.9116522 | M10: =RANK(L10,$L$9:$L$20,0) -> 10
A11: Carla Menezes | B11: Utilidades Domesticas | C11: =SUMIFS($G$48:$G$479,$D$48:$D$479,$A11,$A$48:$A$479,2025) -> 364938.5 | D11: =SUMIFS($H$48:$H$479,$D$48:$D$479,$A11,$A$48:$A$479,2025) -> 364863.51 | E11: =IF(D11=0,0,C11/D11) -> 1.0002055 | F11: =SUMIFS($G$48:$G$479,$D$48:$D$479,$A11,$A$48:$A$479,2026) -> 362055.73 | G11: =SUMIFS($H$48:$H$479,$D$48:$D$479,$A11,$A$48:$A$479,2026) -> 386755.32 | H11: =IF(G11=0,0,F11/G11) -> 0.9361364 | I11: =SUMIFS($G$48:$G$479,$D$48:$D$479,$A11,$A$48:$A$479,2027) -> 380158.52 | J11: =SUMIFS($H$48:$H$479,$D$48:$D$479,$A11,$A$48:$A$479,2027) -> 409960.64 | K11: =IF(J11=0,0,I11/J11) -> 0.92730492 | L11: =IF((D11+G11+J11)=0,0,(C11+F11+I11)/(D11+G11+J11)) -> 0.95314421 | M11: =RANK(L11,$L$9:$L$20,0) -> 8
A12: Diego Fontes | B12: Utilidades Domesticas | C12: =SUMIFS($G$48:$G$479,$D$48:$D$479,$A12,$A$48:$A$479,2025) -> 319321.19 | D12: =SUMIFS($H$48:$H$479,$D$48:$D$479,$A12,$A$48:$A$479,2025) -> 287371.26 | E12: =IF(D12=0,0,C12/D12) -> 1.11118 | F12: =SUMIFS($G$48:$G$479,$D$48:$D$479,$A12,$A$48:$A$479,2026) -> 316798.77 | G12: =SUMIFS($H$48:$H$479,$D$48:$D$479,$A12,$A$48:$A$479,2026) -> 304613.54 | H12: =IF(G12=0,0,F12/G12) -> 1.0400023 | I12: =SUMIFS($G$48:$G$479,$D$48:$D$479,$A12,$A$48:$A$479,2027) -> 332638.7 | J12: =SUMIFS($H$48:$H$479,$D$48:$D$479,$A12,$A$48:$A$479,2027) -> 322890.35 | K12: =IF(J12=0,0,I12/J12) -> 1.0301909 | L12: =IF((D12+G12+J12)=0,0,(C12+F12+I12)/(D12+G12+J12)) -> 1.0588971 | M12: =RANK(L12,$L$9:$L$20,0) -> 5
A13: Priscila Adorno | B13: Utilidades Domesticas | C13: =SUMIFS($G$48:$G$479,$D$48:$D$479,$A13,$A$48:$A$479,2025) -> 228086.56 | D13: =SUMIFS($H$48:$H$479,$D$48:$D$479,$A13,$A$48:$A$479,2025) -> 273672.63 | E13: =IF(D13=0,0,C13/D13) -> 0.83342847 | F13: =SUMIFS($G$48:$G$479,$D$48:$D$479,$A13,$A$48:$A$479,2026) -> 226284.83 | G13: =SUMIFS($H$48:$H$479,$D$48:$D$479,$A13,$A$48:$A$479,2026) -> 290092.99 | H13: =IF(G13=0,0,F13/G13) -> 0.78004241 | I13: =SUMIFS($G$48:$G$479,$D$48:$D$479,$A13,$A$48:$A$479,2027) -> 237599.07 | J13: =SUMIFS($H$48:$H$479,$D$48:$D$479,$A13,$A$48:$A$479,2027) -> 307498.57 | K13: =IF(J13=0,0,I13/J13) -> 0.77268352 | L13: =IF((D13+G13+J13)=0,0,(C13+F13+I13)/(D13+G13+J13)) -> 0.79421429 | M13: =RANK(L13,$L$9:$L$20,0) -> 12
A14: Henrique Vasques | B14: Papelaria e Impressao | C14: =SUMIFS($G$48:$G$479,$D$48:$D$479,$A14,$A$48:$A$479,2025) -> 80765.544 | D14: =SUMIFS($H$48:$H$479,$D$48:$D$479,$A14,$A$48:$A$479,2025) -> 84791.52 | E14: =IF(D14=0,0,C14/D14) -> 0.95251912 | F14: =SUMIFS($G$48:$G$479,$D$48:$D$479,$A14,$A$48:$A$479,2026) -> 118276.7 | G14: =SUMIFS($H$48:$H$479,$D$48:$D$479,$A14,$A$48:$A$479,2026) -> 89879.011 | H14: =IF(G14=0,0,F14/G14) -> 1.3159547 | I14: =SUMIFS($G$48:$G$479,$D$48:$D$479,$A14,$A$48:$A$479,2027) -> 130104.37 | J14: =SUMIFS($H$48:$H$479,$D$48:$D$479,$A14,$A$48:$A$479,2027) -> 95271.752 | K14: =IF(J14=0,0,I14/J14) -> 1.3656133 | L14: =IF((D14+G14+J14)=0,0,(C14+F14+I14)/(D14+G14+J14)) -> 1.2193222 | M14: =RANK(L14,$L$9:$L$20,0) -> 2
A15: Luana Prado | B15: Papelaria e Impressao | C15: =SUMIFS($G$48:$G$479,$D$48:$D$479,$A15,$A$48:$A$479,2025) -> 53843.696 | D15: =SUMIFS($H$48:$H$479,$D$48:$D$479,$A15,$A$48:$A$479,2025) -> 53794.62 | E15: =IF(D15=0,0,C15/D15) -> 1.0009123 | F15: =SUMIFS($G$48:$G$479,$D$48:$D$479,$A15,$A$48:$A$479,2026) -> 78851.136 | G15: =SUMIFS($H$48:$H$479,$D$48:$D$479,$A15,$A$48:$A$479,2026) -> 57022.297 | H15: =IF(G15=0,0,F15/G15) -> 1.3828123 | I15: =SUMIFS($G$48:$G$479,$D$48:$D$479,$A15,$A$48:$A$479,2027) -> 86736.25 | J15: =SUMIFS($H$48:$H$479,$D$48:$D$479,$A15,$A$48:$A$479,2027) -> 60443.635 | K15: =IF(J15=0,0,I15/J15) -> 1.4349939 | L15: =IF((D15+G15+J15)=0,0,(C15+F15+I15)/(D15+G15+J15)) -> 1.2812704 | M15: =RANK(L15,$L$9:$L$20,0) -> 1
A16: Marcelo Tavares | B16: Servicos Automotivos | C16: =SUMIFS($G$48:$G$479,$D$48:$D$479,$A16,$A$48:$A$479,2025) -> 327046.16 | D16: =SUMIFS($H$48:$H$479,$D$48:$D$479,$A16,$A$48:$A$479,2025) -> 327000 | E16: =IF(D16=0,0,C16/D16) -> 1.0001412 | F16: =SUMIFS($G$48:$G$479,$D$48:$D$479,$A16,$A$48:$A$479,2026) -> 349546.85 | G16: =SUMIFS($H$48:$H$479,$D$48:$D$479,$A16,$A$48:$A$479,2026) -> 346620 | H16: =IF(G16=0,0,F16/G16) -> 1.008444 | I16: =SUMIFS($G$48:$G$479,$D$48:$D$479,$A16,$A$48:$A$479,2027) -> 381006.07 | J16: =SUMIFS($H$48:$H$479,$D$48:$D$479,$A16,$A$48:$A$479,2027) -> 367417.2 | K16: =IF(J16=0,0,I16/J16) -> 1.0369848 | L16: =IF((D16+G16+J16)=0,0,(C16+F16+I16)/(D16+G16+J16)) -> 1.015909 | M16: =RANK(L16,$L$9:$L$20,0) -> 7
A17: Sofia Bittencourt | B17: Servicos Automotivos | C17: =SUMIFS($G$48:$G$479,$D$48:$D$479,$A17,$A$48:$A$479,2025) -> 267583.22 | D17: =SUMIFS($H$48:$H$479,$D$48:$D$479,$A17,$A$48:$A$479,2025) -> 254200 | E17: =IF(D17=0,0,C17/D17) -> 1.0526484 | F17: =SUMIFS($G$48:$G$479,$D$48:$D$479,$A17,$A$48:$A$479,2026) -> 285992.88 | G17: =SUMIFS($H$48:$H$479,$D$48:$D$479,$A17,$A$48:$A$479,2026) -> 269452 | H17: =IF(G17=0,0,F17/G17) -> 1.0613871 | I17: =SUMIFS($G$48:$G$479,$D$48:$D$479,$A17,$A$48:$A$479,2027) -> 311732.24 | J17: =SUMIFS($H$48:$H$479,$D$48:$D$479,$A17,$A$48:$A$479,2027) -> 285619.12 | K17: =IF(J17=0,0,I17/J17) -> 1.0914264 | L17: =IF((D17+G17+J17)=0,0,(C17+F17+I17)/(D17+G17+J17)) -> 1.0692441 | M17: =RANK(L17,$L$9:$L$20,0) -> 4
A18: Anderson Klein | B18: Vestuario | C18: =SUMIFS($G$48:$G$479,$D$48:$D$479,$A18,$A$48:$A$479,2025) -> 431719.24 | D18: =SUMIFS($H$48:$H$479,$D$48:$D$479,$A18,$A$48:$A$479,2025) -> 496549.65 | E18: =IF(D18=0,0,C18/D18) -> 0.8694382 | F18: =SUMIFS($G$48:$G$479,$D$48:$D$479,$A18,$A$48:$A$479,2026) -> 451379.48 | G18: =SUMIFS($H$48:$H$479,$D$48:$D$479,$A18,$A$48:$A$479,2026) -> 526342.63 | H18: =IF(G18=0,0,F18/G18) -> 0.85757729 | I18: =SUMIFS($G$48:$G$479,$D$48:$D$479,$A18,$A$48:$A$479,2027) -> 482976.05 | J18: =SUMIFS($H$48:$H$479,$D$48:$D$479,$A18,$A$48:$A$479,2027) -> 557923.19 | K18: =IF(J18=0,0,I18/J18) -> 0.86566764 | L18: =IF((D18+G18+J18)=0,0,(C18+F18+I18)/(D18+G18+J18)) -> 0.86415828 | M18: =RANK(L18,$L$9:$L$20,0) -> 11
A19: Renata Villaca | B19: Vestuario | C19: =SUMIFS($G$48:$G$479,$D$48:$D$479,$A19,$A$48:$A$479,2025) -> 604406.93 | D19: =SUMIFS($H$48:$H$479,$D$48:$D$479,$A19,$A$48:$A$479,2025) -> 556155.61 | E19: =IF(D19=0,0,C19/D19) -> 1.0867587 | F19: =SUMIFS($G$48:$G$479,$D$48:$D$479,$A19,$A$48:$A$479,2026) -> 631931.28 | G19: =SUMIFS($H$48:$H$479,$D$48:$D$479,$A19,$A$48:$A$479,2026) -> 589524.95 | H19: =IF(G19=0,0,F19/G19) -> 1.0719331 | I19: =SUMIFS($G$48:$G$479,$D$48:$D$479,$A19,$A$48:$A$479,2027) -> 676166.47 | J19: =SUMIFS($H$48:$H$479,$D$48:$D$479,$A19,$A$48:$A$479,2027) -> 624896.44 | K19: =IF(J19=0,0,I19/J19) -> 1.0820456 | L19: =IF((D19+G19+J19)=0,0,(C19+F19+I19)/(D19+G19+J19)) -> 1.080159 | M19: =RANK(L19,$L$9:$L$20,0) -> 3
A20: Tiago Moura | B20: Vestuario | C20: =SUMIFS($G$48:$G$479,$D$48:$D$479,$A20,$A$48:$A$479,2025) -> 402937.95 | D20: =SUMIFS($H$48:$H$479,$D$48:$D$479,$A20,$A$48:$A$479,2025) -> 423142.31 | E20: =IF(D20=0,0,C20/D20) -> 0.95225163 | F20: =SUMIFS($G$48:$G$479,$D$48:$D$479,$A20,$A$48:$A$479,2026) -> 421287.52 | G20: =SUMIFS($H$48:$H$479,$D$48:$D$479,$A20,$A$48:$A$479,2026) -> 448530.85 | H20: =IF(G20=0,0,F20/G20) -> 0.93926097 | I20: =SUMIFS($G$48:$G$479,$D$48:$D$479,$A20,$A$48:$A$479,2027) -> 450777.64 | J20: =SUMIFS($H$48:$H$479,$D$48:$D$479,$A20,$A$48:$A$479,2027) -> 475442.7 | K20: =IF(J20=0,0,I20/J20) -> 0.94812192 | L20: =IF((D20+G20+J20)=0,0,(C20+F20+I20)/(D20+G20+J20)) -> 0.94646879 | M20: =RANK(L20,$L$9:$L$20,0) -> 9
A21: TOTAL / MEDIA | B21: Grupo | C21: =SUM(C9:C20) -> 3574762.7 | D21: =SUM(D9:D20) -> 3624391.4 | E21: =IF(D21=0,0,C21/D21) -> 0.98630703 | F21: =SUM(F9:F20) -> 3763378.7 | G21: =SUM(G9:G20) -> 3841854.9 | H21: =IF(G21=0,0,F21/G21) -> 0.97957336 | I21: =SUM(I9:I20) -> 4032546.8 | J21: =SUM(J9:J20) -> 4072366.2 | K21: =IF(J21=0,0,I21/J21) -> 0.99022205 | L21: =IF((D21+G21+J21)=0,0,(C21+F21+I21)/(D21+G21+J21)) -> 0.98544675
A23: CADASTRO DE REPRESENTANTES
A24: Representante | B24: Segmento | C24: Regiao | D24: Participacao no Segmento | E24: Meta Anual 2025 (R$) | F24: Meta Anual 2026 (R$) | G24: Meta Anual 2027 (R$) | H24: Dificuldade
A25: Rafael Nogueira | B25: Materiais de Construcao | C25: Sudeste | D25: 0.55 | E25: 258200 | F25: =E25*(1+$B$5) -> 273692 | G25: =F25*(1+$B$5) -> 290113.52 | H25: 0.95
A26: Beatriz Ramalho | B26: Materiais de Construcao | C26: Sul | D26: 0.45 | E26: 244600 | F26: =E26*(1+$B$5) -> 259276 | G26: =F26*(1+$B$5) -> 274832.56 | H26: 1.1
A27: Carla Menezes | B27: Utilidades Domesticas | C27: Sudeste | D27: 0.4 | E27: 364900 | F27: =E27*(1+$B$5) -> 386794 | G27: =F27*(1+$B$5) -> 410001.64 | H27: 1
A28: Diego Fontes | B28: Utilidades Domesticas | C28: Nordeste | D28: 0.35 | E28: 287400 | F28: =E28*(1+$B$5) -> 304644 | G28: =F28*(1+$B$5) -> 322922.64 | H28: 0.9
A29: Priscila Adorno | B29: Utilidades Domesticas | C29: Sul | D29: 0.25 | E29: 273700 | F29: =E29*(1+$B$5) -> 290122 | G29: =F29*(1+$B$5) -> 307529.32 | H29: 1.2
A30: Henrique Vasques | B30: Papelaria e Impressao | C30: Sudeste | D30: 0.6 | E30: 84800 | F30: =E30*(1+$B$5) -> 89888 | G30: =F30*(1+$B$5) -> 95281.28 | H30: 1.05
A31: Luana Prado | B31: Papelaria e Impressao | C31: Centro-Oeste | D31: 0.4 | E31: 53800 | F31: =E31*(1+$B$5) -> 57028 | G31: =F31*(1+$B$5) -> 60449.68 | H31: 1
A32: Marcelo Tavares | B32: Servicos Automotivos | C32: Sudeste | D32: 0.55 | E32: 327000 | F32: =E32*(1+$B$5) -> 346620 | G32: =F32*(1+$B$5) -> 367417.2 | H32: 1
A33: Sofia Bittencourt | B33: Servicos Automotivos | C33: Sul | D33: 0.45 | E33: 254200 | F33: =E33*(1+$B$5) -> 269452 | G33: =F33*(1+$B$5) -> 285619.12 | H33: 0.95
A34: Anderson Klein | B34: Vestuario | C34: Sul | D34: 0.3 | E34: 496500 | F34: =E34*(1+$B$5) -> 526290 | G34: =F34*(1+$B$5) -> 557867.4 | H34: 1.15
A35: Renata Villaca | B35: Vestuario | C35: Sudeste | D35: 0.42 | E35: 556100 | F35: =E35*(1+$B$5) -> 589466 | G35: =F35*(1+$B$5) -> 624833.96 | H35: 0.92
A36: Tiago Moura | B36: Vestuario | C36: Nordeste | D36: 0.28 | E36: 423100 | F36: =E36*(1+$B$5) -> 448486 | G36: =F36*(1+$B$5) -> 475395.16 | H36: 1.05
A38: PERFIL DE SAZONALIDADE DAS METAS (peso mensal, base real 2025)
A39: Segmento | B39: 45658 | C39: 45689 | D39: 45717 | E39: 45748 | F39: 45778 | G39: 45809 | H39: 45839 | I39: 45870 | J39: 45901 | K39: 45931 | L39: 45962 | M39: 45992
A40: Materiais de Construcao | B40: 0.0573 | C40: 0.083 | D40: 0.0839 | E40: 0.0642 | F40: 0.0929 | G40: 0.0893 | H40: 0.0934 | I40: 0.0766 | J40: 0.0655 | K40: 0.1044 | L40: 0.1 | M40: 0.0896
A41: Utilidades Domesticas | B41: 0.0684 | C41: 0.0679 | D41: 0.0682 | E41: 0.08 | F41: 0.0748 | G41: 0.1024 | H41: 0.095 | I41: 0.0817 | J41: 0.0753 | K41: 0.0768 | L41: 0.0991 | M41: 0.1103
A42: Papelaria e Impressao | B42: 0.2215 | C42: 0.04 | D42: 0.0675 | E42: 0.0659 | F42: 0.0582 | G42: 0.05 | H42: 0.0408 | I42: 0.0436 | J42: 0.1898 | K42: 0.0501 | L42: 0.0435 | M42: 0.129
A43: Servicos Automotivos | B43: 0.0687 | C43: 0.0766 | D43: 0.0805 | E43: 0.0923 | F43: 0.0809 | G43: 0.0767 | H43: 0.0913 | I43: 0.0689 | J43: 0.0694 | K43: 0.0882 | L43: 0.106 | M43: 0.1005
A44: Vestuario | B44: 0.0695 | C44: 0.0674 | D44: 0.081 | E44: 0.0782 | F44: 0.0805 | G44: 0.0846 | H44: 0.0845 | I44: 0.0813 | J44: 0.082 | K44: 0.0828 | L44: 0.1025 | M44: 0.1058
A46: BASE MENSAL DETALHADA
A47: Ano | B47: Mes | C47: ChaveMes | D47: Representante | E47: Segmento | F47: Regiao | G47: Vendas Realizadas | H47: Meta | I47: Atingimento % | J47: Desvio (R$) | K47: Realizado YTD | L47: Meta YTD | M47: Atingimento YTD %
A48: 2025 | B48: 1 | C48: 2025-01 | D48: Rafael Nogueira | E48: Materiais de Construcao | F48: Sudeste | G48: =SUMIFS(DRE_por_UN!$F:$F,DRE_por_UN!$C:$C,$C48,DRE_por_UN!$E:$E,$E48)*VLOOKUP($D48,$A$25:$H$36,4,0) -> 15583.535 | H48: =VLOOKUP($D48,$A$25:$H$36,5,0)*(1+$B$5)^($A48-2025)*INDEX($B$40:$M$44,MATCH($E48,$A$40:$A$44,0),$B48) -> 14794.86 | I48: =IF(H48=0,0,G48/H48) -> 1.0533074 | J48: =G48-H48 -> 788.675 | K48: =SUMIFS($G$48:$G$479,$D$48:$D$479,$D48,$A$48:$A$479,$A48,$B$48:$B$479,"<="&$B48) -> 15583.535 | L48: =SUMIFS($H$48:$H$479,$D$48:$D$479,$D48,$A$48:$A$479,$A48,$B$48:$B$479,"<="&$B48) -> 14794.86 | M48: =IF(L48=0,0,K48/L48) -> 1.0533074
A49: 2025 | B49: 2 | C49: 2025-02 | D49: Rafael Nogueira | E49: Materiais de Construcao | F49: Sudeste | G49: =SUMIFS(DRE_por_UN!$F:$F,DRE_por_UN!$C:$C,$C49,DRE_por_UN!$E:$E,$E49)*VLOOKUP($D49,$A$25:$H$36,4,0) -> 22549.065 | H49: =VLOOKUP($D49,$A$25:$H$36,5,0)*(1+$B$5)^($A49-2025)*INDEX($B$40:$M$44,MATCH($E49,$A$40:$A$44,0),$B49) -> 21430.6 | I49: =IF(H49=0,0,G49/H49) -> 1.0521901 | J49: =G49-H49 -> 1118.465 | K49: =SUMIFS($G$48:$G$479,$D$48:$D$479,$D49,$A$48:$A$479,$A49,$B$48:$B$479,"<="&$B49) -> 38132.6 | L49: =SUMIFS($H$48:$H$479,$D$48:$D$479,$D49,$A$48:$A$479,$A49,$B$48:$B$479,"<="&$B49) -> 36225.46 | M49: =IF(L49=0,0,K49/L49) -> 1.0526464
A50: 2025 | B50: 3 | C50: 2025-03 | D50: Rafael Nogueira | E50: Materiais de Construcao | F50: Sudeste | G50: =SUMIFS(DRE_por_UN!$F:$F,DRE_por_UN!$C:$C,$C50,DRE_por_UN!$E:$E,$E50)*VLOOKUP($D50,$A$25:$H$36,4,0) -> 22803.198 | H50: =VLOOKUP($D50,$A$25:$H$36,5,0)*(1+$B$5)^($A50-2025)*INDEX($B$40:$M$44,MATCH($E50,$A$40:$A$44,0),$B50) -> 21662.98 | I50: =IF(H50=0,0,G50/H50) -> 1.0526344 | J50: =G50-H50 -> 1140.218 | K50: =SUMIFS($G$48:$G$479,$D$48:$D$479,$D50,$A$48:$A$479,$A50,$B$48:$B$479,"<="&$B50) -> 60935.798 | L50: =SUMIFS($H$48:$H$479,$D$48:$D$479,$D50,$A$48:$A$479,$A50,$B$48:$B$479,"<="&$B50) -> 57888.44 | M50: =IF(L50=0,0,K50/L50) -> 1.0526419
A51: 2025 | B51: 4 | C51: 2025-04 | D51: Rafael Nogueira | E51: Materiais de Construcao | F51: Sudeste | G51: =SUMIFS(DRE_por_UN!$F:$F,DRE_por_UN!$C:$C,$C51,DRE_por_UN!$E:$E,$E51)*VLOOKUP($D51,$A$25:$H$36,4,0) -> 17445.439 | H51: =VLOOKUP($D51,$A$25:$H$36,5,0)*(1+$B$5)^($A51-2025)*INDEX($B$40:$M$44,MATCH($E51,$A$40:$A$44,0),$B51) -> 16576.44 | I51: =IF(H51=0,0,G51/H51) -> 1.0524237 | J51: =G51-H51 -> 868.999 | K51: =SUMIFS($G$48:$G$479,$D$48:$D$479,$D51,$A$48:$A$479,$A51,$B$48:$B$479,"<="&$B51) -> 78381.237 | L51: =SUMIFS($H$48:$H$479,$D$48:$D$479,$D51,$A$48:$A$479,$A51,$B$48:$B$479,"<="&$B51) -> 74464.88 | M51: =IF(L51=0,0,K51/L51) -> 1.0525933
A52: 2025 | B52: 5 | C52: 2025-05 | D52: Rafael Nogueira | E52: Materiais de Construcao | F52: Sudeste | G52: =SUMIFS(DRE_por_UN!$F:$F,DRE_por_UN!$C:$C,$C52,DRE_por_UN!$E:$E,$E52)*VLOOKUP($D52,$A$25:$H$36,4,0) -> 25246.458 | H52: =VLOOKUP($D52,$A$25:$H$36,5,0)*(1+$B$5)^($A52-2025)*INDEX($B$40:$M$44,MATCH($E52,$A$40:$A$44,0),$B52) -> 23986.78 | I52: =IF(H52=0,0,G52/H52) -> 1.0525155 | J52: =G52-H52 -> 1259.6775 | K52: =SUMIFS($G$48:$G$479,$D$48:$D$479,$D52,$A$48:$A$479,$A52,$B$48:$B$479,"<="&$B52) -> 103627.69 | L52: =SUMIFS($H$48:$H$479,$D$48:$D$479,$D52,$A$48:$A$479,$A52,$B$48:$B$479,"<="&$B52) -> 98451.66 | M52: =IF(L52=0,0,K52/L52) -> 1.0525744
A53: 2025 | B53: 6 | C53: 2025-06 | D53: Rafael Nogueira | E53: Materiais de Construcao | F53: Sudeste | G53: =SUMIFS(DRE_por_UN!$F:$F,DRE_por_UN!$C:$C,$C53,DRE_por_UN!$E:$E,$E53)*VLOOKUP($D53,$A$25:$H$36,4,0) -> 24268.195 | H53: =VLOOKUP($D53,$A$25:$H$36,5,0)*(1+$B$5)^($A53-2025)*INDEX($B$40:$M$44,MATCH($E53,$A$40:$A$44,0),$B53) -> 23057.26 | I53: =IF(H53=0,0,G53/H53) -> 1.0525186 | J53: =G53-H53 -> 1210.9345 | K53: =SUMIFS($G$48:$G$479,$D$48:$D$479,$D53,$A$48:$A$479,$A53,$B$48:$B$479,"<="&$B53) -> 127895.89 | L53: =SUMIFS($H$48:$H$479,$D$48:$D$479,$D53,$A$48:$A$479,$A53,$B$48:$B$479,"<="&$B53) -> 121508.92 | M53: =IF(L53=0,0,K53/L53) -> 1.0525638
A54: 2025 | B54: 7 | C54: 2025-07 | D54: Rafael Nogueira | E54: Materiais de Construcao | F54: Sudeste | G54: =SUMIFS(DRE_por_UN!$F:$F,DRE_por_UN!$C:$C,$C54,DRE_por_UN!$E:$E,$E54)*VLOOKUP($D54,$A$25:$H$36,4,0) -> 25382.352 | H54: =VLOOKUP($D54,$A$25:$H$36,5,0)*(1+$B$5)^($A54-2025)*INDEX($B$40:$M$44,MATCH($E54,$A$40:$A$44,0),$B54) -> 24115.88 | I54: =IF(H54=0,0,G54/H54) -> 1.0525161 | J54: =G54-H54 -> 1266.4715 | K54: =SUMIFS($G$48:$G$479,$D$48:$D$479,$D54,$A$48:$A$479,$A54,$B$48:$B$479,"<="&$B54) -> 153278.24 | L54: =SUMIFS($H$48:$H$479,$D$48:$D$479,$D54,$A$48:$A$479,$A54,$B$48:$B$479,"<="&$B54) -> 145624.8 | M54: =IF(L54=0,0,K54/L54) -> 1.0525559
A55: 2025 | B55: 8 | C55: 2025-08 | D55: Rafael Nogueira | E55: Materiais de Construcao | F55: Sudeste | G55: =SUMIFS(DRE_por_UN!$F:$F,DRE_por_UN!$C:$C,$C55,DRE_por_UN!$E:$E,$E55)*VLOOKUP($D55,$A$25:$H$36,4,0) -> 20805.246 | H55: =VLOOKUP($D55,$A$25:$H$36,5,0)*(1+$B$5)^($A55-2025)*INDEX($B$40:$M$44,MATCH($E55,$A$40:$A$44,0),$B55) -> 19778.12 | I55: =IF(H55=0,0,G55/H55) -> 1.0519324 | J55: =G55-H55 -> 1027.126 | K55: =SUMIFS($G$48:$G$479,$D$48:$D$479,$D55,$A$48:$A$479,$A55,$B$48:$B$479,"<="&$B55) -> 174083.49 | L55: =SUMIFS($H$48:$H$479,$D$48:$D$479,$D55,$A$48:$A$479,$A55,$B$48:$B$479,"<="&$B55) -> 165402.92 | M55: =IF(L55=0,0,K55/L55) -> 1.0524813
A56: 2025 | B56: 9 | C56: 2025-09 | D56: Rafael Nogueira | E56: Materiais de Construcao | F56: Sudeste | G56: =SUMIFS(DRE_por_UN!$F:$F,DRE_por_UN!$C:$C,$C56,DRE_por_UN!$E:$E,$E56)*VLOOKUP($D56,$A$25:$H$36,4,0) -> 17789.371 | H56: =VLOOKUP($D56,$A$25:$H$36,5,0)*(1+$B$5)^($A56-2025)*INDEX($B$40:$M$44,MATCH($E56,$A$40:$A$44,0),$B56) -> 16912.1 | I56: =IF(H56=0,0,G56/H56) -> 1.0518724 | J56: =G56-H56 -> 877.2705 | K56: =SUMIFS($G$48:$G$479,$D$48:$D$479,$D56,$A$48:$A$479,$A56,$B$48:$B$479,"<="&$B56) -> 191872.86 | L56: =SUMIFS($H$48:$H$479,$D$48:$D$479,$D56,$A$48:$A$479,$A56,$B$48:$B$479,"<="&$B56) -> 182315.02 | M56: =IF(L56=0,0,K56/L56) -> 1.0524248
A57: 2025 | B57: 10 | C57: 2025-10 | D57: Rafael Nogueira | E57: Materiais de Construcao | F57: Sudeste | G57: =SUMIFS(DRE_por_UN!$F:$F,DRE_por_UN!$C:$C,$C57,DRE_por_UN!$E:$E,$E57)*VLOOKUP($D57,$A$25:$H$36,4,0) -> 28372.558 | H57: =VLOOKUP($D57,$A$25:$H$36,5,0)*(1+$B$5)^($A57-2025)*INDEX($B$40:$M$44,MATCH($E57,$A$40:$A$44,0),$B57) -> 26956.08 | I57: =IF(H57=0,0,G57/H57) -> 1.0525476 | J57: =G57-H57 -> 1416.4785 | K57: =SUMIFS($G$48:$G$479,$D$48:$D$479,$D57,$A$48:$A$479,$A57,$B$48:$B$479,"<="&$B57) -> 220245.42 | L57: =SUMIFS($H$48:$H$479,$D$48:$D$479,$D57,$A$48:$A$479,$A57,$B$48:$B$479,"<="&$B57) -> 209271.1 | M57: =IF(L57=0,0,K57/L57) -> 1.0524407
A58: 2025 | B58: 11 | C58: 2025-11 | D58: Rafael Nogueira | E58: Materiais de Construcao | F58: Sudeste | G58: =SUMIFS(DRE_por_UN!$F:$F,DRE_por_UN!$C:$C,$C58,DRE_por_UN!$E:$E,$E58)*VLOOKUP($D58,$A$25:$H$36,4,0) -> 27164.528 | H58: =VLOOKUP($D58,$A$25:$H$36,5,0)*(1+$B$5)^($A58-2025)*INDEX($B$40:$M$44,MATCH($E58,$A$40:$A$44,0),$B58) -> 25820 | I58: =IF(H58=0,0,G58/H58) -> 1.0520731 | J58: =G58-H58 -> 1344.5275 | K58: =SUMIFS($G$48:$G$479,$D$48:$D$479,$D58,$A$48:$A$479,$A58,$B$48:$B$479,"<="&$B58) -> 247409.94 | L58: =SUMIFS($H$48:$H$479,$D$48:$D$479,$D58,$A$48:$A$479,$A58,$B$48:$B$479,"<="&$B58) -> 235091.1 | M58: =IF(L58=0,0,K58/L58) -> 1.0524003
A59: 2025 | B59: 12 | C59: 2025-12 | D59: Rafael Nogueira | E59: Materiais de Construcao | F59: Sudeste | G59: =SUMIFS(DRE_por_UN!$F:$F,DRE_por_UN!$C:$C,$C59,DRE_por_UN!$E:$E,$E59)*VLOOKUP($D59,$A$25:$H$36,4,0) -> 24352.592 | H59: =VLOOKUP($D59,$A$25:$H$36,5,0)*(1+$B$5)^($A59-2025)*INDEX($B$40:$M$44,MATCH($E59,$A$40:$A$44,0),$B59) -> 23134.72 | I59: =IF(H59=0,0,G59/H59) -> 1.0526426 | J59: =G59-H59 -> 1217.872 | K59: =SUMIFS($G$48:$G$479,$D$48:$D$479,$D59,$A$48:$A$479,$A59,$B$48:$B$479,"<="&$B59) -> 271762.53 | L59: =SUMIFS($H$48:$H$479,$D$48:$D$479,$D59,$A$48:$A$479,$A59,$B$48:$B$479,"<="&$B59) -> 258225.82 | M59: =IF(L59=0,0,K59/L59) -> 1.052422
... A479: 2027 | B479: 12 | C479: 2027-12 | D479: Tiago Moura | E479: Vestuario | F479: Nordeste | G479: =SUMIFS(DRE_por_UN!$F:$F,DRE_por_UN!$C:$C,$C479,DRE_por_UN!$E:$E,$E479)*VLOOKUP($D479,$A$25:$H$36,4,0) -> 47917.347 | H479: =VLOOKUP($D479,$A$25:$H$36,5,0)*(1+$B$5)^($A479-2025)*INDEX($B$40:$M$44,MATCH($E479,$A$40:$A$44,0),$B479) -> 50296.808 | I479: =IF(H479=0,0,G479/H479) -> 0.95269161 | J479: =G479-H479 -> -2379.461 | K479: =SUMIFS($G$48:$G$479,$D$48:$D$479,$D479,$A$48:$A$479,$A479,$B$48:$B$479,"<="&$B479) -> 450777.64 | L479: =SUMIFS($H$48:$H$479,$D$48:$D$479,$D479,$A$48:$A$479,$A479,$B$48:$B$479,"<="&$B479) -> 475442.7 | M479: =IF(L479=0,0,K479/L479) -> 0.94812192

Sheet DRE_por_UN
A1: Ano | B1: Mes | C1: ChaveMes | D1: DataRef | E1: Unidade | F1: Receita Bruta | G1: Impostos s/ Vendas | H1: Receita Liquida | I1: Margem Bruta % aplic. | J1: CMV | K1: Lucro Bruto | L1: Folha Direta | M1: Aluguel/Ocupacao | N1: Marketing | O1: Frete/Logistica | P1: Outras Desp. Diretas | Q1: EBITDA da Unidade
A2: 2025 | B2: 1 | C2: 2025-01 | D2: 45658 | E2: Materiais de Construcao | F2: 28333.7 | G2: 10976.54 | H2: =F2-G2 -> 17357.16 | I2: =IF($A2=2025,VLOOKUP($E2,Premissas!$A$52:$P$56,2,0),IF($A2=2026,VLOOKUP($E2,Premissas!$A$52:$P$56,3,0),VLOOKUP($E2,Premissas!$A$52:$P$56,4,0))) -> 0.3 | J2: =H2*(1-I2) -> 12150.012 | K2: =H2-J2 -> 5207.148 | L2: =SUMIFS(Headcount_Folha!$I:$I,Headcount_Folha!$C:$C,$C2,Headcount_Folha!$D:$D,$E2) -> 7392 | M2: =VLOOKUP($E2,Premissas!$A$52:$P$56,10,0)*(1+VLOOKUP($E2,Premissas!$A$52:$P$56,11,0))^($A2-2025) -> 2000 | N2: =H2*VLOOKUP($E2,Premissas!$A$52:$P$56,7,0) -> 260.3574 | O2: =H2*VLOOKUP($E2,Premissas!$A$52:$P$56,8,0) -> 694.2864 | P2: =H2*VLOOKUP($E2,Premissas!$A$52:$P$56,9,0) -> 347.1432 | Q2: =K2-L2-M2-N2-O2-P2 -> -5486.639
A3: 2025 | B3: 2 | C3: 2025-02 | D3: 45689 | E3: Materiais de Construcao | F3: 40998.3 | G3: 15547.09 | H3: =F3-G3 -> 25451.21 | I3: =IF($A3=2025,VLOOKUP($E3,Premissas!$A$52:$P$56,2,0),IF($A3=2026,VLOOKUP($E3,Premissas!$A$52:$P$56,3,0),VLOOKUP($E3,Premissas!$A$52:$P$56,4,0))) -> 0.3 | J3: =H3*(1-I3) -> 17815.847 | K3: =H3-J3 -> 7635.363 | L3: =SUMIFS(Headcount_Folha!$I:$I,Headcount_Folha!$C:$C,$C3,Headcount_Folha!$D:$D,$E3) -> 7392 | M3: =VLOOKUP($E3,Premissas!$A$52:$P$56,10,0)*(1+VLOOKUP($E3,Premissas!$A$52:$P$56,11,0))^($A3-2025) -> 2000 | N3: =H3*VLOOKUP($E3,Premissas!$A$52:$P$56,7,0) -> 381.76815 | O3: =H3*VLOOKUP($E3,Premissas!$A$52:$P$56,8,0) -> 1018.0484 | P3: =H3*VLOOKUP($E3,Premissas!$A$52:$P$56,9,0) -> 509.0242 | Q3: =K3-L3-M3-N3-O3-P3 -> -3665.4778
A4: 2025 | B4: 3 | C4: 2025-03 | D4: 45717 | E4: Materiais de Construcao | F4: 41460.36 | G4: 16952.33 | H4: =F4-G4 -> 24508.03 | I4: =IF($A4=2025,VLOOKUP($E4,Premissas!$A$52:$P$56,2,0),IF($A4=2026,VLOOKUP($E4,Premissas!$A$52:$P$56,3,0),VLOOKUP($E4,Premissas!$A$52:$P$56,4,0))) -> 0.3 | J4: =H4*(1-I4) -> 17155.621 | K4: =H4-J4 -> 7352.409 | L4: =SUMIFS(Headcount_Folha!$I:$I,Headcount_Folha!$C:$C,$C4,Headcount_Folha!$D:$D,$E4) -> 7392 | M4: =VLOOKUP($E4,Premissas!$A$52:$P$56,10,0)*(1+VLOOKUP($E4,Premissas!$A$52:$P$56,11,0))^($A4-2025) -> 2000 | N4: =H4*VLOOKUP($E4,Premissas!$A$52:$P$56,7,0) -> 367.62045 | O4: =H4*VLOOKUP($E4,Premissas!$A$52:$P$56,8,0) -> 980.3212 | P4: =H4*VLOOKUP($E4,Premissas!$A$52:$P$56,9,0) -> 490.1606 | Q4: =K4-L4-M4-N4-O4-P4 -> -3877.6932
A5: 2025 | B5: 4 | C5: 2025-04 | D5: 45748 | E5: Materiais de Construcao | F5: 31718.98 | G5: 12511.23 | H5: =F5-G5 -> 19207.75 | I5: =IF($A5=2025,VLOOKUP($E5,Premissas!$A$52:$P$56,2,0),IF($A5=2026,VLOOKUP($E5,Premissas!$A$52:$P$56,3,0),VLOOKUP($E5,Premissas!$A$52:$P$56,4,0))) -> 0.3 | J5: =H5*(1-I5) -> 13445.425 | K5: =H5-J5 -> 5762.325 | L5: =SUMIFS(Headcount_Folha!$I:$I,Headcount_Folha!$C:$C,$C5,Headcount_Folha!$D:$D,$E5) -> 7392 | M5: =VLOOKUP($E5,Premissas!$A$52:$P$56,10,0)*(1+VLOOKUP($E5,Premissas!$A$52:$P$56,11,0))^($A5-2025) -> 2000 | N5: =H5*VLOOKUP($E5,Premissas!$A$52:$P$56,7,0) -> 288.11625 | O5: =H5*VLOOKUP($E5,Premissas!$A$52:$P$56,8,0) -> 768.31 | P5: =H5*VLOOKUP($E5,Premissas!$A$52:$P$56,9,0) -> 384.155 | Q5: =K5-L5-M5-N5-O5-P5 -> -5070.2563
A6: 2025 | B6: 5 | C6: 2025-05 | D6: 45778 | E6: Materiais de Construcao | F6: 45902.65 | G6: 18226.98 | H6: =F6-G6 -> 27675.67 | I6: =IF($A6=2025,VLOOKUP($E6,Premissas!$A$52:$P$56,2,0),IF($A6=2026,VLOOKUP($E6,Premissas!$A$52:$P$56,3,0),VLOOKUP($E6,Premissas!$A$52:$P$56,4,0))) -> 0.3 | J6: =H6*(1-I6) -> 19372.969 | K6: =H6-J6 -> 8302.701 | L6: =SUMIFS(Headcount_Folha!$I:$I,Headcount_Folha!$C:$C,$C6,Headcount_Folha!$D:$D,$E6) -> 7392 | M6: =VLOOKUP($E6,Premissas!$A$52:$P$56,10,0)*(1+VLOOKUP($E6,Premissas!$A$52:$P$56,11,0))^($A6-2025) -> 2000 | N6: =H6*VLOOKUP($E6,Premissas!$A$52:$P$56,7,0) -> 415.13505 | O6: =H6*VLOOKUP($E6,Premissas!$A$52:$P$56,8,0) -> 1107.0268 | P6: =H6*VLOOKUP($E6,Premissas!$A$52:$P$56,9,0) -> 553.5134 | Q6: =K6-L6-M6-N6-O6-P6 -> -3164.9743
A7: 2025 | B7: 6 | C7: 2025-06 | D7: 45809 | E7: Materiais de Construcao | F7: 44123.99 | G7: 17913.96 | H7: =F7-G7 -> 26210.03 | I7: =IF($A7=2025,VLOOKUP($E7,Premissas!$A$52:$P$56,2,0),IF($A7=2026,VLOOKUP($E7,Premissas!$A$52:$P$56,3,0),VLOOKUP($E7,Premissas!$A$52:$P$56,4,0))) -> 0.3 | J7: =H7*(1-I7) -> 18347.021 | K7: =H7-J7 -> 7863.009 | L7: =SUMIFS(Headcount_Folha!$I:$I,Headcount_Folha!$C:$C,$C7,Headcount_Folha!$D:$D,$E7) -> 7392 | M7: =VLOOKUP($E7,Premissas!$A$52:$P$56,10,0)*(1+VLOOKUP($E7,Premissas!$A$52:$P$56,11,0))^($A7-2025) -> 2000 | N7: =H7*VLOOKUP($E7,Premissas!$A$52:$P$56,7,0) -> 393.15045 | O7: =H7*VLOOKUP($E7,Premissas!$A$52:$P$56,8,0) -> 1048.4012 | P7: =H7*VLOOKUP($E7,Premissas!$A$52:$P$56,9,0) -> 524.2006 | Q7: =K7-L7-M7-N7-O7-P7 -> -3494.7432
A8: 2025 | B8: 7 | C8: 2025-07 | D8: 45839 | E8: Materiais de Construcao | F8: 46149.73 | G8: 18062.72 | H8: =F8-G8 -> 28087.01 | I8: =IF($A8=2025,VLOOKUP($E8,Premissas!$A$52:$P$56,2,0),IF($A8=2026,VLOOKUP($E8,Premissas!$A$52:$P$56,3,0),VLOOKUP($E8,Premissas!$A$52:$P$56,4,0))) -> 0.3 | J8: =H8*(1-I8) -> 19660.907 | K8: =H8-J8 -> 8426.103 | L8: =SUMIFS(Headcount_Folha!$I:$I,Headcount_Folha!$C:$C,$C8,Headcount_Folha!$D:$D,$E8) -> 7392 | M8: =VLOOKUP($E8,Premissas!$A$52:$P$56,10,0)*(1+VLOOKUP($E8,Premissas!$A$52:$P$56,11,0))^($A8-2025) -> 2000 | N8: =H8*VLOOKUP($E8,Premissas!$A$52:$P$56,7,0) -> 421.30515 | O8: =H8*VLOOKUP($E8,Premissas!$A$52:$P$56,8,0) -> 1123.4804 | P8: =H8*VLOOKUP($E8,Premissas!$A$52:$P$56,9,0) -> 561.7402 | Q8: =K8-L8-M8-N8-O8-P8 -> -3072.4228
A9: 2025 | B9: 8 | C9: 2025-08 | D9: 45870 | E9: Materiais de Construcao | F9: 37827.72 | G9: 14097.8 | H9: =F9-G9 -> 23729.92 | I9: =IF($A9=2025,VLOOKUP($E9,Premissas!$A$52:$P$56,2,0),IF($A9=2026,VLOOKUP($E9,Premissas!$A$52:$P$56,3,0),VLOOKUP($E9,Premissas!$A$52:$P$56,4,0))) -> 0.3 | J9: =H9*(1-I9) -> 16610.944 | K9: =H9-J9 -> 7118.976 | L9: =SUMIFS(Headcount_Folha!$I:$I,Headcount_Folha!$C:$C,$C9,Headcount_Folha!$D:$D,$E9) -> 7392 | M9: =VLOOKUP($E9,Premissas!$A$52:$P$56,10,0)*(1+VLOOKUP($E9,Premissas!$A$52:$P$56,11,0))^($A9-2025) -> 2000 | N9: =H9*VLOOKUP($E9,Premissas!$A$52:$P$56,7,0) -> 355.9488 | O9: =H9*VLOOKUP($E9,Premissas!$A$52:$P$56,8,0) -> 949.1968 | P9: =H9*VLOOKUP($E9,Premissas!$A$52:$P$56,9,0) -> 474.5984 | Q9: =K9-L9-M9-N9-O9-P9 -> -4052.768
A10: 2025 | B10: 9 | C10: 2025-09 | D10: 45901 | E10: Materiais de Construcao | F10: 32344.31 | G10: 12588.19 | H10: =F10-G10 -> 19756.12 | I10: =IF($A10=2025,VLOOKUP($E10,Premissas!$A$52:$P$56,2,0),IF($A10=2026,VLOOKUP($E10,Premissas!$A$52:$P$56,3,0),VLOOKUP($E10,Premissas!$A$52:$P$56,4,0))) -> 0.3 | J10: =H10*(1-I10) -> 13829.284 | K10: =H10-J10 -> 5926.836 | L10: =SUMIFS(Headcount_Folha!$I:$I,Headcount_Folha!$C:$C,$C10,Headcount_Folha!$D:$D,$E10) -> 7392 | M10: =VLOOKUP($E10,Premissas!$A$52:$P$56,10,0)*(1+VLOOKUP($E10,Premissas!$A$52:$P$56,11,0))^($A10-2025) -> 2000 | N10: =H10*VLOOKUP($E10,Premissas!$A$52:$P$56,7,0) -> 296.3418 | O10: =H10*VLOOKUP($E10,Premissas!$A$52:$P$56,8,0) -> 790.2448 | P10: =H10*VLOOKUP($E10,Premissas!$A$52:$P$56,9,0) -> 395.1224 | Q10: =K10-L10-M10-N10-O10-P10 -> -4946.873
A11: 2025 | B11: 10 | C11: 2025-10 | D11: 45931 | E11: Materiais de Construcao | F11: 51586.47 | G11: 18181.38 | H11: =F11-G11 -> 33405.09 | I11: =IF($A11=2025,VLOOKUP($E11,Premissas!$A$52:$P$56,2,0),IF($A11=2026,VLOOKUP($E11,Premissas!$A$52:$P$56,3,0),VLOOKUP($E11,Premissas!$A$52:$P$56,4,0))) -> 0.3 | J11: =H11*(1-I11) -> 23383.563 | K11: =H11-J11 -> 10021.527 | L11: =SUMIFS(Headcount_Folha!$I:$I,Headcount_Folha!$C:$C,$C11,Headcount_Folha!$D:$D,$E11) -> 7392 | M11: =VLOOKUP($E11,Premissas!$A$52:$P$56,10,0)*(1+VLOOKUP($E11,Premissas!$A$52:$P$56,11,0))^($A11-2025) -> 2000 | N11: =H11*VLOOKUP($E11,Premissas!$A$52:$P$56,7,0) -> 501.07635 | O11: =H11*VLOOKUP($E11,Premissas!$A$52:$P$56,8,0) -> 1336.2036 | P11: =H11*VLOOKUP($E11,Premissas!$A$52:$P$56,9,0) -> 668.1018 | Q11: =K11-L11-M11-N11-O11-P11 -> -1875.8547
A12: 2025 | B12: 11 | C12: 2025-11 | D12: 45962 | E12: Materiais de Construcao | F12: 49390.05 | G12: 20494.95 | H12: =F12-G12 -> 28895.1 | I12: =IF($A12=2025,VLOOKUP($E12,Premissas!$A$52:$P$56,2,0),IF($A12=2026,VLOOKUP($E12,Premissas!$A$52:$P$56,3,0),VLOOKUP($E12,Premissas!$A$52:$P$56,4,0))) -> 0.3 | J12: =H12*(1-I12) -> 20226.57 | K12: =H12-J12 -> 8668.53 | L12: =SUMIFS(Headcount_Folha!$I:$I,Headcount_Folha!$C:$C,$C12,Headcount_Folha!$D:$D,$E12) -> 7392 | M12: =VLOOKUP($E12,Premissas!$A$52:$P$56,10,0)*(1+VLOOKUP($E12,Premissas!$A$52:$P$56,11,0))^($A12-2025) -> 2000 | N12: =H12*VLOOKUP($E12,Premissas!$A$52:$P$56,7,0) -> 433.4265 | O12: =H12*VLOOKUP($E12,Premissas!$A$52:$P$56,8,0) -> 1155.804 | P12: =H12*VLOOKUP($E12,Premissas!$A$52:$P$56,9,0) -> 577.902 | Q12: =K12-L12-M12-N12-O12-P12 -> -2890.6025
A13: 2025 | B13: 12 | C13: 2025-12 | D13: 45992 | E13: Materiais de Construcao | F13: 44277.44 | G13: 17195.48 | H13: =F13-G13 -> 27081.96 | I13: =IF($A13=2025,VLOOKUP($E13,Premissas!$A$52:$P$56,2,0),IF($A13=2026,VLOOKUP($E13,Premissas!$A$52:$P$56,3,0),VLOOKUP($E13,Premissas!$A$52:$P$56,4,0))) -> 0.3 | J13: =H13*(1-I13) -> 18957.372 | K13: =H13-J13 -> 8124.588 | L13: =SUMIFS(Headcount_Folha!$I:$I,Headcount_Folha!$C:$C,$C13,Headcount_Folha!$D:$D,$E13) -> 7392 | M13: =VLOOKUP($E13,Premissas!$A$52:$P$56,10,0)*(1+VLOOKUP($E13,Premissas!$A$52:$P$56,11,0))^($A13-2025) -> 2000 | N13: =H13*VLOOKUP($E13,Premissas!$A$52:$P$56,7,0) -> 406.2294 | O13: =H13*VLOOKUP($E13,Premissas!$A$52:$P$56,8,0) -> 1083.2784 | P13: =H13*VLOOKUP($E13,Premissas!$A$52:$P$56,9,0) -> 541.6392 | Q13: =K13-L13-M13-N13-O13-P13 -> -3298.559
... A25: 2026 | B25: 12 | C25: 2026-12 | D25: 46357 | E25: Materiais de Construcao | F25: 56271.68 | G25: 22222.25 | H25: =F25-G25 -> 34049.43 | I25: =IF($A25=2025,VLOOKUP($E25,Premissas!$A$52:$P$56,2,0),IF($A25=2026,VLOOKUP($E25,Premissas!$A$52:$P$56,3,0),VLOOKUP($E25,Premissas!$A$52:$P$56,4,0))) -> 0.3 | J25: =H25*(1-I25) -> 23834.601 | K25: =H25-J25 -> 10214.829 | L25: =SUMIFS(Headcount_Folha!$I:$I,Headcount_Folha!$C:$C,$C25,Headcount_Folha!$D:$D,$E25) -> 7392 | M25: =VLOOKUP($E25,Premissas!$A$52:$P$56,10,0)*(1+VLOOKUP($E25,Premissas!$A$52:$P$56,11,0))^($A25-2025) -> 2090 | N25: =H25*VLOOKUP($E25,Premissas!$A$52:$P$56,7,0) -> 510.74145 | O25: =H25*VLOOKUP($E25,Premissas!$A$52:$P$56,8,0) -> 1361.9772 | P25: =H25*VLOOKUP($E25,Premissas!$A$52:$P$56,9,0) -> 680.9886 | Q25: =K25-L25-M25-N25-O25-P25 -> -1820.8782
A26: 2027 | B26: 1 | C26: 2027-01 | D26: 46388 | E26: Materiais de Construcao | F26: =F14*(1+VLOOKUP($E26,Premissas!$A$52:$P$56,6,0)) -> 36473.62 | G26: =F26*VLOOKUP($E26,Premissas!$A$52:$P$56,5,0) -> 14490.969 | H26: =F26-G26 -> 21982.651 | I26: =IF($A26=2025,VLOOKUP($E26,Premissas!$A$52:$P$56,2,0),IF($A26=2026,VLOOKUP($E26,Premissas!$A$52:$P$56,3,0),VLOOKUP($E26,Premissas!$A$52:$P$56,4,0))) -> 0.3 | J26: =H26*(1-I26) -> 15387.855 | K26: =H26-J26 -> 6594.7952 | L26: =SUMIFS(Headcount_Folha!$I:$I,Headcount_Folha!$C:$C,$C26,Headcount_Folha!$D:$D,$E26) -> 7392 | M26: =VLOOKUP($E26,Premissas!$A$52:$P$56,10,0)*(1+VLOOKUP($E26,Premissas!$A$52:$P$56,11,0))^($A26-2025) -> 2184.05 | N26: =H26*VLOOKUP($E26,Premissas!$A$52:$P$56,7,0) -> 329.73976 | O26: =H26*VLOOKUP($E26,Premissas!$A$52:$P$56,8,0) -> 879.30602 | P26: =H26*VLOOKUP($E26,Premissas!$A$52:$P$56,9,0) -> 439.65301 | Q26: =K26-L26-M26-N26-O26-P26 -> -4629.9536
A27: 2027 | B27: 2 | C27: 2027-02 | D27: 46419 | E27: Materiais de Construcao | F27: =F15*(1+VLOOKUP($E27,Premissas!$A$52:$P$56,6,0)) -> 31269.964 | G27: =F27*VLOOKUP($E27,Premissas!$A$52:$P$56,5,0) -> 12423.557 | H27: =F27-G27 -> 18846.407 | I27: =IF($A27=2025,VLOOKUP($E27,Premissas!$A$52:$P$56,2,0),IF($A27=2026,VLOOKUP($E27,Premissas!$A$52:$P$56,3,0),VLOOKUP($E27,Premissas!$A$52:$P$56,4,0))) -> 0.3 | J27: =H27*(1-I27) -> 13192.485 | K27: =H27-J27 -> 5653.9221 | L27: =SUMIFS(Headcount_Folha!$I:$I,Headcount_Folha!$C:$C,$C27,Headcount_Folha!$D:$D,$E27) -> 7392 | M27: =VLOOKUP($E27,Premissas!$A$52:$P$56,10,0)*(1+VLOOKUP($E27,Premissas!$A$52:$P$56,11,0))^($A27-2025) -> 2184.05 | N27: =H27*VLOOKUP($E27,Premissas!$A$52:$P$56,7,0) -> 282.69611 | O27: =H27*VLOOKUP($E27,Premissas!$A$52:$P$56,8,0) -> 753.85628 | P27: =H27*VLOOKUP($E27,Premissas!$A$52:$P$56,9,0) -> 376.92814 | Q27: =K27-L27-M27-N27-O27-P27 -> -5335.6084
A28: 2027 | B28: 3 | C28: 2027-03 | D28: 46447 | E28: Materiais de Construcao | F28: =F16*(1+VLOOKUP($E28,Premissas!$A$52:$P$56,6,0)) -> 45951.7 | G28: =F28*VLOOKUP($E28,Premissas!$A$52:$P$56,5,0) -> 18256.61 | H28: =F28-G28 -> 27695.089 | I28: =IF($A28=2025,VLOOKUP($E28,Premissas!$A$52:$P$56,2,0),IF($A28=2026,VLOOKUP($E28,Premissas!$A$52:$P$56,3,0),VLOOKUP($E28,Premissas!$A$52:$P$56,4,0))) -> 0.3 | J28: =H28*(1-I28) -> 19386.563 | K28: =H28-J28 -> 8308.5268 | L28: =SUMIFS(Headcount_Folha!$I:$I,Headcount_Folha!$C:$C,$C28,Headcount_Folha!$D:$D,$E28) -> 7392 | M28: =VLOOKUP($E28,Premissas!$A$52:$P$56,10,0)*(1+VLOOKUP($E28,Premissas!$A$52:$P$56,11,0))^($A28-2025) -> 2184.05 | N28: =H28*VLOOKUP($E28,Premissas!$A$52:$P$56,7,0) -> 415.42634 | O28: =H28*VLOOKUP($E28,Premissas!$A$52:$P$56,8,0) -> 1107.8036 | P28: =H28*VLOOKUP($E28,Premissas!$A$52:$P$56,9,0) -> 553.90179 | Q28: =K28-L28-M28-N28-O28-P28 -> -3344.6549
A29: 2027 | B29: 4 | C29: 2027-04 | D29: 46478 | E29: Materiais de Construcao | F29: =F17*(1+VLOOKUP($E29,Premissas!$A$52:$P$56,6,0)) -> 35514.968 | G29: =F29*VLOOKUP($E29,Premissas!$A$52:$P$56,5,0) -> 14110.097 | H29: =F29-G29 -> 21404.871 | I29: =IF($A29=2025,VLOOKUP($E29,Premissas!$A$52:$P$56,2,0),IF($A29=2026,VLOOKUP($E29,Premissas!$A$52:$P$56,3,0),VLOOKUP($E29,Premissas!$A$52:$P$56,4,0))) -> 0.3 | J29: =H29*(1-I29) -> 14983.41 | K29: =H29-J29 -> 6421.4614 | L29: =SUMIFS(Headcount_Folha!$I:$I,Headcount_Folha!$C:$C,$C29,Headcount_Folha!$D:$D,$E29) -> 7392 | M29: =VLOOKUP($E29,Premissas!$A$52:$P$56,10,0)*(1+VLOOKUP($E29,Premissas!$A$52:$P$56,11,0))^($A29-2025) -> 2184.05 | N29: =H29*VLOOKUP($E29,Premissas!$A$52:$P$56,7,0) -> 321.07307 | O29: =H29*VLOOKUP($E29,Premissas!$A$52:$P$56,8,0) -> 856.19486 | P29: =H29*VLOOKUP($E29,Premissas!$A$52:$P$56,9,0) -> 428.09743 | Q29: =K29-L29-M29-N29-O29-P29 -> -4759.9539
A30: 2027 | B30: 5 | C30: 2027-05 | D30: 46508 | E30: Materiais de Construcao | F30: =F18*(1+VLOOKUP($E30,Premissas!$A$52:$P$56,6,0)) -> 45854.381 | G30: =F30*VLOOKUP($E30,Premissas!$A$52:$P$56,5,0) -> 18217.945 | H30: =F30-G30 -> 27636.435 | I30: =IF($A30=2025,VLOOKUP($E30,Premissas!$A$52:$P$56,2,0),IF($A30=2026,VLOOKUP($E30,Premissas!$A$52:$P$56,3,0),VLOOKUP($E30,Premissas!$A$52:$P$56,4,0))) -> 0.3 | J30: =H30*(1-I30) -> 19345.505 | K30: =H30-J30 -> 8290.9306 | L30: =SUMIFS(Headcount_Folha!$I:$I,Headcount_Folha!$C:$C,$C30,Headcount_Folha!$D:$D,$E30) -> 7392 | M30: =VLOOKUP($E30,Premissas!$A$52:$P$56,10,0)*(1+VLOOKUP($E30,Premissas!$A$52:$P$56,11,0))^($A30-2025) -> 2184.05 | N30: =H30*VLOOKUP($E30,Premissas!$A$52:$P$56,7,0) -> 414.54653 | O30: =H30*VLOOKUP($E30,Premissas!$A$52:$P$56,8,0) -> 1105.4574 | P30: =H30*VLOOKUP($E30,Premissas!$A$52:$P$56,9,0) -> 552.72871 | Q30: =K30-L30-M30-N30-O30-P30 -> -3357.8521
A31: 2027 | B31: 6 | C31: 2027-06 | D31: 46539 | E31: Materiais de Construcao | F31: =F19*(1+VLOOKUP($E31,Premissas!$A$52:$P$56,6,0)) -> 39154.504 | G31: =F31*VLOOKUP($E31,Premissas!$A$52:$P$56,5,0) -> 15556.084 | H31: =F31-G31 -> 23598.419 | I31: =IF($A31=2025,VLOOKUP($E31,Premissas!$A$52:$P$56,2,0),IF($A31=2026,VLOOKUP($E31,Premissas!$A$52:$P$56,3,0),VLOOKUP($E31,Premissas!$A$52:$P$56,4,0))) -> 0.3 | J31: =H31*(1-I31) -> 16518.894 | K31: =H31-J31 -> 7079.5258 | L31: =SUMIFS(Headcount_Folha!$I:$I,Headcount_Folha!$C:$C,$C31,Headcount_Folha!$D:$D,$E31) -> 7392 | M31: =VLOOKUP($E31,Premissas!$A$52:$P$56,10,0)*(1+VLOOKUP($E31,Premissas!$A$52:$P$56,11,0))^($A31-2025) -> 2184.05 | N31: =H31*VLOOKUP($E31,Premissas!$A$52:$P$56,7,0) -> 353.97629 | O31: =H31*VLOOKUP($E31,Premissas!$A$52:$P$56,8,0) -> 943.93677 | P31: =H31*VLOOKUP($E31,Premissas!$A$52:$P$56,9,0) -> 471.96839 | Q31: =K31-L31-M31-N31-O31-P31 -> -4266.4057
A32: 2027 | B32: 7 | C32: 2027-07 | D32: 46569 | E32: Materiais de Construcao | F32: =F20*(1+VLOOKUP($E32,Premissas!$A$52:$P$56,6,0)) -> 56147.472 | G32: =F32*VLOOKUP($E32,Premissas!$A$52:$P$56,5,0) -> 22307.391 | H32: =F32-G32 -> 33840.081 | I32: =IF($A32=2025,VLOOKUP($E32,Premissas!$A$52:$P$56,2,0),IF($A32=2026,VLOOKUP($E32,Premissas!$A$52:$P$56,3,0),VLOOKUP($E32,Premissas!$A$52:$P$56,4,0))) -> 0.3 | J32: =H32*(1-I32) -> 23688.057 | K32: =H32-J32 -> 10152.024 | L32: =SUMIFS(Headcount_Folha!$I:$I,Headcount_Folha!$C:$C,$C32,Headcount_Folha!$D:$D,$E32) -> 7392 | M32: =VLOOKUP($E32,Premissas!$A$52:$P$56,10,0)*(1+VLOOKUP($E32,Premissas!$A$52:$P$56,11,0))^($A32-2025) -> 2184.05 | N32: =H32*VLOOKUP($E32,Premissas!$A$52:$P$56,7,0) -> 507.60122 | O32: =H32*VLOOKUP($E32,Premissas!$A$52:$P$56,8,0) -> 1353.6033 | P32: =H32*VLOOKUP($E32,Premissas!$A$52:$P$56,9,0) -> 676.80163 | Q32: =K32-L32-M32-N32-O32-P32 -> -1962.0317
A33: 2027 | B33: 8 | C33: 2027-08 | D33: 46600 | E33: Materiais de Construcao | F33: =F21*(1+VLOOKUP($E33,Premissas!$A$52:$P$56,6,0)) -> 49977.713 | G33: =F33*VLOOKUP($E33,Premissas!$A$52:$P$56,5,0) -> 19856.145 | H33: =F33-G33 -> 30121.568 | I33: =IF($A33=2025,VLOOKUP($E33,Premissas!$A$52:$P$56,2,0),IF($A33=2026,VLOOKUP($E33,Premissas!$A$52:$P$56,3,0),VLOOKUP($E33,Premissas!$A$52:$P$56,4,0))) -> 0.3 | J33: =H33*(1-I33) -> 21085.097 | K33: =H33-J33 -> 9036.4703 | L33: =SUMIFS(Headcount_Folha!$I:$I,Headcount_Folha!$C:$C,$C33,Headcount_Folha!$D:$D,$E33) -> 7392 | M33: =VLOOKUP($E33,Premissas!$A$52:$P$56,10,0)*(1+VLOOKUP($E33,Premissas!$A$52:$P$56,11,0))^($A33-2025) -> 2184.05 | N33: =H33*VLOOKUP($E33,Premissas!$A$52:$P$56,7,0) -> 451.82351 | O33: =H33*VLOOKUP($E33,Premissas!$A$52:$P$56,8,0) -> 1204.8627 | P33: =H33*VLOOKUP($E33,Premissas!$A$52:$P$56,9,0) -> 602.43135 | Q33: =K33-L33-M33-N33-O33-P33 -> -2798.6973
A34: 2027 | B34: 9 | C34: 2027-09 | D34: 46631 | E34: Materiais de Construcao | F34: =F22*(1+VLOOKUP($E34,Premissas!$A$52:$P$56,6,0)) -> 50261.839 | G34: =F34*VLOOKUP($E34,Premissas!$A$52:$P$56,5,0) -> 19969.029 | H34: =F34-G34 -> 30292.81 | I34: =IF($A34=2025,VLOOKUP($E34,Premissas!$A$52:$P$56,2,0),IF($A34=2026,VLOOKUP($E34,Premissas!$A$52:$P$56,3,0),VLOOKUP($E34,Premissas!$A$52:$P$56,4,0))) -> 0.3 | J34: =H34*(1-I34) -> 21204.967 | K34: =H34-J34 -> 9087.8431 | L34: =SUMIFS(Headcount_Folha!$I:$I,Headcount_Folha!$C:$C,$C34,Headcount_Folha!$D:$D,$E34) -> 7392 | M34: =VLOOKUP($E34,Premissas!$A$52:$P$56,10,0)*(1+VLOOKUP($E34,Premissas!$A$52:$P$56,11,0))^($A34-2025) -> 2184.05 | N34: =H34*VLOOKUP($E34,Premissas!$A$52:$P$56,7,0) -> 454.39216 | O34: =H34*VLOOKUP($E34,Premissas!$A$52:$P$56,8,0) -> 1211.7124 | P34: =H34*VLOOKUP($E34,Premissas!$A$52:$P$56,9,0) -> 605.85621 | Q34: =K34-L34-M34-N34-O34-P34 -> -2760.1676
A35: 2027 | B35: 10 | C35: 2027-10 | D35: 46661 | E35: Materiais de Construcao | F35: =F23*(1+VLOOKUP($E35,Premissas!$A$52:$P$56,6,0)) -> 51504.822 | G35: =F35*VLOOKUP($E35,Premissas!$A$52:$P$56,5,0) -> 20462.866 | H35: =F35-G35 -> 31041.956 | I35: =IF($A35=2025,VLOOKUP($E35,Premissas!$A$52:$P$56,2,0),IF($A35=2026,VLOOKUP($E35,Premissas!$A$52:$P$56,3,0),VLOOKUP($E35,Premissas!$A$52:$P$56,4,0))) -> 0.3 | J35: =H35*(1-I35) -> 21729.369 | K35: =H35-J35 -> 9312.5869 | L35: =SUMIFS(Headcount_Folha!$I:$I,Headcount_Folha!$C:$C,$C35,Headcount_Folha!$D:$D,$E35) -> 7392 | M35: =VLOOKUP($E35,Premissas!$A$52:$P$56,10,0)*(1+VLOOKUP($E35,Premissas!$A$52:$P$56,11,0))^($A35-2025) -> 2184.05 | N35: =H35*VLOOKUP($E35,Premissas!$A$52:$P$56,7,0) -> 465.62934 | O35: =H35*VLOOKUP($E35,Premissas!$A$52:$P$56,8,0) -> 1241.6782 | P35: =H35*VLOOKUP($E35,Premissas!$A$52:$P$56,9,0) -> 620.83912 | Q35: =K35-L35-M35-N35-O35-P35 -> -2591.6099
A36: 2027 | B36: 11 | C36: 2027-11 | D36: 46692 | E36: Materiais de Construcao | F36: =F24*(1+VLOOKUP($E36,Premissas!$A$52:$P$56,6,0)) -> 59766.984 | G36: =F36*VLOOKUP($E36,Premissas!$A$52:$P$56,5,0) -> 23745.423 | H36: =F36-G36 -> 36021.561 | I36: =IF($A36=2025,VLOOKUP($E36,Premissas!$A$52:$P$56,2,0),IF($A36=2026,VLOOKUP($E36,Premissas!$A$52:$P$56,3,0),VLOOKUP($E36,Premissas!$A$52:$P$56,4,0))) -> 0.3 | J36: =H36*(1-I36) -> 25215.093 | K36: =H36-J36 -> 10806.468 | L36: =SUMIFS(Headcount_Folha!$I:$I,Headcount_Folha!$C:$C,$C36,Headcount_Folha!$D:$D,$E36) -> 7392 | M36: =VLOOKUP($E36,Premissas!$A$52:$P$56,10,0)*(1+VLOOKUP($E36,Premissas!$A$52:$P$56,11,0))^($A36-2025) -> 2184.05 | N36: =H36*VLOOKUP($E36,Premissas!$A$52:$P$56,7,0) -> 540.32342 | O36: =H36*VLOOKUP($E36,Premissas!$A$52:$P$56,8,0) -> 1440.8625 | P36: =H36*VLOOKUP($E36,Premissas!$A$52:$P$56,9,0) -> 720.43123 | Q36: =K36-L36-M36-N36-O36-P36 -> -1471.1987
A37: 2027 | B37: 12 | C37: 2027-12 | D37: 46722 | E37: Materiais de Construcao | F37: =F25*(1+VLOOKUP($E37,Premissas!$A$52:$P$56,6,0)) -> 60773.414 | G37: =F37*VLOOKUP($E37,Premissas!$A$52:$P$56,5,0) -> 24145.278 | H37: =F37-G37 -> 36628.137 | I37: =IF($A37=2025,VLOOKUP($E37,Premissas!$A$52:$P$56,2,0),IF($A37=2026,VLOOKUP($E37,Premissas!$A$52:$P$56,3,0),VLOOKUP($E37,Premissas!$A$52:$P$56,4,0))) -> 0.3 | J37: =H37*(1-I37) -> 25639.696 | K37: =H37-J37 -> 10988.441 | L37: =SUMIFS(Headcount_Folha!$I:$I,Headcount_Folha!$C:$C,$C37,Headcount_Folha!$D:$D,$E37) -> 7392 | M37: =VLOOKUP($E37,Premissas!$A$52:$P$56,10,0)*(1+VLOOKUP($E37,Premissas!$A$52:$P$56,11,0))^($A37-2025) -> 2184.05 | N37: =H37*VLOOKUP($E37,Premissas!$A$52:$P$56,7,0) -> 549.42205 | O37: =H37*VLOOKUP($E37,Premissas!$A$52:$P$56,8,0) -> 1465.1255 | P37: =H37*VLOOKUP($E37,Premissas!$A$52:$P$56,9,0) -> 732.56274 | Q37: =K37-L37-M37-N37-O37-P37 -> -1334.7192
A38: 2025 | B38: 1 | C38: 2025-01 | D38: 45658 | E38: Utilidades Domesticas | F38: 62404.31 | G38: 21248.71 | H38: =F38-G38 -> 41155.6 | I38: =IF($A38=2025,VLOOKUP($E38,Premissas!$A$52:$P$56,2,0),IF($A38=2026,VLOOKUP($E38,Premissas!$A$52:$P$56,3,0),VLOOKUP($E38,Premissas!$A$52:$P$56,4,0))) -> 0.38 | J38: =H38*(1-I38) -> 25516.472 | K38: =H38-J38 -> 15639.128 | L38: =SUMIFS(Headcount_Folha!$I:$I,Headcount_Folha!$C:$C,$C38,Headcount_Folha!$D:$D,$E38) -> 9576 | M38: =VLOOKUP($E38,Premissas!$A$52:$P$56,10,0)*(1+VLOOKUP($E38,Premissas!$A$52:$P$56,11,0))^($A38-2025) -> 3000 | N38: =H38*VLOOKUP($E38,Premissas!$A$52:$P$56,7,0) -> 823.112 | O38: =H38*VLOOKUP($E38,Premissas!$A$52:$P$56,8,0) -> 1440.446 | P38: =H38*VLOOKUP($E38,Premissas!$A$52:$P$56,9,0) -> 823.112 | Q38: =K38-L38-M38-N38-O38-P38 -> -23.542
A39: 2025 | B39: 2 | C39: 2025-02 | D39: 45689 | E39: Utilidades Domesticas | F39: 61977.91 | G39: 20793.47 | H39: =F39-G39 -> 41184.44 | I39: =IF($A39=2025,VLOOKUP($E39,Premissas!$A$52:$P$56,2,0),IF($A39=2026,VLOOKUP($E39,Premissas!$A$52:$P$56,3,0),VLOOKUP($E39,Premissas!$A$52:$P$56,4,0))) -> 0.38 | J39: =H39*(1-I39) -> 25534.353 | K39: =H39-J39 -> 15650.087 | L39: =SUMIFS(Headcount_Folha!$I:$I,Headcount_Folha!$C:$C,$C39,Headcount_Folha!$D:$D,$E39) -> 9576 | M39: =VLOOKUP($E39,Premissas!$A$52:$P$56,10,0)*(1+VLOOKUP($E39,Premissas!$A$52:$P$56,11,0))^($A39-2025) -> 3000 | N39: =H39*VLOOKUP($E39,Premissas!$A$52:$P$56,7,0) -> 823.6888 | O39: =H39*VLOOKUP($E39,Premissas!$A$52:$P$56,8,0) -> 1441.4554 | P39: =H39*VLOOKUP($E39,Premissas!$A$52:$P$56,9,0) -> 823.6888 | Q39: =K39-L39-M39-N39-O39-P39 -> -14.7458
A40: 2025 | B40: 3 | C40: 2025-03 | D40: 45717 | E40: Utilidades Domesticas | F40: 62232.13 | G40: 21382.98 | H40: =F40-G40 -> 40849.15 | I40: =IF($A40=2025,VLOOKUP($E40,Premissas!$A$52:$P$56,2,0),IF($A40=2026,VLOOKUP($E40,Premissas!$A$52:$P$56,3,0),VLOOKUP($E40,Premissas!$A$52:$P$56,4,0))) -> 0.38 | J40: =H40*(1-I40) -> 25326.473 | K40: =H40-J40 -> 15522.677 | L40: =SUMIFS(Headcount_Folha!$I:$I,Headcount_Folha!$C:$C,$C40,Headcount_Folha!$D:$D,$E40) -> 9576 | M40: =VLOOKUP($E40,Premissas!$A$52:$P$56,10,0)*(1+VLOOKUP($E40,Premissas!$A$52:$P$56,11,0))^($A40-2025) -> 3000 | N40: =H40*VLOOKUP($E40,Premissas!$A$52:$P$56,7,0) -> 816.983 | O40: =H40*VLOOKUP($E40,Premissas!$A$52:$P$56,8,0) -> 1429.7203 | P40: =H40*VLOOKUP($E40,Premissas!$A$52:$P$56,9,0) -> 816.983 | Q40: =K40-L40-M40-N40-O40-P40 -> -117.00925
A41: 2025 | B41: 4 | C41: 2025-04 | D41: 45748 | E41: Utilidades Domesticas | F41: 73019.38 | G41: 25018.97 | H41: =F41-G41 -> 48000.41 | I41: =IF($A41=2025,VLOOKUP($E41,Premissas!$A$52:$P$56,2,0),IF($A41=2026,VLOOKUP($E41,Premissas!$A$52:$P$56,3,0),VLOOKUP($E41,Premissas!$A$52:$P$56,4,0))) -> 0.38 | J41: =H41*(1-I41) -> 29760.254 | K41: =H41-J41 -> 18240.156 | L41: =SUMIFS(Headcount_Folha!$I:$I,Headcount_Folha!$C:$C,$C41,Headcount_Folha!$D:$D,$E41) -> 9576 | M41: =VLOOKUP($E41,Premissas!$A$52:$P$56,10,0)*(1+VLOOKUP($E41,Premissas!$A$52:$P$56,11,0))^($A41-2025) -> 3000 | N41: =H41*VLOOKUP($E41,Premissas!$A$52:$P$56,7,0) -> 960.0082 | O41: =H41*VLOOKUP($E41,Premissas!$A$52:$P$56,8,0) -> 1680.0143 | P41: =H41*VLOOKUP($E41,Premissas!$A$52:$P$56,9,0) -> 960.0082 | Q41: =K41-L41-M41-N41-O41-P41 -> 2064.1251
A42: 2025 | B42: 5 | C42: 2025-05 | D42: 45778 | E42: Utilidades Domesticas | F42: 68209.77 | G42: 23301.21 | H42: =F42-G42 -> 44908.56 | I42: =IF($A42=2025,VLOOKUP($E42,Premissas!$A$52:$P$56,2,0),IF($A42=2026,VLOOKUP($E42,Premissas!$A$52:$P$56,3,0),VLOOKUP($E42,Premissas!$A$52:$P$56,4,0))) -> 0.38 | J42: =H42*(1-I42) -> 27843.307 | K42: =H42-J42 -> 17065.253 | L42: =SUMIFS(Headcount_Folha!$I:$I,Headcount_Folha!$C:$C,$C42,Headcount_Folha!$D:$D,$E42) -> 9576 | M42: =VLOOKUP($E42,Premissas!$A$52:$P$56,10,0)*(1+VLOOKUP($E42,Premissas!$A$52:$P$56,11,0))^($A42-2025) -> 3000 | N42: =H42*VLOOKUP($E42,Premissas!$A$52:$P$56,7,0) -> 898.1712 | O42: =H42*VLOOKUP($E42,Premissas!$A$52:$P$56,8,0) -> 1571.7996 | P42: =H42*VLOOKUP($E42,Premissas!$A$52:$P$56,9,0) -> 898.1712 | Q42: =K42-L42-M42-N42-O42-P42 -> 1121.1108
A43: 2025 | B43: 6 | C43: 2025-06 | D43: 45809 | E43: Utilidades Domesticas | F43: 93443.01 | G43: 31006.59 | H43: =F43-G43 -> 62436.42 | I43: =IF($A43=2025,VLOOKUP($E43,Premissas!$A$52:$P$56,2,0),IF($A43=2026,VLOOKUP($E43,Premissas!$A$52:$P$56,3,0),VLOOKUP($E43,Premissas!$A$52:$P$56,4,0))) -> 0.38 | J43: =H43*(1-I43) -> 38710.58 | K43: =H43-J43 -> 23725.84 | L43: =SUMIFS(Headcount_Folha!$I:$I,Headcount_Folha!$C:$C,$C43,Headcount_Folha!$D:$D,$E43) -> 9576 | M43: =VLOOKUP($E43,Premissas!$A$52:$P$56,10,0)*(1+VLOOKUP($E43,Premissas!$A$52:$P$56,11,0))^($A43-2025) -> 3000 | N43: =H43*VLOOKUP($E43,Premissas!$A$52:$P$56,7,0) -> 1248.7284 | O43: =H43*VLOOKUP($E43,Premissas!$A$52:$P$56,8,0) -> 2185.2747 | P43: =H43*VLOOKUP($E43,Premissas!$A$52:$P$56,9,0) -> 1248.7284 | Q43: =K43-L43-M43-N43-O43-P43 -> 6467.1081
A44: 2025 | B44: 7 | C44: 2025-07 | D44: 45839 | E44: Utilidades Domesticas | F44: 86683.24 | G44: 30059.43 | H44: =F44-G44 -> 56623.81 | I44: =IF($A44=2025,VLOOKUP($E44,Premissas!$A$52:$P$56,2,0),IF($A44=2026,VLOOKUP($E44,Premissas!$A$52:$P$56,3,0),VLOOKUP($E44,Premissas!$A$52:$P$56,4,0))) -> 0.38 | J44: =H44*(1-I44) -> 35106.762 | K44: =H44-J44 -> 21517.048 | L44: =SUMIFS(Headcount_Folha!$I:$I,Headcount_Folha!$C:$C,$C44,Headcount_Folha!$D:$D,$E44) -> 9576 | M44: =VLOOKUP($E44,Premissas!$A$52:$P$56,10,0)*(1+VLOOKUP($E44,Premissas!$A$52:$P$56,11,0))^($A44-2025) -> 3000 | N44: =H44*VLOOKUP($E44,Premissas!$A$52:$P$56,7,0) -> 1132.4762 | O44: =H44*VLOOKUP($E44,Premissas!$A$52:$P$56,8,0) -> 1981.8334 | P44: =H44*VLOOKUP($E44,Premissas!$A$52:$P$56,9,0) -> 1132.4762 | Q44: =K44-L44-M44-N44-O44-P44 -> 4694.2621
A45: 2025 | B45: 8 | C45: 2025-08 | D45: 45870 | E45: Utilidades Domesticas | F45: 74561.38 | G45: 25193.01 | H45: =F45-G45 -> 49368.37 | I45: =IF($A45=2025,VLOOKUP($E45,Premissas!$A$52:$P$56,2,0),IF($A45=2026,VLOOKUP($E45,Premissas!$A$52:$P$56,3,0),VLOOKUP($E45,Premissas!$A$52:$P$56,4,0))) -> 0.38 | J45: =H45*(1-I45) -> 30608.389 | K45: =H45-J45 -> 18759.981 | L45: =SUMIFS(Headcount_Folha!$I:$I,Headcount_Folha!$C:$C,$C45,Headcount_Folha!$D:$D,$E45) -> 9576 | M45: =VLOOKUP($E45,Premissas!$A$52:$P$56,10,0)*(1+VLOOKUP($E45,Premissas!$A$52:$P$56,11,0))^($A45-2025) -> 3000 | N45: =H45*VLOOKUP($E45,Premissas!$A$52:$P$56,7,0) -> 987.3674 | O45: =H45*VLOOKUP($E45,Premissas!$A$52:$P$56,8,0) -> 1727.8929 | P45: =H45*VLOOKUP($E45,Premissas!$A$52:$P$56,9,0) -> 987.3674 | Q45: =K45-L45-M45-N45-O45-P45 -> 2481.3529
A46: 2025 | B46: 9 | C46: 2025-09 | D46: 45901 | E46: Utilidades Domesticas | F46: 68739.54 | G46: 23174.78 | H46: =F46-G46 -> 45564.76 | I46: =IF($A46=2025,VLOOKUP($E46,Premissas!$A$52:$P$56,2,0),IF($A46=2026,VLOOKUP($E46,Premissas!$A$52:$P$56,3,0),VLOOKUP($E46,Premissas!$A$52:$P$56,4,0))) -> 0.38 | J46: =H46*(1-I46) -> 28250.151 | K46: =H46-J46 -> 17314.609 | L46: =SUMIFS(Headcount_Folha!$I:$I,Headcount_Folha!$C:$C,$C46,Headcount_Folha!$D:$D,$E46) -> 9576 | M46: =VLOOKUP($E46,Premissas!$A$52:$P$56,10,0)*(1+VLOOKUP($E46,Premissas!$A$52:$P$56,11,0))^($A46-2025) -> 3000 | N46: =H46*VLOOKUP($E46,Premissas!$A$52:$P$56,7,0) -> 911.2952 | O46: =H46*VLOOKUP($E46,Premissas!$A$52:$P$56,8,0) -> 1594.7666 | P46: =H46*VLOOKUP($E46,Premissas!$A$52:$P$56,9,0) -> 911.2952 | Q46: =K46-L46-M46-N46-O46-P46 -> 1321.2518
A47: 2025 | B47: 10 | C47: 2025-10 | D47: 45931 | E47: Utilidades Domesticas | F47: 70042.77 | G47: 23235.35 | H47: =F47-G47 -> 46807.42 | I47: =IF($A47=2025,VLOOKUP($E47,Premissas!$A$52:$P$56,2,0),IF($A47=2026,VLOOKUP($E47,Premissas!$A$52:$P$56,3,0),VLOOKUP($E47,Premissas!$A$52:$P$56,4,0))) -> 0.38 | J47: =H47*(1-I47) -> 29020.6 | K47: =H47-J47 -> 17786.82 | L47: =SUMIFS(Headcount_Folha!$I:$I,Headcount_Folha!$C:$C,$C47,Headcount_Folha!$D:$D,$E47) -> 9576 | M47: =VLOOKUP($E47,Premissas!$A$52:$P$56,10,0)*(1+VLOOKUP($E47,Premissas!$A$52:$P$56,11,0))^($A47-2025) -> 3000 | N47: =H47*VLOOKUP($E47,Premissas!$A$52:$P$56,7,0) -> 936.1484 | O47: =H47*VLOOKUP($E47,Premissas!$A$52:$P$56,8,0) -> 1638.2597 | P47: =H47*VLOOKUP($E47,Premissas!$A$52:$P$56,9,0) -> 936.1484 | Q47: =K47-L47-M47-N47-O47-P47 -> 1700.2631
A48: 2025 | B48: 11 | C48: 2025-11 | D48: 45962 | E48: Utilidades Domesticas | F48: 90370.52 | G48: 31205.56 | H48: =F48-G48 -> 59164.96 | I48: =IF($A48=2025,VLOOKUP($E48,Premissas!$A$52:$P$56,2,0),IF($A48=2026,VLOOKUP($E48,Premissas!$A$52:$P$56,3,0),VLOOKUP($E48,Premissas!$A$52:$P$56,4,0))) -> 0.38 | J48: =H48*(1-I48) -> 36682.275 | K48: =H48-J48 -> 22482.685 | L48: =SUMIFS(Headcount_Folha!$I:$I,Headcount_Folha!$C:$C,$C48,Headcount_Folha!$D:$D,$E48) -> 9576 | M48: =VLOOKUP($E48,Premissas!$A$52:$P$56,10,0)*(1+VLOOKUP($E48,Premissas!$A$52:$P$56,11,0))^($A48-2025) -> 3000 | N48: =H48*VLOOKUP($E48,Premissas!$A$52:$P$56,7,0) -> 1183.2992 | O48: =H48*VLOOKUP($E48,Premissas!$A$52:$P$56,8,0) -> 2070.7736 | P48: =H48*VLOOKUP($E48,Premissas!$A$52:$P$56,9,0) -> 1183.2992 | Q48: =K48-L48-M48-N48-O48-P48 -> 5469.3128
A49: 2025 | B49: 12 | C49: 2025-12 | D49: 45992 | E49: Utilidades Domesticas | F49: 100662.29 | G49: 34439.23 | H49: =F49-G49 -> 66223.06 | I49: =IF($A49=2025,VLOOKUP($E49,Premissas!$A$52:$P$56,2,0),IF($A49=2026,VLOOKUP($E49,Premissas!$A$52:$P$56,3,0),VLOOKUP($E49,Premissas!$A$52:$P$56,4,0))) -> 0.38 | J49: =H49*(1-I49) -> 41058.297 | K49: =H49-J49 -> 25164.763 | L49: =SUMIFS(Headcount_Folha!$I:$I,Headcount_Folha!$C:$C,$C49,Headcount_Folha!$D:$D,$E49) -> 9576 | M49: =VLOOKUP($E49,Premissas!$A$52:$P$56,10,0)*(1+VLOOKUP($E49,Premissas!$A$52:$P$56,11,0))^($A49-2025) -> 3000 | N49: =H49*VLOOKUP($E49,Premissas!$A$52:$P$56,7,0) -> 1324.4612 | O49: =H49*VLOOKUP($E49,Premissas!$A$52:$P$56,8,0) -> 2317.8071 | P49: =H49*VLOOKUP($E49,Premissas!$A$52:$P$56,9,0) -> 1324.4612 | Q49: =K49-L49-M49-N49-O49-P49 -> 7622.0333
... A61: 2026 | B61: 12 | C61: 2026-12 | D61: 46357 | E61: Utilidades Domesticas | F61: 104153.83 | G61: 35215.17 | H61: =F61-G61 -> 68938.66 | I61: =IF($A61=2025,VLOOKUP($E61,Premissas!$A$52:$P$56,2,0),IF($A61=2026,VLOOKUP($E61,Premissas!$A$52:$P$56,3,0),VLOOKUP($E61,Premissas!$A$52:$P$56,4,0))) -> 0.34 | J61: =H61*(1-I61) -> 45499.516 | K61: =H61-J61 -> 23439.144 | L61: =SUMIFS(Headcount_Folha!$I:$I,Headcount_Folha!$C:$C,$C61,Headcount_Folha!$D:$D,$E61) -> 9576 | M61: =VLOOKUP($E61,Premissas!$A$52:$P$56,10,0)*(1+VLOOKUP($E61,Premissas!$A$52:$P$56,11,0))^($A61-2025) -> 3135 | N61: =H61*VLOOKUP($E61,Premissas!$A$52:$P$56,7,0) -> 1378.7732 | O61: =H61*VLOOKUP($E61,Premissas!$A$52:$P$56,8,0) -> 2412.8531 | P61: =H61*VLOOKUP($E61,Premissas!$A$52:$P$56,9,0) -> 1378.7732 | Q61: =K61-L61-M61-N61-O61-P61 -> 5557.7449
A62: 2027 | B62: 1 | C62: 2027-01 | D62: 46388 | E62: Utilidades Domesticas | F62: =F50*(1+VLOOKUP($E62,Premissas!$A$52:$P$56,6,0)) -> 65858.058 | G62: =F62*VLOOKUP($E62,Premissas!$A$52:$P$56,5,0) -> 22661.758 | H62: =F62-G62 -> 43196.3 | I62: =IF($A62=2025,VLOOKUP($E62,Premissas!$A$52:$P$56,2,0),IF($A62=2026,VLOOKUP($E62,Premissas!$A$52:$P$56,3,0),VLOOKUP($E62,Premissas!$A$52:$P$56,4,0))) -> 0.32 | J62: =H62*(1-I62) -> 29373.484 | K62: =H62-J62 -> 13822.816 | L62: =SUMIFS(Headcount_Folha!$I:$I,Headcount_Folha!$C:$C,$C62,Headcount_Folha!$D:$D,$E62) -> 12768 | M62: =VLOOKUP($E62,Premissas!$A$52:$P$56,10,0)*(1+VLOOKUP($E62,Premissas!$A$52:$P$56,11,0))^($A62-2025) -> 3276.075 | N62: =H62*VLOOKUP($E62,Premissas!$A$52:$P$56,7,0) -> 863.926 | O62: =H62*VLOOKUP($E62,Premissas!$A$52:$P$56,8,0) -> 1511.8705 | P62: =H62*VLOOKUP($E62,Premissas!$A$52:$P$56,9,0) -> 863.926 | Q62: =K62-L62-M62-N62-O62-P62 -> -5460.9814
A63: 2027 | B63: 2 | C63: 2027-02 | D63: 46419 | E63: Utilidades Domesticas | F63: =F51*(1+VLOOKUP($E63,Premissas!$A$52:$P$56,6,0)) -> 51276.844 | G63: =F63*VLOOKUP($E63,Premissas!$A$52:$P$56,5,0) -> 17644.362 | H63: =F63-G63 -> 33632.482 | I63: =IF($A63=2025,VLOOKUP($E63,Premissas!$A$52:$P$56,2,0),IF($A63=2026,VLOOKUP($E63,Premissas!$A$52:$P$56,3,0),VLOOKUP($E63,Premissas!$A$52:$P$56,4,0))) -> 0.32 | J63: =H63*(1-I63) -> 22870.088 | K63: =H63-J63 -> 10762.394 | L63: =SUMIFS(Headcount_Folha!$I:$I,Headcount_Folha!$C:$C,$C63,Headcount_Folha!$D:$D,$E63) -> 12768 | M63: =VLOOKUP($E63,Premissas!$A$52:$P$56,10,0)*(1+VLOOKUP($E63,Premissas!$A$52:$P$56,11,0))^($A63-2025) -> 3276.075 | N63: =H63*VLOOKUP($E63,Premissas!$A$52:$P$56,7,0) -> 672.64965 | O63: =H63*VLOOKUP($E63,Premissas!$A$52:$P$56,8,0) -> 1177.1369 | P63: =H63*VLOOKUP($E63,Premissas!$A$52:$P$56,9,0) -> 672.64965 | Q63: =K63-L63-M63-N63-O63-P63 -> -7804.1168
A64: 2027 | B64: 3 | C64: 2027-03 | D64: 46447 | E64: Utilidades Domesticas | F64: =F52*(1+VLOOKUP($E64,Premissas!$A$52:$P$56,6,0)) -> 85718.178 | G64: =F64*VLOOKUP($E64,Premissas!$A$52:$P$56,5,0) -> 29495.625 | H64: =F64-G64 -> 56222.553 | I64: =IF($A64=2025,VLOOKUP($E64,Premissas!$A$52:$P$56,2,0),IF($A64=2026,VLOOKUP($E64,Premissas!$A$52:$P$56,3,0),VLOOKUP($E64,Premissas!$A$52:$P$56,4,0))) -> 0.32 | J64: =H64*(1-I64) -> 38231.336 | K64: =H64-J64 -> 17991.217 | L64: =SUMIFS(Headcount_Folha!$I:$I,Headcount_Folha!$C:$C,$C64,Headcount_Folha!$D:$D,$E64) -> 12768 | M64: =VLOOKUP($E64,Premissas!$A$52:$P$56,10,0)*(1+VLOOKUP($E64,Premissas!$A$52:$P$56,11,0))^($A64-2025) -> 3276.075 | N64: =H64*VLOOKUP($E64,Premissas!$A$52:$P$56,7,0) -> 1124.4511 | O64: =H64*VLOOKUP($E64,Premissas!$A$52:$P$56,8,0) -> 1967.7894 | P64: =H64*VLOOKUP($E64,Premissas!$A$52:$P$56,9,0) -> 1124.4511 | Q64: =K64-L64-M64-N64-O64-P64 -> -2269.5495
A65: 2027 | B65: 4 | C65: 2027-04 | D65: 46478 | E65: Utilidades Domesticas | F65: =F53*(1+VLOOKUP($E65,Premissas!$A$52:$P$56,6,0)) -> 56689.542 | G65: =F65*VLOOKUP($E65,Premissas!$A$52:$P$56,5,0) -> 19506.871 | H65: =F65-G65 -> 37182.671 | I65: =IF($A65=2025,VLOOKUP($E65,Premissas!$A$52:$P$56,2,0),IF($A65=2026,VLOOKUP($E65,Premissas!$A$52:$P$56,3,0),VLOOKUP($E65,Premissas!$A$52:$P$56,4,0))) -> 0.32 | J65: =H65*(1-I65) -> 25284.216 | K65: =H65-J65 -> 11898.455 | L65: =SUMIFS(Headcount_Folha!$I:$I,Headcount_Folha!$C:$C,$C65,Headcount_Folha!$D:$D,$E65) -> 12768 | M65: =VLOOKUP($E65,Premissas!$A$52:$P$56,10,0)*(1+VLOOKUP($E65,Premissas!$A$52:$P$56,11,0))^($A65-2025) -> 3276.075 | N65: =H65*VLOOKUP($E65,Premissas!$A$52:$P$56,7,0) -> 743.65341 | O65: =H65*VLOOKUP($E65,Premissas!$A$52:$P$56,8,0) -> 1301.3935 | P65: =H65*VLOOKUP($E65,Premissas!$A$52:$P$56,9,0) -> 743.65341 | Q65: =K65-L65-M65-N65-O65-P65 -> -6934.3207
A66: 2027 | B66: 5 | C66: 2027-05 | D66: 46508 | E66: Utilidades Domesticas | F66: =F54*(1+VLOOKUP($E66,Premissas!$A$52:$P$56,6,0)) -> 82491.759 | G66: =F66*VLOOKUP($E66,Premissas!$A$52:$P$56,5,0) -> 28385.414 | H66: =F66-G66 -> 54106.345 | I66: =IF($A66=2025,VLOOKUP($E66,Premissas!$A$52:$P$56,2,0),IF($A66=2026,VLOOKUP($E66,Premissas!$A$52:$P$56,3,0),VLOOKUP($E66,Premissas!$A$52:$P$56,4,0))) -> 0.32 | J66: =H66*(1-I66) -> 36792.314 | K66: =H66-J66 -> 17314.03 | L66: =SUMIFS(Headcount_Folha!$I:$I,Headcount_Folha!$C:$C,$C66,Headcount_Folha!$D:$D,$E66) -> 12768 | M66: =VLOOKUP($E66,Premissas!$A$52:$P$56,10,0)*(1+VLOOKUP($E66,Premissas!$A$52:$P$56,11,0))^($A66-2025) -> 3276.075 | N66: =H66*VLOOKUP($E66,Premissas!$A$52:$P$56,7,0) -> 1082.1269 | O66: =H66*VLOOKUP($E66,Premissas!$A$52:$P$56,8,0) -> 1893.7221 | P66: =H66*VLOOKUP($E66,Premissas!$A$52:$P$56,9,0) -> 1082.1269 | Q66: =K66-L66-M66-N66-O66-P66 -> -2788.0205
A67: 2027 | B67: 6 | C67: 2027-06 | D67: 46539 | E67: Utilidades Domesticas | F67: =F55*(1+VLOOKUP($E67,Premissas!$A$52:$P$56,6,0)) -> 78591.135 | G67: =F67*VLOOKUP($E67,Premissas!$A$52:$P$56,5,0) -> 27043.21 | H67: =F67-G67 -> 51547.925 | I67: =IF($A67=2025,VLOOKUP($E67,Premissas!$A$52:$P$56,2,0),IF($A67=2026,VLOOKUP($E67,Premissas!$A$52:$P$56,3,0),VLOOKUP($E67,Premissas!$A$52:$P$56,4,0))) -> 0.32 | J67: =H67*(1-I67) -> 35052.589 | K67: =H67-J67 -> 16495.336 | L67: =SUMIFS(Headcount_Folha!$I:$I,Headcount_Folha!$C:$C,$C67,Headcount_Folha!$D:$D,$E67) -> 12768 | M67: =VLOOKUP($E67,Premissas!$A$52:$P$56,10,0)*(1+VLOOKUP($E67,Premissas!$A$52:$P$56,11,0))^($A67-2025) -> 3276.075 | N67: =H67*VLOOKUP($E67,Premissas!$A$52:$P$56,7,0) -> 1030.9585 | O67: =H67*VLOOKUP($E67,Premissas!$A$52:$P$56,8,0) -> 1804.1774 | P67: =H67*VLOOKUP($E67,Premissas!$A$52:$P$56,9,0) -> 1030.9585 | Q67: =K67-L67-M67-N67-O67-P67 -> -3414.8333
A68: 2027 | B68: 7 | C68: 2027-07 | D68: 46569 | E68: Utilidades Domesticas | F68: =F56*(1+VLOOKUP($E68,Premissas!$A$52:$P$56,6,0)) -> 89893.261 | G68: =F68*VLOOKUP($E68,Premissas!$A$52:$P$56,5,0) -> 30932.271 | H68: =F68-G68 -> 58960.99 | I68: =IF($A68=2025,VLOOKUP($E68,Premissas!$A$52:$P$56,2,0),IF($A68=2026,VLOOKUP($E68,Premissas!$A$52:$P$56,3,0),VLOOKUP($E68,Premissas!$A$52:$P$56,4,0))) -> 0.32 | J68: =H68*(1-I68) -> 40093.473 | K68: =H68-J68 -> 18867.517 | L68: =SUMIFS(Headcount_Folha!$I:$I,Headcount_Folha!$C:$C,$C68,Headcount_Folha!$D:$D,$E68) -> 12768 | M68: =VLOOKUP($E68,Premissas!$A$52:$P$56,10,0)*(1+VLOOKUP($E68,Premissas!$A$52:$P$56,11,0))^($A68-2025) -> 3276.075 | N68: =H68*VLOOKUP($E68,Premissas!$A$52:$P$56,7,0) -> 1179.2198 | O68: =H68*VLOOKUP($E68,Premissas!$A$52:$P$56,8,0) -> 2063.6347 | P68: =H68*VLOOKUP($E68,Premissas!$A$52:$P$56,9,0) -> 1179.2198 | Q68: =K68-L68-M68-N68-O68-P68 -> -1598.6324
A69: 2027 | B69: 8 | C69: 2027-08 | D69: 46600 | E69: Utilidades Domesticas | F69: =F57*(1+VLOOKUP($E69,Premissas!$A$52:$P$56,6,0)) -> 78995.028 | G69: =F69*VLOOKUP($E69,Premissas!$A$52:$P$56,5,0) -> 27182.189 | H69: =F69-G69 -> 51812.839 | I69: =IF($A69=2025,VLOOKUP($E69,Premissas!$A$52:$P$56,2,0),IF($A69=2026,VLOOKUP($E69,Premissas!$A$52:$P$56,3,0),VLOOKUP($E69,Premissas!$A$52:$P$56,4,0))) -> 0.32 | J69: =H69*(1-I69) -> 35232.73 | K69: =H69-J69 -> 16580.108 | L69: =SUMIFS(Headcount_Folha!$I:$I,Headcount_Folha!$C:$C,$C69,Headcount_Folha!$D:$D,$E69) -> 12768 | M69: =VLOOKUP($E69,Premissas!$A$52:$P$56,10,0)*(1+VLOOKUP($E69,Premissas!$A$52:$P$56,11,0))^($A69-2025) -> 3276.075 | N69: =H69*VLOOKUP($E69,Premissas!$A$52:$P$56,7,0) -> 1036.2568 | O69: =H69*VLOOKUP($E69,Premissas!$A$52:$P$56,8,0) -> 1813.4494 | P69: =H69*VLOOKUP($E69,Premissas!$A$52:$P$56,9,0) -> 1036.2568 | Q69: =K69-L69-M69-N69-O69-P69 -> -3349.9295
A70: 2027 | B70: 9 | C70: 2027-09 | D70: 46631 | E70: Utilidades Domesticas | F70: =F58*(1+VLOOKUP($E70,Premissas!$A$52:$P$56,6,0)) -> 94358.617 | G70: =F70*VLOOKUP($E70,Premissas!$A$52:$P$56,5,0) -> 32468.8 | H70: =F70-G70 -> 61889.817 | I70: =IF($A70=2025,VLOOKUP($E70,Premissas!$A$52:$P$56,2,0),IF($A70=2026,VLOOKUP($E70,Premissas!$A$52:$P$56,3,0),VLOOKUP($E70,Premissas!$A$52:$P$56,4,0))) -> 0.32 | J70: =H70*(1-I70) -> 42085.076 | K70: =H70-J70 -> 19804.742 | L70: =SUMIFS(Headcount_Folha!$I:$I,Headcount_Folha!$C:$C,$C70,Headcount_Folha!$D:$D,$E70) -> 12768 | M70: =VLOOKUP($E70,Premissas!$A$52:$P$56,10,0)*(1+VLOOKUP($E70,Premissas!$A$52:$P$56,11,0))^($A70-2025) -> 3276.075 | N70: =H70*VLOOKUP($E70,Premissas!$A$52:$P$56,7,0) -> 1237.7963 | O70: =H70*VLOOKUP($E70,Premissas!$A$52:$P$56,8,0) -> 2166.1436 | P70: =H70*VLOOKUP($E70,Premissas!$A$52:$P$56,9,0) -> 1237.7963 | Q70: =K70-L70-M70-N70-O70-P70 -> -881.06978
A71: 2027 | B71: 10 | C71: 2027-10 | D71: 46661 | E71: Utilidades Domesticas | F71: =F59*(1+VLOOKUP($E71,Premissas!$A$52:$P$56,6,0)) -> 60773.265 | G71: =F71*VLOOKUP($E71,Premissas!$A$52:$P$56,5,0) -> 20912.08 | H71: =F71-G71 -> 39861.185 | I71: =IF($A71=2025,VLOOKUP($E71,Premissas!$A$52:$P$56,2,0),IF($A71=2026,VLOOKUP($E71,Premissas!$A$52:$P$56,3,0),VLOOKUP($E71,Premissas!$A$52:$P$56,4,0))) -> 0.32 | J71: =H71*(1-I71) -> 27105.605 | K71: =H71-J71 -> 12755.579 | L71: =SUMIFS(Headcount_Folha!$I:$I,Headcount_Folha!$C:$C,$C71,Headcount_Folha!$D:$D,$E71) -> 12768 | M71: =VLOOKUP($E71,Premissas!$A$52:$P$56,10,0)*(1+VLOOKUP($E71,Premissas!$A$52:$P$56,11,0))^($A71-2025) -> 3276.075 | N71: =H71*VLOOKUP($E71,Premissas!$A$52:$P$56,7,0) -> 797.22369 | O71: =H71*VLOOKUP($E71,Premissas!$A$52:$P$56,8,0) -> 1395.1415 | P71: =H71*VLOOKUP($E71,Premissas!$A$52:$P$56,9,0) -> 797.22369 | Q71: =K71-L71-M71-N71-O71-P71 -> -6278.0848
A72: 2027 | B72: 11 | C72: 2027-11 | D72: 46692 | E72: Utilidades Domesticas | F72: =F60*(1+VLOOKUP($E72,Premissas!$A$52:$P$56,6,0)) -> 96389.087 | G72: =F72*VLOOKUP($E72,Premissas!$A$52:$P$56,5,0) -> 33167.485 | H72: =F72-G72 -> 63221.602 | I72: =IF($A72=2025,VLOOKUP($E72,Premissas!$A$52:$P$56,2,0),IF($A72=2026,VLOOKUP($E72,Premissas!$A$52:$P$56,3,0),VLOOKUP($E72,Premissas!$A$52:$P$56,4,0))) -> 0.32 | J72: =H72*(1-I72) -> 42990.689 | K72: =H72-J72 -> 20230.913 | L72: =SUMIFS(Headcount_Folha!$I:$I,Headcount_Folha!$C:$C,$C72,Headcount_Folha!$D:$D,$E72) -> 12768 | M72: =VLOOKUP($E72,Premissas!$A$52:$P$56,10,0)*(1+VLOOKUP($E72,Premissas!$A$52:$P$56,11,0))^($A72-2025) -> 3276.075 | N72: =H72*VLOOKUP($E72,Premissas!$A$52:$P$56,7,0) -> 1264.432 | O72: =H72*VLOOKUP($E72,Premissas!$A$52:$P$56,8,0) -> 2212.7561 | P72: =H72*VLOOKUP($E72,Premissas!$A$52:$P$56,9,0) -> 1264.432 | Q72: =K72-L72-M72-N72-O72-P72 -> -554.78255
A73: 2027 | B73: 12 | C73: 2027-12 | D73: 46722 | E73: Utilidades Domesticas | F73: =F61*(1+VLOOKUP($E73,Premissas!$A$52:$P$56,6,0)) -> 109361.52 | G73: =F73*VLOOKUP($E73,Premissas!$A$52:$P$56,5,0) -> 37631.3 | H73: =F73-G73 -> 71730.222 | I73: =IF($A73=2025,VLOOKUP($E73,Premissas!$A$52:$P$56,2,0),IF($A73=2026,VLOOKUP($E73,Premissas!$A$52:$P$56,3,0),VLOOKUP($E73,Premissas!$A$52:$P$56,4,0))) -> 0.32 | J73: =H73*(1-I73) -> 48776.551 | K73: =H73-J73 -> 22953.671 | L73: =SUMIFS(Headcount_Folha!$I:$I,Headcount_Folha!$C:$C,$C73,Headcount_Folha!$D:$D,$E73) -> 12768 | M73: =VLOOKUP($E73,Premissas!$A$52:$P$56,10,0)*(1+VLOOKUP($E73,Premissas!$A$52:$P$56,11,0))^($A73-2025) -> 3276.075 | N73: =H73*VLOOKUP($E73,Premissas!$A$52:$P$56,7,0) -> 1434.6044 | O73: =H73*VLOOKUP($E73,Premissas!$A$52:$P$56,8,0) -> 2510.5578 | P73: =H73*VLOOKUP($E73,Premissas!$A$52:$P$56,9,0) -> 1434.6044 | Q73: =K73-L73-M73-N73-O73-P73 -> 1529.8294
A74: 2025 | B74: 1 | C74: 2025-01 | D74: 45658 | E74: Papelaria e Impressao | F74: 29815.71 | G74: 13014.17 | H74: =F74-G74 -> 16801.54 | I74: =IF($A74=2025,VLOOKUP($E74,Premissas!$A$52:$P$56,2,0),IF($A74=2026,VLOOKUP($E74,Premissas!$A$52:$P$56,3,0),VLOOKUP($E74,Premissas!$A$52:$P$56,4,0))) -> 0.42 | J74: =H74*(1-I74) -> 9744.8932 | K74: =H74-J74 -> 7056.6468 | L74: =SUMIFS(Headcount_Folha!$I:$I,Headcount_Folha!$C:$C,$C74,Headcount_Folha!$D:$D,$E74) -> 3360 | M74: =VLOOKUP($E74,Premissas!$A$52:$P$56,10,0)*(1+VLOOKUP($E74,Premissas!$A$52:$P$56,11,0))^($A74-2025) -> 1000 | N74: =H74*VLOOKUP($E74,Premissas!$A$52:$P$56,7,0) -> 420.0385 | O74: =H74*VLOOKUP($E74,Premissas!$A$52:$P$56,8,0) -> 336.0308 | P74: =H74*VLOOKUP($E74,Premissas!$A$52:$P$56,9,0) -> 420.0385 | Q74: =K74-L74-M74-N74-O74-P74 -> 1520.539
A75: 2025 | B75: 2 | C75: 2025-02 | D75: 45689 | E75: Papelaria e Impressao | F75: 5390.37 | G75: 2009.84 | H75: =F75-G75 -> 3380.53 | I75: =IF($A75=2025,VLOOKUP($E75,Premissas!$A$52:$P$56,2,0),IF($A75=2026,VLOOKUP($E75,Premissas!$A$52:$P$56,3,0),VLOOKUP($E75,Premissas!$A$52:$P$56,4,0))) -> 0.42 | J75: =H75*(1-I75) -> 1960.7074 | K75: =H75-J75 -> 1419.8226 | L75: =SUMIFS(Headcount_Folha!$I:$I,Headcount_Folha!$C:$C,$C75,Headcount_Folha!$D:$D,$E75) -> 3360 | M75: =VLOOKUP($E75,Premissas!$A$52:$P$56,10,0)*(1+VLOOKUP($E75,Premissas!$A$52:$P$56,11,0))^($A75-2025) -> 1000 | N75: =H75*VLOOKUP($E75,Premissas!$A$52:$P$56,7,0) -> 84.51325 | O75: =H75*VLOOKUP($E75,Premissas!$A$52:$P$56,8,0) -> 67.6106 | P75: =H75*VLOOKUP($E75,Premissas!$A$52:$P$56,9,0) -> 84.51325 | Q75: =K75-L75-M75-N75-O75-P75 -> -3176.8145
A76: 2025 | B76: 3 | C76: 2025-03 | D76: 45717 | E76: Papelaria e Impressao | F76: 9085.57 | G76: 3714.9 | H76: =F76-G76 -> 5370.67 | I76: =IF($A76=2025,VLOOKUP($E76,Premissas!$A$52:$P$56,2,0),IF($A76=2026,VLOOKUP($E76,Premissas!$A$52:$P$56,3,0),VLOOKUP($E76,Premissas!$A$52:$P$56,4,0))) -> 0.42 | J76: =H76*(1-I76) -> 3114.9886 | K76: =H76-J76 -> 2255.6814 | L76: =SUMIFS(Headcount_Folha!$I:$I,Headcount_Folha!$C:$C,$C76,Headcount_Folha!$D:$D,$E76) -> 3360 | M76: =VLOOKUP($E76,Premissas!$A$52:$P$56,10,0)*(1+VLOOKUP($E76,Premissas!$A$52:$P$56,11,0))^($A76-2025) -> 1000 | N76: =H76*VLOOKUP($E76,Premissas!$A$52:$P$56,7,0) -> 134.26675 | O76: =H76*VLOOKUP($E76,Premissas!$A$52:$P$56,8,0) -> 107.4134 | P76: =H76*VLOOKUP($E76,Premissas!$A$52:$P$56,9,0) -> 134.26675 | Q76: =K76-L76-M76-N76-O76-P76 -> -2480.2655
A77: 2025 | B77: 4 | C77: 2025-04 | D77: 45748 | E77: Papelaria e Impressao | F77: 8866.3 | G77: 3636.28 | H77: =F77-G77 -> 5230.02 | I77: =IF($A77=2025,VLOOKUP($E77,Premissas!$A$52:$P$56,2,0),IF($A77=2026,VLOOKUP($E77,Premissas!$A$52:$P$56,3,0),VLOOKUP($E77,Premissas!$A$52:$P$56,4,0))) -> 0.42 | J77: =H77*(1-I77) -> 3033.4116 | K77: =H77-J77 -> 2196.6084 | L77: =SUMIFS(Headcount_Folha!$I:$I,Headcount_Folha!$C:$C,$C77,Headcount_Folha!$D:$D,$E77) -> 3360 | M77: =VLOOKUP($E77,Premissas!$A$52:$P$56,10,0)*(1+VLOOKUP($E77,Premissas!$A$52:$P$56,11,0))^($A77-2025) -> 1000 | N77: =H77*VLOOKUP($E77,Premissas!$A$52:$P$56,7,0) -> 130.7505 | O77: =H77*VLOOKUP($E77,Premissas!$A$52:$P$56,8,0) -> 104.6004 | P77: =H77*VLOOKUP($E77,Premissas!$A$52:$P$56,9,0) -> 130.7505 | Q77: =K77-L77-M77-N77-O77-P77 -> -2529.493
A78: 2025 | B78: 5 | C78: 2025-05 | D78: 45778 | E78: Papelaria e Impressao | F78: 7839.01 | G78: 2648.58 | H78: =F78-G78 -> 5190.43 | I78: =IF($A78=2025,VLOOKUP($E78,Premissas!$A$52:$P$56,2,0),IF($A78=2026,VLOOKUP($E78,Premissas!$A$52:$P$56,3,0),VLOOKUP($E78,Premissas!$A$52:$P$56,4,0))) -> 0.42 | J78: =H78*(1-I78) -> 3010.4494 | K78: =H78-J78 -> 2179.9806 | L78: =SUMIFS(Headcount_Folha!$I:$I,Headcount_Folha!$C:$C,$C78,Headcount_Folha!$D:$D,$E78) -> 3360 | M78: =VLOOKUP($E78,Premissas!$A$52:$P$56,10,0)*(1+VLOOKUP($E78,Premissas!$A$52:$P$56,11,0))^($A78-2025) -> 1000 | N78: =H78*VLOOKUP($E78,Premissas!$A$52:$P$56,7,0) -> 129.76075 | O78: =H78*VLOOKUP($E78,Premissas!$A$52:$P$56,8,0) -> 103.8086 | P78: =H78*VLOOKUP($E78,Premissas!$A$52:$P$56,9,0) -> 129.76075 | Q78: =K78-L78-M78-N78-O78-P78 -> -2543.3495
A79: 2025 | B79: 6 | C79: 2025-06 | D79: 45809 | E79: Papelaria e Impressao | F79: 6734.89 | G79: 2484.52 | H79: =F79-G79 -> 4250.37 | I79: =IF($A79=2025,VLOOKUP($E79,Premissas!$A$52:$P$56,2,0),IF($A79=2026,VLOOKUP($E79,Premissas!$A$52:$P$56,3,0),VLOOKUP($E79,Premissas!$A$52:$P$56,4,0))) -> 0.42 | J79: =H79*(1-I79) -> 2465.2146 | K79: =H79-J79 -> 1785.1554 | L79: =SUMIFS(Headcount_Folha!$I:$I,Headcount_Folha!$C:$C,$C79,Headcount_Folha!$D:$D,$E79) -> 3360 | M79: =VLOOKUP($E79,Premissas!$A$52:$P$56,10,0)*(1+VLOOKUP($E79,Premissas!$A$52:$P$56,11,0))^($A79-2025) -> 1000 | N79: =H79*VLOOKUP($E79,Premissas!$A$52:$P$56,7,0) -> 106.25925 | O79: =H79*VLOOKUP($E79,Premissas!$A$52:$P$56,8,0) -> 85.0074 | P79: =H79*VLOOKUP($E79,Premissas!$A$52:$P$56,9,0) -> 106.25925 | Q79: =K79-L79-M79-N79-O79-P79 -> -2872.3705
A80: 2025 | B80: 7 | C80: 2025-07 | D80: 45839 | E80: Papelaria e Impressao | F80: 5488.76 | G80: 1974.87 | H80: =F80-G80 -> 3513.89 | I80: =IF($A80=2025,VLOOKUP($E80,Premissas!$A$52:$P$56,2,0),IF($A80=2026,VLOOKUP($E80,Premissas!$A$52:$P$56,3,0),VLOOKUP($E80,Premissas!$A$52:$P$56,4,0))) -> 0.42 | J80: =H80*(1-I80) -> 2038.0562 | K80: =H80-J80 -> 1475.8338 | L80: =SUMIFS(Headcount_Folha!$I:$I,Headcount_Folha!$C:$C,$C80,Headcount_Folha!$D:$D,$E80) -> 3360 | M80: =VLOOKUP($E80,Premissas!$A$52:$P$56,10,0)*(1+VLOOKUP($E80,Premissas!$A$52:$P$56,11,0))^($A80-2025) -> 1000 | N80: =H80*VLOOKUP($E80,Premissas!$A$52:$P$56,7,0) -> 87.84725 | O80: =H80*VLOOKUP($E80,Premissas!$A$52:$P$56,8,0) -> 70.2778 | P80: =H80*VLOOKUP($E80,Premissas!$A$52:$P$56,9,0) -> 87.84725 | Q80: =K80-L80-M80-N80-O80-P80 -> -3130.1385
A81: 2025 | B81: 8 | C81: 2025-08 | D81: 45870 | E81: Papelaria e Impressao | F81: 5873.91 | G81: 2176.14 | H81: =F81-G81 -> 3697.77 | I81: =IF($A81=2025,VLOOKUP($E81,Premissas!$A$52:$P$56,2,0),IF($A81=2026,VLOOKUP($E81,Premissas!$A$52:$P$56,3,0),VLOOKUP($E81,Premissas!$A$52:$P$56,4,0))) -> 0.42 | J81: =H81*(1-I81) -> 2144.7066 | K81: =H81-J81 -> 1553.0634 | L81: =SUMIFS(Headcount_Folha!$I:$I,Headcount_Folha!$C:$C,$C81,Headcount_Folha!$D:$D,$E81) -> 3360 | M81: =VLOOKUP($E81,Premissas!$A$52:$P$56,10,0)*(1+VLOOKUP($E81,Premissas!$A$52:$P$56,11,0))^($A81-2025) -> 1000 | N81: =H81*VLOOKUP($E81,Premissas!$A$52:$P$56,7,0) -> 92.44425 | O81: =H81*VLOOKUP($E81,Premissas!$A$52:$P$56,8,0) -> 73.9554 | P81: =H81*VLOOKUP($E81,Premissas!$A$52:$P$56,9,0) -> 92.44425 | Q81: =K81-L81-M81-N81-O81-P81 -> -3065.7805
A82: 2025 | B82: 9 | C82: 2025-09 | D82: 45901 | E82: Papelaria e Impressao | F82: 25549.5 | G82: 12054.81 | H82: =F82-G82 -> 13494.69 | I82: =IF($A82=2025,VLOOKUP($E82,Premissas!$A$52:$P$56,2,0),IF($A82=2026,VLOOKUP($E82,Premissas!$A$52:$P$56,3,0),VLOOKUP($E82,Premissas!$A$52:$P$56,4,0))) -> 0.42 | J82: =H82*(1-I82) -> 7826.9202 | K82: =H82-J82 -> 5667.7698 | L82: =SUMIFS(Headcount_Folha!$I:$I,Headcount_Folha!$C:$C,$C82,Headcount_Folha!$D:$D,$E82) -> 3360 | M82: =VLOOKUP($E82,Premissas!$A$52:$P$56,10,0)*(1+VLOOKUP($E82,Premissas!$A$52:$P$56,11,0))^($A82-2025) -> 1000 | N82: =H82*VLOOKUP($E82,Premissas!$A$52:$P$56,7,0) -> 337.36725 | O82: =H82*VLOOKUP($E82,Premissas!$A$52:$P$56,8,0) -> 269.8938 | P82: =H82*VLOOKUP($E82,Premissas!$A$52:$P$56,9,0) -> 337.36725 | Q82: =K82-L82-M82-N82-O82-P82 -> 363.1415
A83: 2025 | B83: 10 | C83: 2025-10 | D83: 45931 | E83: Papelaria e Impressao | F83: 6739.63 | G83: 2705.44 | H83: =F83-G83 -> 4034.19 | I83: =IF($A83=2025,VLOOKUP($E83,Premissas!$A$52:$P$56,2,0),IF($A83=2026,VLOOKUP($E83,Premissas!$A$52:$P$56,3,0),VLOOKUP($E83,Premissas!$A$52:$P$56,4,0))) -> 0.42 | J83: =H83*(1-I83) -> 2339.8302 | K83: =H83-J83 -> 1694.3598 | L83: =SUMIFS(Headcount_Folha!$I:$I,Headcount_Folha!$C:$C,$C83,Headcount_Folha!$D:$D,$E83) -> 3360 | M83: =VLOOKUP($E83,Premissas!$A$52:$P$56,10,0)*(1+VLOOKUP($E83,Premissas!$A$52:$P$56,11,0))^($A83-2025) -> 1000 | N83: =H83*VLOOKUP($E83,Premissas!$A$52:$P$56,7,0) -> 100.85475 | O83: =H83*VLOOKUP($E83,Premissas!$A$52:$P$56,8,0) -> 80.6838 | P83: =H83*VLOOKUP($E83,Premissas!$A$52:$P$56,9,0) -> 100.85475 | Q83: =K83-L83-M83-N83-O83-P83 -> -2948.0335
A84: 2025 | B84: 11 | C84: 2025-11 | D84: 45962 | E84: Papelaria e Impressao | F84: 5857.92 | G84: 2494.18 | H84: =F84-G84 -> 3363.74 | I84: =IF($A84=2025,VLOOKUP($E84,Premissas!$A$52:$P$56,2,0),IF($A84=2026,VLOOKUP($E84,Premissas!$A$52:$P$56,3,0),VLOOKUP($E84,Premissas!$A$52:$P$56,4,0))) -> 0.42 | J84: =H84*(1-I84) -> 1950.9692 | K84: =H84-J84 -> 1412.7708 | L84: =SUMIFS(Headcount_Folha!$I:$I,Headcount_Folha!$C:$C,$C84,Headcount_Folha!$D:$D,$E84) -> 3360 | M84: =VLOOKUP($E84,Premissas!$A$52:$P$56,10,0)*(1+VLOOKUP($E84,Premissas!$A$52:$P$56,11,0))^($A84-2025) -> 1000 | N84: =H84*VLOOKUP($E84,Premissas!$A$52:$P$56,7,0) -> 84.0935 | O84: =H84*VLOOKUP($E84,Premissas!$A$52:$P$56,8,0) -> 67.2748 | P84: =H84*VLOOKUP($E84,Premissas!$A$52:$P$56,9,0) -> 84.0935 | Q84: =K84-L84-M84-N84-O84-P84 -> -3182.691
A85: 2025 | B85: 12 | C85: 2025-12 | D85: 45992 | E85: Papelaria e Impressao | F85: 17367.67 | G85: 7824.35 | H85: =F85-G85 -> 9543.32 | I85: =IF($A85=2025,VLOOKUP($E85,Premissas!$A$52:$P$56,2,0),IF($A85=2026,VLOOKUP($E85,Premissas!$A$52:$P$56,3,0),VLOOKUP($E85,Premissas!$A$52:$P$56,4,0))) -> 0.42 | J85: =H85*(1-I85) -> 5535.1256 | K85: =H85-J85 -> 4008.1944 | L85: =SUMIFS(Headcount_Folha!$I:$I,Headcount_Folha!$C:$C,$C85,Headcount_Folha!$D:$D,$E85) -> 3360 | M85: =VLOOKUP($E85,Premissas!$A$52:$P$56,10,0)*(1+VLOOKUP($E85,Premissas!$A$52:$P$56,11,0))^($A85-2025) -> 1000 | N85: =H85*VLOOKUP($E85,Premissas!$A$52:$P$56,7,0) -> 238.583 | O85: =H85*VLOOKUP($E85,Premissas!$A$52:$P$56,8,0) -> 190.8664 | P85: =H85*VLOOKUP($E85,Premissas!$A$52:$P$56,9,0) -> 238.583 | Q85: =K85-L85-M85-N85-O85-P85 -> -1019.838
... A97: 2026 | B97: 12 | C97: 2026-12 | D97: 46357 | E97: Papelaria e Impressao | F97: 10594.57 | G97: 3894.75 | H97: =F97-G97 -> 6699.82 | I97: =IF($A97=2025,VLOOKUP($E97,Premissas!$A$52:$P$56,2,0),IF($A97=2026,VLOOKUP($E97,Premissas!$A$52:$P$56,3,0),VLOOKUP($E97,Premissas!$A$52:$P$56,4,0))) -> 0.42 | J97: =H97*(1-I97) -> 3885.8956 | K97: =H97-J97 -> 2813.9244 | L97: =SUMIFS(Headcount_Folha!$I:$I,Headcount_Folha!$C:$C,$C97,Headcount_Folha!$D:$D,$E97) -> 3360 | M97: =VLOOKUP($E97,Premissas!$A$52:$P$56,10,0)*(1+VLOOKUP($E97,Premissas!$A$52:$P$56,11,0))^($A97-2025) -> 1045 | N97: =H97*VLOOKUP($E97,Premissas!$A$52:$P$56,7,0) -> 167.4955 | O97: =H97*VLOOKUP($E97,Premissas!$A$52:$P$56,8,0) -> 133.9964 | P97: =H97*VLOOKUP($E97,Premissas!$A$52:$P$56,9,0) -> 167.4955 | Q97: =K97-L97-M97-N97-O97-P97 -> -2060.063
A98: 2027 | B98: 1 | C98: 2027-01 | D98: 46388 | E98: Papelaria e Impressao | F98: =F86*(1+VLOOKUP($E98,Premissas!$A$52:$P$56,6,0)) -> 29058.799 | G98: =F98*VLOOKUP($E98,Premissas!$A$52:$P$56,5,0) -> 11452.073 | H98: =F98-G98 -> 17606.726 | I98: =IF($A98=2025,VLOOKUP($E98,Premissas!$A$52:$P$56,2,0),IF($A98=2026,VLOOKUP($E98,Premissas!$A$52:$P$56,3,0),VLOOKUP($E98,Premissas!$A$52:$P$56,4,0))) -> 0.42 | J98: =H98*(1-I98) -> 10211.901 | K98: =H98-J98 -> 7394.8251 | L98: =SUMIFS(Headcount_Folha!$I:$I,Headcount_Folha!$C:$C,$C98,Headcount_Folha!$D:$D,$E98) -> 3360 | M98: =VLOOKUP($E98,Premissas!$A$52:$P$56,10,0)*(1+VLOOKUP($E98,Premissas!$A$52:$P$56,11,0))^($A98-2025) -> 1092.025 | N98: =H98*VLOOKUP($E98,Premissas!$A$52:$P$56,7,0) -> 440.16816 | O98: =H98*VLOOKUP($E98,Premissas!$A$52:$P$56,8,0) -> 352.13453 | P98: =H98*VLOOKUP($E98,Premissas!$A$52:$P$56,9,0) -> 440.16816 | Q98: =K98-L98-M98-N98-O98-P98 -> 1710.3292
A99: 2027 | B99: 2 | C99: 2027-02 | D99: 46419 | E99: Papelaria e Impressao | F99: =F87*(1+VLOOKUP($E99,Premissas!$A$52:$P$56,6,0)) -> 4183.41 | G99: =F99*VLOOKUP($E99,Premissas!$A$52:$P$56,5,0) -> 1648.6819 | H99: =F99-G99 -> 2534.7281 | I99: =IF($A99=2025,VLOOKUP($E99,Premissas!$A$52:$P$56,2,0),IF($A99=2026,VLOOKUP($E99,Premissas!$A$52:$P$56,3,0),VLOOKUP($E99,Premissas!$A$52:$P$56,4,0))) -> 0.42 | J99: =H99*(1-I99) -> 1470.1423 | K99: =H99-J99 -> 1064.5858 | L99: =SUMIFS(Headcount_Folha!$I:$I,Headcount_Folha!$C:$C,$C99,Headcount_Folha!$D:$D,$E99) -> 3360 | M99: =VLOOKUP($E99,Premissas!$A$52:$P$56,10,0)*(1+VLOOKUP($E99,Premissas!$A$52:$P$56,11,0))^($A99-2025) -> 1092.025 | N99: =H99*VLOOKUP($E99,Premissas!$A$52:$P$56,7,0) -> 63.368203 | O99: =H99*VLOOKUP($E99,Premissas!$A$52:$P$56,8,0) -> 50.694562 | P99: =H99*VLOOKUP($E99,Premissas!$A$52:$P$56,9,0) -> 63.368203 | Q99: =K99-L99-M99-N99-O99-P99 -> -3564.8702
A100: 2027 | B100: 3 | C100: 2027-03 | D100: 46447 | E100: Papelaria e Impressao | F100: =F88*(1+VLOOKUP($E100,Premissas!$A$52:$P$56,6,0)) -> 7493.156 | G100: =F100*VLOOKUP($E100,Premissas!$A$52:$P$56,5,0) -> 2953.0528 | H100: =F100-G100 -> 4540.1032 | I100: =IF($A100=2025,VLOOKUP($E100,Premissas!$A$52:$P$56,2,0),IF($A100=2026,VLOOKUP($E100,Premissas!$A$52:$P$56,3,0),VLOOKUP($E100,Premissas!$A$52:$P$56,4,0))) -> 0.42 | J100: =H100*(1-I100) -> 2633.2599 | K100: =H100-J100 -> 1906.8434 | L100: =SUMIFS(Headcount_Folha!$I:$I,Headcount_Folha!$C:$C,$C100,Headcount_Folha!$D:$D,$E100) -> 3360 | M100: =VLOOKUP($E100,Premissas!$A$52:$P$56,10,0)*(1+VLOOKUP($E100,Premissas!$A$52:$P$56,11,0))^($A100-2025) -> 1092.025 | N100: =H100*VLOOKUP($E100,Premissas!$A$52:$P$56,7,0) -> 113.50258 | O100: =H100*VLOOKUP($E100,Premissas!$A$52:$P$56,8,0) -> 90.802064 | P100: =H100*VLOOKUP($E100,Premissas!$A$52:$P$56,9,0) -> 113.50258 | Q100: =K100-L100-M100-N100-O100-P100 -> -2862.9889
